Workbook
Name Electric: Reference!$D$2:$D$2
Name Motor___Cooling: Reference!$C$2:$C$2
Name Packing: Reference!$A$1:$A$3
Name Plastic: Reference!$B$2:$B$3

Sheet Qm-ValidationPredict
B2: Which Quarter:
B3: 12
B4: For:
B5: Validation
B6: Overtime?
B7: {=INDIRECT("'Input_Q"&B3&"-Predict'!C8")} -> Overtime
B9: From last Quarter
B10: Decicion Point
B11: Prediction
B14: 1. Operation
B16: Cost Overview
B17: Plant | C17: 0 | E17: Note: Raw material cost including the shipping fee related to each part
B18: Research & Development | C18: =F19*F20 -> 135000 | E18: Operation Cost Datasheet | I18: Q3 Order | K18: Type | L18: Unit Cost+Shipping | M18: Climatizer unit cost | N18: Order cost
B19: Raw Material | C19: =N23 -> 0 | E19: R&D | F19: 15000 | G19: /unit | J19: Packing | K19: Premium | L19: =VLOOKUP($K$19,$E$24:F59,2,FALSE) -> 36 | M19: =L19*$F$25 -> 36 | N19: =M19*$F$24 -> 0
B20: Raw Material Storage Costs | C20: =C34*0.02*M24 -> 1136.0868 | F20: {=INDIRECT("'Input_Q"&B3&"-Predict'!C38")} -> 9 | I20: Decision | J20: Plastic | K20: Superplast | L20: =VLOOKUP($K$20,$E$25:F60,2,FALSE) -> 44.52 | M20: =L20*$F$28 -> 89.04 | N20: =M20*$F$24 -> 0
B21: Production Fixed Cost | C21: 280000 | E21: MachineryModel | J21: Motor & Cooling | K21: Freezpro | L21: =VLOOKUP($K$21,$E$26:F63,2,FALSE) -> 187.2 | M21: =L21*$F$38 -> 374.4 | N21: =M21*$F$24 -> 0
C22: =SUM(C17:C21) -> 416136.09 | E22: Model1 | F22: 1300000 | J22: Electric | K22: Proline | L22: =VLOOKUP($K$22,$E$21:F60,2,FALSE) -> 24.15 | M22: =L22*$F$51 -> 72.45 | N22: =M22*$F$24 -> 0
E23: Model2 | F23: 1500000 | I23: unit climatizer cost | M23: =SUM(M19:M22) -> 571.89 | N23: =SUM(N19:N22) -> 0
E24: Raw Material | F24: {=INDIRECT("'Input_Q"&B3&"-Predict'!C36")} -> 0 | G24: # of climatizer RM | I24: Unit Value | M24: =M23-M19 -> 535.89 | N24: =M24*F24 -> 0
B25: Productivity | C25: {=IF(B5="Validation",'Qm-ValidationPredict'!C30/'Qm-ValidationPredict'!C29,INDIRECT("'Input_Q"&B3&"-Predict'!C34"))} -> 0.97019957 | E25: Packing | F25: 1 | G25: unit/climatizer
E26: Standard | F26: 20
B27: Climatizer Stock | C27: =INDEX(Data_Stock!B2:N11,MATCH("Left Inventory",Data_Stock!B2:B11,0),MATCH(VALUE(B3-1),Data_Stock!B2:N2,0)) -> 90 | E27: Premium | F27: 36
B28: Raw Material Available | C28: =INDEX(Data_Stock!B2:N11,MATCH("Left",Data_Stock!B2:B11,0),MATCH(VALUE(B3-1),Data_Stock!B2:N2,0)) -> 1545 | E28: Plastic | F28: 2 | G28: unit/climatizer
B29: Planned Production | C29: {=INDIRECT("'Input_Q"&B3&"-Predict'!C33")} -> 1483.2 | E29: Plastinjet | F29: =(1+F31)*F30 -> 43.2
B30: =IF(B5="Validation","Actual Production","Predict Production") -> Actual Production | C30: =INDEX(Data_Stock!B2:N11,MATCH("Produced",Data_Stock!B2:B11,0),MATCH(VALUE(B3),Data_Stock!B2:N2,0)) -> 1439 | E30: material | F30: 40
E31: Shipping | F31: 0.08
B32: Raw Material Left | E32: Superplast | F32: =(1+F34)*F33 -> 44.52
B33: Raw Material Purchased | C33: =F24 -> 0 | E33: material | F33: 42
B34: Raw Material Available for Q+1 | C34: =IF(B5="Validation",INDEX(Data_Stock!B2:N11,MATCH("Left",Data_Stock!B2:B11,0),MATCH('Qm-ValidationPredict'!B3,Data_Stock!B2:N2,0)),C28+F24-C30) -> 106 | E34: Shipping | F34: 0.06
B35: Total Inventory Value | C35: =C34*M24 -> 56804.34 | E35: IPLM | F35: =(1+F37)*F36 -> 56.1
E36: material | F36: 55
E37: Shipping | F37: 0.02
E38: Moter&Cooling | F38: 2 | G38: unit/climatizer
E39: Motojister | F39: =(1+F41)*F40 -> 117.7
E40: material | F40: 110
E41: Shipping | F41: 0.07
E42: Motormaster | F42: =(1+F44)*F43 -> 186.3
E43: material | F43: 162
E44: Shipping | F44: 0.15
E45: InfinityParts | F45: =(1+F47)*F46 -> 193.6
E46: material | F46: 176
E47: Shipping | F47: 0.1
E48: Freezpro | F48: =(1+F50)*F49 -> 187.2
E49: material | F49: 180
E50: Shipping | F50: 0.04
E51: ElectrocalKit | F51: 3 | G51: unit/climatizer
E52: Chukchuk | F52: =(1+F54)*F53 -> 21.6
E53: material | F53: 18
E54: Shipping | F54: 0.2
E55: ConduiteElec | F55: =(1+F57)*F56 -> 22
E56: material | F56: 20
E57: Shipping | F57: 0.1
E58: Proline | F58: =(1+F60)*F59 -> 24.15
E59: material | F59: 23
E60: Shipping | F60: 0.05
B65: 2. Market
B67: Cost Overview
B68: Sales Income | C68: =SUMPRODUCT(F73:I73,F71:I71) -> 3728892
B69: A&P Investiments | C69: =J75 -> 349088.82 | E69: =IF(B5="Validation","Actual S.C.R","Predict S.C.R") -> Actual S.C.R | F69: {=IF($B$5="Validation",F73/F72,INDIRECT("'Input_Q"&$B$3&"-Predict'!D29"))} -> 0.85562633 | G69: {=IF($B$5="Validation",G73/G72,INDIRECT("'Input_Q"&$B$3&"-Predict'!D30"))} -> 0.78651685 | H69: {=IF($B$5="Validation",H73/H72,INDIRECT("'Input_Q"&$B$3&"-Predict'!D31"))} -> 0.85106383 | I69: {=IF($B$5="Validation",I73/I72,INDIRECT("'Input_Q"&$B$3&"-Predict'!D32"))} -> 0.83121827
B70: Commision Total | C70: =C68*C74 -> 223733.52 | E70: Region | F70: 1 | G70: 2 | H70: 3 | I70: 4 | J70: Total
C71: =SUM(C68:C70) -> 4301714.3 | E71: Unit sale price | F71: {=INDIRECT("'Input_Q"&$B$3&"-Predict'!C10")} -> 2899 | G71: {=INDIRECT("'Input_Q"&$B$3&"-Predict'!C11")} -> 2599 | H71: {=INDIRECT("'Input_Q"&$B$3&"-Predict'!C12")} -> 2899 | I71: {=INDIRECT("'Input_Q"&$B$3&"-Predict'!C13")} -> 2899 | J71: /
E72: Planned Sale | F72: {=INDIRECT("'Input_Q"&$B$3&"-Predict'!C24")} -> 471 | G72: {=INDIRECT("'Input_Q"&$B$3&"-Predict'!C25")} -> 267 | H72: {=INDIRECT("'Input_Q"&$B$3&"-Predict'!C26")} -> 47 | I72: {=INDIRECT("'Input_Q"&$B$3&"-Predict'!C27")} -> 788 | J72: =Archived_Testing_Q5!B19 -> 1600
E73: =IF(B5="Validation","Actual Sale","Predict Sale") -> Actual Sale | F73: =IF($E$73="Actual Sale",INDEX(Data_Sales!$B$3:$N$8,MATCH(F70,Data_Sales!$B$3:$B$8,0),MATCH($B$3,Data_Sales!$B$3:$N$3,0)),ROUNDDOWN(F69*F72,0)) -> 403 | G73: =IF($E$73="Actual Sale",INDEX(Data_Sales!$B$3:$N$8,MATCH(G70,Data_Sales!$B$3:$B$8,0),MATCH($B$3,Data_Sales!$B$3:$N$3,0)),ROUNDDOWN(G69*G72,0)) -> 210 | H73: =IF($E$73="Actual Sale",INDEX(Data_Sales!$B$3:$N$8,MATCH(H70,Data_Sales!$B$3:$B$8,0),MATCH($B$3,Data_Sales!$B$3:$N$3,0)),ROUNDDOWN(H69*H72,0)) -> 40 | I73: =IF($E$73="Actual Sale",INDEX(Data_Sales!$B$3:$N$8,MATCH(I70,Data_Sales!$B$3:$B$8,0),MATCH($B$3,Data_Sales!$B$3:$N$3,0)),ROUNDDOWN(I69*I72,0)) -> 655 | J73: =SUM(F73:I73) -> 1308
B74: Commision | C74: {=INDIRECT("'Input_Q"&B3&"-Predict'!C39")} -> 0.06 | E74: Advertisement unit | F74: {=INDIRECT("'Input_Q"&$B$3&"-Predict'!C41")} -> 7 | G74: {=INDIRECT("'Input_Q"&$B$3&"-Predict'!C42")} -> 10 | H74: {=INDIRECT("'Input_Q"&$B$3&"-Predict'!C43")} -> 1 | I74: {=INDIRECT("'Input_Q"&$B$3&"-Predict'!C44")} -> 8
B75: Planned sale | C75: =J72 -> 1600 | E75: A&P Investment | F75: =F72*F71*F74/100 -> 95580.03 | G75: =G72*G71*G74/100 -> 69393.3 | H75: =H72*H71*H74/100 -> 1362.53 | I75: =I72*I71*I74/100 -> 182752.96 | J75: =SUM(F75:I75) -> 349088.82
B76: Predicted sale | C76: =J73 -> 1308 | E76: New Hired sales | F76: {=INDIRECT("'Input_Q"&$B$3&"-Predict'!C46")} -> 0 | G76: {=INDIRECT("'Input_Q"&$B$3&"-Predict'!C47")} -> 0 | H76: {=INDIRECT("'Input_Q"&$B$3&"-Predict'!C48")} -> 0 | I76: {=INDIRECT("'Input_Q"&$B$3&"-Predict'!C49")} -> 0 | J76: /
B77: left finished good | C77: =C75-C76 -> 292 | E77: Active Sales Force | F77: =INDEX(Data_EmployeeNumber!$A$4:$E$16,MATCH('Qm-ValidationPredict'!$B$3-1,Data_EmployeeNumber!$A$4:$A$16,0),MATCH('Qm-ValidationPredict'!F70,Data_EmployeeNumber!$A$4:$E$4,0))+'Qm-ValidationPredict'!F76 -> 3 | G77: =INDEX(Data_EmployeeNumber!$A$4:$E$16,MATCH('Qm-ValidationPredict'!$B$3-1,Data_EmployeeNumber!$A$4:$A$16,0),MATCH('Qm-ValidationPredict'!G70,Data_EmployeeNumber!$A$4:$E$4,0))+'Qm-ValidationPredict'!G76 -> 3 | H77: =INDEX(Data_EmployeeNumber!$A$4:$E$16,MATCH('Qm-ValidationPredict'!$B$3-1,Data_EmployeeNumber!$A$4:$A$16,0),MATCH('Qm-ValidationPredict'!H70,Data_EmployeeNumber!$A$4:$E$4,0))+'Qm-ValidationPredict'!H76 -> 1 | I77: =INDEX(Data_EmployeeNumber!$A$4:$E$16,MATCH('Qm-ValidationPredict'!$B$3-1,Data_EmployeeNumber!$A$4:$A$16,0),MATCH('Qm-ValidationPredict'!I70,Data_EmployeeNumber!$A$4:$E$4,0))+'Qm-ValidationPredict'!I76 -> 4 | J77: =SUM(F77:I77) -> 11
E78: Total Region Demand | J78: From Report
E79: Market Share by Region | J79: From Report
E80: Feight Cost | F80: 39.23 | G80: 0 | H80: 45.3 | I80: 57
B89: 3. Human Resource
B91: Cost Overview
B92: Salaries | C92: =I98 -> 304200 | E92: Base Salary | F92: {=INDIRECT("'Input_Q"&$B$3&"-Predict'!C50")} -> 5200 | H92: Base Salary | I92: salary per position | J92: Number of employee | K92: Multiplier | L92: Total For 1
B93: Training Investments | C93: =K103 -> 50000 | H93: Manager | I93: =$F$92*K93 -> 26000 | J93: 1 | K93: 5 | L93: =J93*K93 -> 5
B94: CSR. Investments | C94: =K104 -> 18000 | E94: Investment | H94: Operators | I94: =$F$92*K94 -> 5200 | J94: 35 | K94: 1 | L94: =J94*K94 -> 35
B95: Fringe Benefits Investments | C95: =K105 -> 47000 | E95: Training | F95: 10000 | H95: Supervisors | I95: =$F$92*K95 -> 13000 | J95: 3 | K95: 2.5 | L95: =J95*K95 -> 7.5
C96: =SUM(C92:C95) -> 419200 | E96: Unit | F96: {=INDIRECT("'Input_Q"&$B$3&"-Predict'!C51")} -> 5 | H96: Sellers | I96: =$F$92*K96 -> 5200 | J96: =J77 -> 11 | K96: 1 | L96: =J96*K96 -> 11
E97: CSR | F97: 2000 | H97: Total | I97: / | J97: =SUM(J93:J96) -> 50 | K97: / | L97: =SUM(L93:L96) -> 58.5
B98: Employee Satisfaction | E98: Unit | F98: {=INDIRECT("'Input_Q"&$B$3&"-Predict'!C52")} -> 9 | H98: Total Salary paid | I98: =L97*F92 -> 304200
H100: Other Investment and Expense
E101: Fringe Benefit | I101: Unit | J101: Number | K101: Total
E102: Dental | F102: 165 | H102: Salary | I102: =F92 -> 5200 | J102: =L97 -> 58.5 | K102: =I102*J102 -> 304200
E103: Food | F103: 175 | H103: Training | I103: =F95 -> 10000 | J103: =F96 -> 5 | K103: =F95*J103 -> 50000
E104: Tuition | F104: 400 | H104: CSR | I104: =F97 -> 2000 | J104: =F98 -> 9 | K104: =F97*J104 -> 18000
E105: Retirement | F105: 280 | H105: Fringe benefit | I105: =F102+F106+F107+F108 -> 940 | J105: =J97 -> 50 | K105: =I105*J105 -> 47000
E106: Medical | F106: 350 | K106: =SUM(K102:K105) -> 419200
E107: Life Insurance | F107: 135
E108: Transportation | F108: 290
B111: 4. Finance
B113: Contracted Loan | C113: 0
B114: Interest Rate | C114: 0
B115: Interest | C115: =C113*C114 -> 0
B116: Information Report Purchase | C116: {=INDIRECT("'Input_Q"&$B$3&"-Predict'!C53")} -> 150000
B120: Our income statement based on the predicted sales , not the planned sale
B123: Sales Income | C123: =IFERROR(VLOOKUP(B123,$B$14:$C$121,2,FALSE),0) -> 3728892
B124: COGS | C124: =IF(D124="Match",(C74+0.125)*C123+J73*M23,E124) -> 1437877.1 | D124: Match | E124: 996058.8 | G124: DL | I124: =H124/$H$128 -> 0
B125: Gross Profit and Loss | C125: =C123-C124 -> 2291014.9 | G125: FC | H125: =SUMIF(D127:D139,"FC",C127:C139) -> 1871624.9 | I125: =H125/$H$128 -> 1430.9059
G126: COGS | H126: =C124 -> 1437877.1 | I126: =H126/$H$128 -> 1099.2944
B127: Production Fixed Cost | C127: =IF(B7="Overtime",560000,280000) -> 560000 | D127: FC | G127: Full Cost | H127: =SUM(H124:H126) -> 3309502
B128: Salaries | C128: =IF(B7="Overtime",VALUE(IFERROR(VLOOKUP(B128,$B$14:$C$121,2,FALSE),0))*2,VALUE(IFERROR(VLOOKUP(B128,$B$14:$C$121,2,FALSE),0))) -> 608400 | D128: FC | G128: Unit Sold | H128: =C76 -> 1308
...

Sheet Archive-Input_Qm-Predict
C1: Preparasion for next quarter prediction
B2: TRUE | C2: 1. Validate data from previous quarter ( By QingQing)
B3: FALSE | C3: 2. Update Data_ Sheets( Need cash flow update By Seb)
B4: FALSE | C4: 3.Create new prediction sheet for new quarter+ Validation ( QingQing)
B5: FALSE | C5: 4. Choose the Number of current quarter in B6
B6: Quarter | C6: 7
B7: Strategy | C7: Maximum Capacity | E7: Note: Conservasive strategy have a constrain which will only keep the next quarter RM unit =1200
B8: Working Hour | C8: Overtime
B9: SalePrice
B10: 1 | C10: 2899
B11: 2 | C11: 2399
B12: 3 | C12: 2899
B13: 4 | C13: 2899
B14: NET PROFIT / LOSS | C14: {=INDIRECT("'Q"&C6&"-Predict'!C149")} -> 121140.48
B15: PROFIT AND LOSS STATEMENT RESULTS | C15: {=INDIRECT("'Q"&C6&"-Predict'!C154")} -> -470423.89
B17: Previous Quarter balance | C17: =INDEX(Data_IncomeStatement!A1:M33,MATCH("PROFIT AND LOSS STATEMENT RESULTS", Data_IncomeStatement!A1:A33, 0),MATCH(VALUE(C6-1), Data_IncomeStatement!A1:M1, 0)) -> -591564.37 | D17: DO NOT CHANGE THIS CELL!! | I17: Revenue | J17: Predicted sale*price
B18: Loan interest | C18: 0 | D18: C139 | E18: Given | I18: Price | J18: COGS
B19: Climatizer Stock | C19: =INDEX(Data_Stock!B2:N11,MATCH("Left Inventory",Data_Stock!B2:B11,0),MATCH(VALUE(C6-1),Data_Stock!B2:N2,0)) -> 25 | D19: DO NOT CHANGE THIS CELL!! | E19: Given | G19: =819+741-960 -> 600 | J19: 1. Predicted sale unit * raw material cost
B20: Raw Material Available | C20: =INDEX(Data_Stock!B2:N11,MATCH("Left",Data_Stock!B2:B11,0),MATCH(VALUE(C6-1),Data_Stock!B2:N2,0)) -> 1632 | D20: DO NOT CHANGE THIS CELL!! | E20: Given | J20: 2. Revenue *( Commision + 0.125)
B21: Maximum Sell unit | C21: =IF(C8="Overtime",MIN((1500*C34+C19),(C19+(C20*C34))),MIN((1200*C34+C19),(C19+(C20*C34)))) -> 1465
B22: Plan to Sell | C22: =C21 -> 1465 | E22: # Prediction based on the demand
B23: ="----------------------------------------------->>" -> ----------------------------------------------->> | C23: =MIN(C22,C21) -> 1465 | D23: DO NOT CHANGE THIS CELL!! | E23: #Capped by the maximum sell unit | J23: Fixed cost
B24: 1 | C24: =ROUNDDOWN($C$23*D24,0) -> 439 | D24: 0.3 | E24: # Plan to have more market share | J24: 1. 280000
B25: 2 | C25: =ROUNDDOWN($C$23*D25,0) -> 249 | D25: 0.17 | E25: # Focus | J25: 2. Loan Interest
B26: 3 | C26: =ROUNDDOWN($C$23*D26,0) -> 43 | D26: =1-D27-D25-D24 -> 0.03 | J26: 2. R&D investment
B27: 4 | C27: =ROUNDDOWN($C$23*D27,0) -> 732 | D27: 0.5 | E27: # Leader | J27: 3. Report to purchase
B28: Predicted Sale | C28: =SUM(C29:C32) -> 1014 | D28: Based on the predicted conversion rate | J28: 4. Raw material inventory (new purchase + left after production)
B29: 1 | C29: =ROUNDDOWN(C24*D29,0) -> 307 | D29: 0.7 | E29: 1613 | F29: =C29/E29 -> 0.19032858 | J29: 5. A&P
B30: 2 | C30: =ROUNDDOWN(C25*D30,0) -> 174 | D30: 0.7 | E30: 1094 | F30: =C30/E30 -> 0.15904936 | J30: 6. Total salary
B31: 3 | C31: =ROUNDDOWN(C26*D31,0) -> 21 | D31: 0.5 | E31: 1210 | F31: =C31/E31 -> 0.017355372
B32: 4 | C32: =ROUNDDOWN(C27*D32,0) -> 512 | D32: 0.7 | E32: 1843 | F32: =C32/E32 -> 0.27780792
B33: Plan to produce | C33: =C23-C19 -> 1440 | E33: # = plan to sale - finish good stock
B34: Productivity | C34: 0.96
B35: Predicted Produced | C35: =ROUNDDOWN(C33*C34,0) -> 1382
B36: Raw Material to purchase | C36: 1500
B37: ="------------------------------->" -> -------------------------------> | C37: =IF(C7="Conservasive",1200-(C20-C35),C36) -> 1500 | E37: # = 1200 - (Raw material available - real produce)
B38: R&D | C38: 9
B39: Commision | C39: 0.06
B40: Advertisement
B41: 1 | C41: 7 | D41: ='Q7-Predict'!F75 -> 89086.27
B42: 2 | C42: 9 | D42: ='Q7-Predict'!G75 -> 53761.59
B43: 3 | C43: 1 | D43: ='Q7-Predict'!H75 -> 1246.57
B44: 4 | C44: 7 | D44: ='Q7-Predict'!I75 -> 148544.76
B45: New Hire
B46: 1 | C46: 1
B47: 2 | C47: 0
B48: 3 | C48: -1
B49: 4 | C49: 0
B50: Base Salary | C50: 5200
B51: Training | C51: 7
B52: C&R | C52: 5
B53: Total information | C53: 80000 | D53: #Manually Calculate+input

Sheet Input_Qm-Predict
B1: Preparasion for next quarter prediction
B2: TRUE | C2: 1. Validate data from previous quarter ( By QingQing)
B3: FALSE | C3: 2. Update Data_ Sheets( Need cash flow update By Seb)
B4: FALSE | C4: 3.Create new prediction sheet for new quarter+ Validation ( QingQing)
B5: FALSE | C5: 4. Choose the Number of current quarter in B6
B6: Quarter | C6: 12
B7: Strategy | C7: Maximum Capacity | E7: Note: Conservative strategy have a constrain which will only keep the next quarter RM unit =1200
B8: Working Hour | C8: Overtime
B9: SalePrice | E9: Predicted Sale
B10: 1 | C10: 2899 | E10: =C28 -> 626
B11: 2 | C11: 2399 | E11: BreakEven unit
B12: 3 | C12: 2899 | E12: {=INDIRECT("'Q"&C6&"-Predict'!C165")} -> 1357
B13: 4 | C13: 2899 | E13: =IF(E12>E10,"Need Adjustment","All Good") -> Need Adjustment
B14: NET PROFIT / LOSS | C14: {=INDIRECT("'Q"&C6&"-Predict'!C149")} -> 71587.377
B15: PROFIT AND LOSS STATEMENT RESULTS | C15: {=INDIRECT("'Q"&C6&"-Predict'!C154")} -> 1998746.5
B17: Previous Quarter balance | C17: =INDEX(Data_IncomeStatement!A1:M33,MATCH("PROFIT AND LOSS STATEMENT RESULTS", Data_IncomeStatement!A1:A33, 0),MATCH(VALUE(C6-1), Data_IncomeStatement!A1:M1, 0)) -> 1927159.1 | E17: DO NOT CHANGE THIS CELL!!
B18: Loan interest | C18: 0 | E18: Given
B19: Climatizer Stock | C19: =INDEX(Data_Stock!B2:N11,MATCH("Left Inventory",Data_Stock!B2:B11,0),MATCH(VALUE(C6-1),Data_Stock!B2:N2,0)) -> 90 | E19: DO NOT CHANGE THIS CELL!!
B20: Raw Material Available | C20: =INDEX(Data_Stock!B2:N11,MATCH("Left",Data_Stock!B2:B11,0),MATCH(VALUE(C6-1),Data_Stock!B2:N2,0)) -> 1545 | E20: DO NOT CHANGE THIS CELL!!
B21: Maximum Sell unit | C21: =IF(C8="Overtime",MIN((1560*C34+C19),(C19+(C20*C34))),MIN((1200*C34+C19),(C19+(C20*C34)))) -> 1573.2
B22: Plan to Sell | C22: =C21 -> 1573.2 | E22: # Prediction based on the demand
B23: ="----------------------------------------------->>" -> ----------------------------------------------->> | C23: =MIN(C22,C21) -> 1573.2 | D23: Proportion | E23: #Capped by the maximum sell unit
B24: 1 | C24: =ROUNDDOWN($C$23*D24,0) -> 471 | D24: 0.3 | E24: # Plan to have more market share
B25: 2 | C25: =ROUNDDOWN($C$23*D25,0) -> 267 | D25: 0.17 | E25: # Focus
B26: 3 | C26: =ROUNDDOWN($C$23*D26,0) -> 47 | D26: =1-D27-D25-D24 -> 0.03
B27: 4 | C27: =ROUNDDOWN($C$23*D27,0) -> 786 | D27: 0.5 | E27: # Leader
B28: Predicted Sale | C28: =SUM(C29:C32) -> 626 | D28: Proportion | E28: #Based on the predicted conversion rate
B29: 1 | C29: =ROUNDDOWN(C24*D29,0) -> 188 | D29: 0.4
B30: 2 | C30: =ROUNDDOWN(C25*D30,0) -> 106 | D30: 0.4
B31: 3 | C31: =ROUNDDOWN(C26*D31,0) -> 18 | D31: 0.4
B32: 4 | C32: =ROUNDDOWN(C27*D32,0) -> 314 | D32: 0.4
B33: Plan to produce | C33: =C23-C19 -> 1483.2 | E33: # = plan to sale - finish good stock
B34: Productivity | C34: 0.96
B35: Predicted Produced | C35: =ROUNDDOWN(C33*C34,0) -> 1423
B36: Raw Material to purchase | C36: 1500
B37: ="------------------------------->" -> -------------------------------> | C37: =IF(C7="Conservasive",1200-(C20-C35),C36) -> 1500 | E37: # = 1200 - (Raw material available - real produce)
B38: R&D | C38: 9
B39: Commision | C39: 0.06
B40: Advertisement | C40: Level
B41: 1 | C41: 7
B42: 2 | C42: 9
B43: 3 | C43: 1
B44: 4 | C44: 7
B45: New Hire
B46: 1 | C46: 1
B47: 2 | C47: 0
B48: 3 | C48: -1
B49: 4 | C49: 0
B50: Base Salary | C50: 5200
B51: Training | C51: 7
B52: C&R | C52: 5
B53: Total information | C53: 80000 | E53: #Manually Calculate+input

Sheet Read Me
A1: The comprehensive manual can be found in the other document.
A3: Sheet Name | B3: Description
A4: Qm-ValidationPredict | B4: Template for Validation or Prediction
A5: Input_Qm-Predict | B5: Decision points input for prediction period
A6: DashBoard | B6: Overview performance--Income statement, market share, stock
A7: Reference | B7: Cell reference
A8: Pricing-Working
A9: Information-Working
A10: Data- | B10: Data Sheets Containing our Data Price, Sales, CashFlows, Stock, IS, Emp #.
A11: Q12-Validation | B11: Q# Validation Reports - Inputting Results
A12: Q12-Predict | B12: Q# Prediction Reports - Forecasted Results
A13: Input_Q12-Predict
A14: Q11-Validation
A15: Q11-Predict
A16: Input_Q11-Predict
A17: Input_Q10-Predict
A18: Q10-Validation
A19: Q10-Predict
A20: Q9-Validation
A21: Input_Q9-Predict
A22: Q9-Predict
A23: Q8-Validation
A24: Input_Q8-Predict
... A40: Q1-Data

Sheet Dashboard
B3: Sales Per Region | R3: Market Share Per Region - Purchased for Quarter 3 | AI3: Income Statements Per Quarter
B5: Sales | AZ5: Inventory Flow
C6: Q1 | D6: Q2 | E6: Q3 | F6: Q4 | G6: Q5 | H6: Q6 | I6: Q7 | J6: Q8 | K6: Q9 | L6: Q10 | M6: Q11 | N6: Q12 | V6: Market Share | W6: Region 1 | X6: Region 2 | Y6: Region 3 | Z6: Region 4 | AJ6: Q1 | AK6: Q2 | AL6: Q3 | AM6: Q4 | AN6: Q5 | AO6: Q6 | AP6: Q7 | AQ6: Q8 | AR6: Q9 | AS6: Q10 | AT6: Q11 | AU6: Q12 | AZ6: Raw Materials | BA6: Q1 | BB6: Q2 | BC6: Q3 | BD6: Q4 | BE6: Q5 | BF6: Q6 | BG6: Q7 | BH6: Q8 | BI6: Q9 | BJ6: Q10 | BK6: Q11 | BL6: Q12
B7: Region 1 | C7: 0 | D7: 50 | E7: 99 | F7: 210 | G7: 292 | H7: 150 | I7: 359 | J7: 264 | K7: 427 | L7: 484 | M7: 577 | N7: 403 | V7: EcoChill | W7: 0.5533 | X7: 0 | Y7: 0.1664 | Z7: 0.1392 | AI7: Sales Income | AJ7: ='Q1'!B90 -> 0 | AK7: ='Q2'!B111 -> 798556 | AL7: ='Q3-Validation'!C123 -> 1923112 | AM7: ='Q4-Validation'!C123 -> 1686105 | AN7: ='Q5-Validation'!C123 -> 3489303 | AO7: ='Q6-Validation'!$C$123 -> 2554023 | AP7: ='Q7-Validation'!C123 -> 3616316 | AQ7: ='Q8-Validation'!C123 -> 2792036 | AR7: ='Q9-Validation'!C123 -> 4158295 | AS7: ='Q10-Validation'!C123 -> 4562295 | AT7: ='Q11-Validation'!C123 -> 5265050 | AU7: ='Q12-Validation'!C123 -> 3728892 | AZ7: Used in Production | BA7: 0 | BB7: 1128 | BC7: 1134 | BD7: 1134 | BE7: 750 | BF7: 924 | BG7: 1382 | BH7: 1382 | BI7: 1498 | BJ7: 1498 | BK7: 1513 | BL7: 1439
B8: Region 2 | C8: 0 | D8: 103 | E8: 216 | F8: 79 | G8: 297 | H8: 301 | I8: 212 | J8: 198 | K8: 271 | L8: 302 | M8: 327 | N8: 210 | V8: EcoBreeze | W8: 0.1134 | X8: 0.3501 | Y8: 0.3103 | Z8: 0.5833 | AI8: COGS | AJ8: ='Q1'!B91 -> 0 | AK8: ='Q2'!B112 -> 423285.9 | AL8: ='Q3-Validation'!C124 -> 1045048.8 | AM8: ='Q4-Validation'!C124 -> 791550.97 | AN8: ='Q5-Validation'!C124 -> 1444533.1 | AO8: ='Q6-Validation'!$C$124 -> 996058.8 | AP8: ='Q7-Validation'!C124 -> 1357101.2 | AQ8: ='Q8-Validation'!C124 -> 1033124.6 | AR8: ='Q9-Validation'!C124 -> 1575799 | AS8: ='Q10-Validation'!C124 -> 1761908 | AT8: ='Q11-Validation'!C124 -> 1965430.8 | AU8: ='Q12-Validation'!C124 -> 1390789.1 | AZ8: Purchased | BA8: 1200 | BB8: 1200 | BC8: 1200 | BD8: 1062 | BE8: 675 | BF8: 1500 | BG8: 1500 | BH8: 1500 | BI8: 1560 | BJ8: 1560 | BK8: 1066 | BL8: 0
B9: Region 3 | C9: 0 | D9: 66 | E9: 207 | F9: 121 | G9: 117 | H9: 25 | I9: 39 | J9: 50 | K9: 48 | L9: 151 | M9: 57 | N9: 40 | V9: Loll | W9: 0.1523 | X9: 0.2334 | Y9: 0.1169 | Z9: 0.1619 | AI9: Gross Profit and Loss | AJ9: ='Q1'!B92 -> 0 | AK9: ='Q2'!B113 -> 375270.1 | AL9: ='Q3-Validation'!C125 -> 878063.22 | AM9: ='Q4-Validation'!C125 -> 894554.03 | AN9: ='Q5-Validation'!C125 -> 2044769.9 | AO9: ='Q6-Validation'!$C$125 -> 1557964.2 | AP9: ='Q7-Validation'!C125 -> 2259214.8 | AQ9: ='Q8-Validation'!C125 -> 1758911.4 | AR9: ='Q9-Validation'!C125 -> 2582496 | AS9: ='Q10-Validation'!C125 -> 2800387 | AT9: ='Q11-Validation'!C125 -> 3299619.2 | AU9: ='Q12-Validation'!C125 -> 2338102.9 | AZ9: Left | BA9: 1200 | BB9: =BB8+BA9-BB7 -> 1272 | BC9: =BC8+BB9-BC7 -> 1338 | BD9: =BD8+BC9-BD7 -> 1266 | BE9: =BE8+BD9-BE7 -> 1191 | BF9: =BF8+BE9-BF7 -> 1767 | BG9: =BG8+BF9-BG7 -> 1885 | BH9: =BH8+BG9-BH7 -> 2003 | BI9: =BI8+BH9-BI7 -> 2065 | ... BL9: =BL8+BK9-BL7 -> 241
B10: Region 4 | C10: 0 | D10: 325 | E10: 616 | F10: 485 | G10: 785 | H10: 501 | I10: 674 | J10: 452 | K10: 759 | L10: 668 | M10: 889 | N10: 655 | V10: NorthBreeze | W10: =1-SUM(W7:W9) -> 0.181 | X10: =1-SUM(X7:X9) -> 0.4165 | Y10: =1-SUM(Y7:Y9) -> 0.4064 | Z10: =1-SUM(Z7:Z9) -> 0.1156 | AZ10: Finished Goods
B11: Freight Cost | D11: 23490 | E11: 47968 | F11: 41370 | G11: 61890 | H11: 36058 | I11: 55012 | J11: 38776 | K11: 63022 | L11: 64144 | M11: 76922 | N11: 55710 | AI11: Production Fixed Cost | AJ11: ='Q1'!B94 -> 280000 | AK11: ='Q2'!B115 -> 280000 | AL11: ='Q3-Validation'!C127 -> 280000 | AM11: ='Q4-Validation'!C127 -> 280000 | AN11: ='Q5-Validation'!C127 -> 280000 | AO11: ='Q6-Validation'!$C$127 -> 280000 | AP11: ='Q7-Validation'!C127 -> 560000 | AQ11: ='Q8-Validation'!C127 -> 560000 | AR11: ='Q9-Validation'!C127 -> 560000 | AS11: ='Q10-Validation'!C127 -> 560000 | AT11: ='Q11-Validation'!C127 -> 560000 | AU11: ='Q12-Validation'!C127 -> 560000 | AZ11: Produced | BA11: =BA7 -> 0 | BB11: =BB7 -> 1128 | BC11: =BC7 -> 1134 | BD11: =BD7 -> 1134 | BE11: =BE7 -> 750 | BF11: =BF7 -> 924 | BG11: =BG7 -> 1382 | BH11: =BH7 -> 1382 | ... BL11: =BL7 -> 1439
AI12: Salaries | AJ12: ='Q1'!B95 -> 267500 | AK12: ='Q2'!B116 -> 272500 | AL12: ='Q3-Validation'!C128 -> 282500 | AM12: ='Q4-Validation'!C128 -> 287500 | AN12: ='Q5-Validation'!C128 -> 304200 | AO12: ='Q6-Validation'!$C$128 -> 304200 | AP12: ='Q7-Validation'!C128 -> 608400 | AQ12: ='Q8-Validation'!C128 -> 608400 | AR12: ='Q9-Validation'!C128 -> 608400 | AS12: ='Q10-Validation'!C128 -> 608400 | AT12: ='Q11-Validation'!C128 -> 608400 | AU12: ='Q12-Validation'!C128 -> 608400 | AZ12: Available to sell | BA12: 0 | BB12: =BA14+BB11 -> 1128 | BC12: =BB14+BC11 -> 1718 | BD12: =BC14+BD11 -> 1714 | BE12: 1600 | BF12: 1600 | BG12: 1600 | BH12: 1600 | BI12: 1600 | BJ12: 1600 | BK12: 1925 | BL12: 1573
AI13: Training Investments | AJ13: ='Q1'!B96 -> 20000 | AK13: ='Q2'!B117 -> 30000 | AL13: ='Q3-Validation'!C129 -> 40000 | AM13: ='Q4-Validation'!C129 -> 40000 | AN13: ='Q5-Validation'!C129 -> 70000 | AO13: ='Q6-Validation'!$C$129 -> 70000 | AP13: ='Q7-Validation'!C129 -> 70000 | AQ13: ='Q8-Validation'!C129 -> 70000 | AR13: ='Q9-Validation'!C129 -> 70000 | AS13: ='Q10-Validation'!C129 -> 70000 | AT13: ='Q11-Validation'!C129 -> 50000 | AU13: ='Q12-Validation'!C129 -> 50000 | AZ13: Sold | BA13: 0 | BB13: 544 | BC13: 1138 | BD13: 895 | BE13: 1491 | BF13: 977 | BG13: 1284 | BH13: 964 | BI13: 1505 | BJ13: 1605 | BK13: 1850 | BL13: 1308
AI14: Fringe Benefits Investments | AJ14: ='Q1'!B97 -> 52425 | AK14: ='Q2'!B118 -> 53590 | AL14: ='Q3-Validation'!C130 -> 55920 | AM14: ='Q4-Validation'!C130 -> 57085 | AN14: ='Q5-Validation'!C130 -> 47000 | AO14: ='Q6-Validation'!$C$130 -> 47000 | AP14: ='Q7-Validation'!C130 -> 47000 | AQ14: ='Q8-Validation'!C130 -> 47000 | AR14: ='Q9-Validation'!C130 -> 47000 | AS14: ='Q10-Validation'!C130 -> 47000 | AT14: ='Q11-Validation'!C130 -> 47000 | AU14: ='Q12-Validation'!C130 -> 47000 | AZ14: Left Inventory | BA14: =BA12-BA13 -> 0 | BB14: =BB12-BB13 -> 584 | BC14: =BC12-BC13 -> 580 | BD14: =BD12-BD13 -> 819 | BE14: =BE12-BE13 -> 109 | BF14: =BF12-BF13 -> 623 | BG14: =BG12-BG13 -> 316 | BH14: =BH12-BH13 -> 636 | ... BL14: =BL12-BL13 -> 265
AI15: CSR. Investments | AJ15: ='Q1'!B98 -> 4000 | AK15: ='Q2'!B119 -> 4000 | AL15: ='Q3-Validation'!C131 -> 8000 | AM15: ='Q4-Validation'!C131 -> 8000 | AN15: ='Q5-Validation'!C131 -> 10000 | AO15: ='Q6-Validation'!$C$131 -> 10000 | AP15: ='Q7-Validation'!C131 -> 10000 | AQ15: ='Q8-Validation'!C131 -> 10000 | AR15: ='Q9-Validation'!C131 -> 18000 | AS15: ='Q10-Validation'!C131 -> 18000 | AT15: ='Q11-Validation'!C131 -> 18000 | AU15: ='Q12-Validation'!C131 -> 18000
AI16: Profit Sharing Payment | AJ16: ='Q1'!B99 -> 0 | AK16: ='Q2'!B120 -> 0 | AL16: ='Q3-Validation'!C132 -> 0 | AM16: ='Q4-Validation'!C132 -> 0 | AN16: ='Q5-Validation'!C132 -> 0 | AO16: ='Q6-Validation'!$C$132 -> 0 | AP16: ='Q7-Validation'!C132 -> 0 | AQ16: ='Q8-Validation'!C132 -> 0 | AR16: ='Q9-Validation'!C132 -> 0 | AS16: ='Q10-Validation'!C132 -> 0 | AT16: ='Q11-Validation'!C132 -> 0 | AU16: ='Q12-Validation'!C132 -> 0
AI17: Research & Development | AJ17: ='Q1'!B100 -> 30000 | AK17: ='Q2'!B121 -> 45000 | AL17: ='Q3-Validation'!C133 -> 75000 | AM17: ='Q4-Validation'!C133 -> 75000 | AN17: ='Q5-Validation'!C133 -> 135000 | AO17: ='Q6-Validation'!$C$133 -> 135000 | AP17: ='Q7-Validation'!C133 -> 135000 | AQ17: ='Q8-Validation'!C133 -> 135000 | AR17: ='Q9-Validation'!C133 -> 135000 | AS17: ='Q10-Validation'!C133 -> 135000 | AT17: ='Q11-Validation'!C133 -> 135000 | AU17: ='Q12-Validation'!C133 -> 135000
AI18: A&P Investiments | AJ18: ='Q1'!B101 -> 0 | AK18: ='Q2'!B122 -> 72902.82 | AL18: ='Q3-Validation'!C134 -> 145921.76 | AM18: ='Q4-Validation'!C134 -> 165218.4 | AN18: ='Q5-Validation'!C134 -> 238537.6 | AO18: ='Q6-Validation'!$C$134 -> 190565.01 | AP18: ='Q7-Validation'!C134 -> 292639.19 | AQ18: ='Q8-Validation'!C134 -> 319567.59 | AR18: ='Q9-Validation'!C134 -> 427041.03 | AS18: ='Q10-Validation'!C134 -> 423771.62 | AT18: ='Q11-Validation'!C134 -> 427301.22 | AU18: ='Q12-Validation'!C134 -> 349088.82
AI19: Raw Material Storage Costs | AJ19: ='Q1'!B102 -> 12861.36 | AK19: ='Q2'!B123 -> 13633.042 | AL19: ='Q3-Validation'!C135 -> 14340.416 | AM19: ='Q4-Validation'!C135 -> 13568.735 | AN19: ='Q5-Validation'!C135 -> 11317.997 | AO19: ='Q6-Validation'!$C$135 -> 17491.45 | AP19: ='Q7-Validation'!C135 -> 18756.15 | AQ19: ='Q8-Validation'!C135 -> 20020.85 | AR19: ='Q9-Validation'!C135 -> 20685.354 | AS19: ='Q10-Validation'!C135 -> 21349.858 | AT19: ='Q11-Validation'!C135 -> 16559.001 | AU19: ='Q12-Validation'!C135 -> 1136.0868
AI20: Information Report Purchase | AJ20: ='Q1'!B103 -> 40000 | AK20: ='Q2'!B124 -> 80000 | AL20: ='Q3-Validation'!C136 -> 80000 | AM20: ='Q4-Validation'!C136 -> 80000 | AN20: ='Q5-Validation'!C136 -> 40000 | AO20: ='Q6-Validation'!$C$136 -> 40000 | AP20: ='Q7-Validation'!C136 -> 80000 | AQ20: ='Q8-Validation'!C136 -> 40000 | AR20: ='Q9-Validation'!C136 -> 80000 | AS20: ='Q10-Validation'!C136 -> 0 | AT20: ='Q11-Validation'!C136 -> 80000 | AU20: ='Q12-Validation'!C136 -> 150000
AI21: Freight Costs | AJ21: ='Q1'!B104 -> 0 | AK21: ='Q2'!B125 -> 23490 | AL21: ='Q3-Validation'!C137 -> 47968 | AM21: ='Q4-Validation'!C137 -> 41370 | AN21: ='Q5-Validation'!C137 -> 61890 | AO21: ='Q6-Validation'!$C$137 -> 36058 | AP21: ='Q7-Validation'!C137 -> 55012 | AQ21: ='Q8-Validation'!C137 -> 38776 | AR21: ='Q9-Validation'!C137 -> 63022 | AS21: ='Q10-Validation'!C137 -> 64144 | AT21: ='Q11-Validation'!C137 -> 76922 | AU21: ='Q12-Validation'!C137 -> 55710
AI22: Loss & Damage | AJ22: ='Q1'!B105 -> 0 | AK22: ='Q2'!B126 -> 0 | AL22: ='Q3-Validation'!C138 -> 0 | AM22: ='Q4-Validation'!C138 -> 0 | AN22: ='Q5-Validation'!C138 -> 0 | AO22: ='Q6-Validation'!$C$138 -> 0 | AP22: ='Q7-Validation'!C138 -> 0 | AQ22: ='Q8-Validation'!C138 -> 0 | AR22: ='Q9-Validation'!C138 -> 0 | AS22: ='Q10-Validation'!C138 -> 0 | AT22: ='Q11-Validation'!C138 -> 0 | AU22: ='Q12-Validation'!C138 -> 0
AI23: Loan Interest | AJ23: ='Q1'!B106 -> 0 | AK23: ='Q2'!B127 -> 0 | AL23: ='Q3-Validation'!C139 -> 24003.38 | AM23: ='Q4-Validation'!C139 -> 40253.36 | AN23: ='Q5-Validation'!C139 -> 116709.02 | AO23: ='Q6-Validation'!$C$139 -> 0 | AP23: ='Q7-Validation'!C139 -> 0 | AQ23: ='Q8-Validation'!C139 -> 0 | AR23: ='Q9-Validation'!C139 -> 0 | AS23: ='Q10-Validation'!C139 -> 0 | AT23: ='Q11-Validation'!C139 -> 0 | AU23: ='Q12-Validation'!C139 -> 0
AI24: Factoring Interest | AJ24: ='Q1'!B107 -> 0 | AK24: ='Q2'!B128 -> 0 | AL24: ='Q3-Validation'!C140 -> 0 | AM24: ='Q4-Validation'!C140 -> 0 | AN24: ='Q5-Validation'!C140 -> 0 | AO24: ='Q6-Validation'!$C$140 -> 0 | AP24: ='Q7-Validation'!C140 -> 0 | AQ24: ='Q8-Validation'!C140 -> 0 | AR24: ='Q9-Validation'!C140 -> 0 | AS24: ='Q10-Validation'!C140 -> 0 | AT24: ='Q11-Validation'!C140 -> 0 | AU24: ='Q12-Validation'!C140 -> 0
AI25: Decision Fine | AJ25: ='Q1'!B108 -> 0 | AK25: ='Q2'!B129 -> 0 | AL25: ='Q3-Validation'!C141 -> 0 | AM25: ='Q4-Validation'!C141 -> 0 | AN25: ='Q5-Validation'!C141 -> 0 | AO25: ='Q6-Validation'!$C$141 -> 0 | AP25: ='Q7-Validation'!C141 -> 0 | AQ25: ='Q8-Validation'!C141 -> 0 | AR25: ='Q9-Validation'!C141 -> 0 | AS25: ='Q10-Validation'!C141 -> 0 | AT25: ='Q11-Validation'!C141 -> 0 | AU25: ='Q12-Validation'!C141 -> 0
AI26: PROFIT & LOSS STATEMENT EXPENSES | AJ26: ='Q1'!B109 -> 706786.36 | AK26: ='Q2'!B130 -> 875115.86 | AL26: ='Q3-Validation'!C142 -> 1053653.6 | AM26: ='Q4-Validation'!C142 -> 1087995.5 | AN26: ='Q5-Validation'!C142 -> 1314654.6 | AO26: ='Q6-Validation'!$C$142 -> 1130314.5 | AP26: ='Q7-Validation'!C142 -> 1876807.3 | AQ26: ='Q8-Validation'!C142 -> 1848764.4 | AR26: ='Q9-Validation'!C142 -> 2029148.4 | AS26: ='Q10-Validation'!C142 -> 1947665.5 | AT26: ='Q11-Validation'!C142 -> 2019182.2 | AU26: ='Q12-Validation'!C142 -> 1974334.9
AI28: (+) Income savings | AJ28: ='Q1'!B111 -> 0 | AK28: ='Q2'!B132 -> 0 | AL28: ='Q3-Validation'!C144 -> 0 | AM28: ='Q4-Validation'!C144 -> 0 | AN28: ='Q5-Validation'!C144 -> 0 | AO28: ='Q6-Validation'!$C$144 -> 0 | AP28: ='Q7-Validation'!C144 -> 0 | AQ28: ='Q8-Validation'!C144 -> 0 | AR28: ='Q9-Validation'!C144 -> 0 | AS28: ='Q10-Validation'!C144 -> 0 | AT28: ='Q11-Validation'!C144 -> 0 | AU28: ='Q12-Validation'!C144 -> 0
AI29: (+) Bonus Value | AJ29: ='Q1'!B112 -> 0 | AK29: ='Q2'!B133 -> 0 | AL29: ='Q3-Validation'!C145 -> 0 | AM29: ='Q4-Validation'!C145 -> 0 | AN29: ='Q5-Validation'!C145 -> 0 | AO29: ='Q6-Validation'!$C$145 -> 0 | AP29: ='Q7-Validation'!C145 -> 0 | AQ29: ='Q8-Validation'!C145 -> 0 | AR29: ='Q9-Validation'!C145 -> 0 | AS29: ='Q10-Validation'!C145 -> 0 | AT29: ='Q11-Validation'!C145 -> 0 | AU29: ='Q12-Validation'!C145 -> 0
AI31: Pretax Income | AJ31: ='Q1'!B114 -> -706786.36 | AK31: ='Q2'!B135 -> -499845.76 | AL31: ='Q3-Validation'!C147 -> -175590.34 | AM31: ='Q4-Validation'!C147 -> -193441.46 | AN31: ='Q5-Validation'!C147 -> 730115.33 | AO31: ='Q6-Validation'!$C$147 -> 427649.74 | AP31: ='Q7-Validation'!C147 -> 382407.45 | AQ31: ='Q8-Validation'!C147 -> -89853.06 | AR31: ='Q9-Validation'!C147 -> 553347.61 | AS31: ='Q10-Validation'!C147 -> 852721.5 | AT31: ='Q11-Validation'!C147 -> 1280437 | AU31: ='Q12-Validation'!C147 -> 363767.96
AI32: (-) IR | AJ32: ='Q1'!B115 -> 0 | AK32: ='Q2'!B136 -> 0 | AL32: ='Q3-Validation'!C148 -> 0 | AM32: ='Q4-Validation'!C148 -> 0 | AN32: ='Q5-Validation'!C148 -> 109517.3 | AO32: ='Q6-Validation'!$C$148 -> 64147.461 | AP32: ='Q7-Validation'!C148 -> 57361.118 | AQ32: ='Q8-Validation'!C148 -> 0 | AR32: ='Q9-Validation'!C148 -> 83002.141 | AS32: ='Q10-Validation'!C148 -> 127908.22 | AT32: ='Q11-Validation'!C148 -> 192065.55 | AU32: ='Q12-Validation'!C148 -> 54565.194
AI33: NET PROFIT / LOSS | AJ33: ='Q1'!B116 -> -706786.36 | AK33: ='Q2'!B137 -> -499845.76 | AL33: ='Q3-Validation'!C149 -> -175590.34 | AM33: ='Q4-Validation'!C149 -> -193441.46 | AN33: ='Q5-Validation'!C149 -> 620598.03 | AO33: ='Q6-Validation'!$C$149 -> 363502.28 | AP33: ='Q7-Validation'!C149 -> 325046.33 | AQ33: ='Q8-Validation'!C149 -> -89853.06 | AR33: ='Q9-Validation'!C149 -> 470345.47 | AS33: ='Q10-Validation'!C149 -> 724813.27 | AT33: ='Q11-Validation'!C149 -> 1088371.5 | AU33: ='Q12-Validation'!C149 -> 309202.77
AI35: PREVIOUS QUARTER BALANCE | AJ35: ='Q1'!B118 -> 0 | AK35: ='Q2'!B139 -> -706786.36 | AL35: ='Q3-Validation'!C151 -> -1206632.1 | AM35: ='Q4-Validation'!C151 -> -1382222.5 | AN35: ='Q5-Validation'!C151 -> -1575663.9 | AO35: ='Q6-Validation'!$C$151 -> -955066.65 | AP35: ='Q7-Validation'!C151 -> -591564.37 | AQ35: ='Q8-Validation'!C151 -> -266518.04 | AR35: ='Q9-Validation'!C151 -> -356371.1 | AS35: ='Q10-Validation'!C151 -> 113974.37 | AT35: ='Q11-Validation'!C151 -> 838787.64 | AU35: ='Q12-Validation'!C151 -> 1927159.1
AI36: NET PROFIT / LOSS | AJ36: ='Q1'!B119 -> -706786.36 | AK36: ='Q2'!B140 -> -1206632.1 | AL36: ='Q3-Validation'!C152 -> -1382222.5 | AM36: ='Q4-Validation'!C152 -> -1575663.9 | AN36: ='Q5-Validation'!C152 -> -955065.89 | AO36: ='Q6-Validation'!$C$152 -> 363502.28 | AP36: ='Q7-Validation'!C152 -> 325046.33 | AQ36: ='Q8-Validation'!C152 -> -89853.06 | AR36: ='Q9-Validation'!C152 -> 470345.47 | AS36: ='Q10-Validation'!C152 -> 724813.27 | AT36: ='Q11-Validation'!C152 -> 1088371.5 | AU36: ='Q12-Validation'!C152 -> 309202.77
AI37: Fixed sale variation | AJ37: ='Q1'!B120 -> 0 | AK37: ='Q2'!B141 -> 0 | AL37: ='Q3-Validation'!C153 -> 0 | AM37: ='Q4-Validation'!C153 -> 0 | AN37: ='Q5-Validation'!C153 -> 0 | AO37: ='Q6-Validation'!$C$153 -> 0 | AP37: ='Q7-Validation'!C153 -> 0 | AQ37: ='Q8-Validation'!C153 -> 0 | AR37: ='Q9-Validation'!C153 -> 0 | AS37: ='Q10-Validation'!C153 -> 0 | AT37: ='Q11-Validation'!C153 -> 0 | AU37: ='Q12-Validation'!C153 -> 0
AI38: PROFIT AND LOSS STATEMENT RESULTS | AJ38: ='Q1'!B121 -> -706786.36 | AK38: ='Q2'!B142 -> -1206632.1 | AL38: ='Q3-Validation'!C154 -> -1382222.5 | AM38: ='Q4-Validation'!C154 -> -1575663.9 | AN38: ='Q5-Validation'!C154 -> -955065.89 | AO38: ='Q6-Validation'!$C$154 -> -591564.37 | AP38: ='Q7-Validation'!C154 -> -266518.04 | AQ38: ='Q8-Validation'!C154 -> -356371.1 | AR38: ='Q9-Validation'!C154 -> 113974.37 | AS38: ='Q10-Validation'!C154 -> 838787.64 | AT38: ='Q11-Validation'!C154 -> 1927159.1 | AU38: ='Q12-Validation'!C154 -> 2236361.9
X47: Market Share Per Region - Purchased for Quarter 7
V49: Market Share | W49: Region 1 | X49: Region 2 | Y49: Region 3 | Z49: Region 4
V50: EcoChill | W50: 0.3939 | X50: 0.1154 | Y50: 0.4008 | Z50: 0.073
V51: EcoBreeze | W51: 0.3509 | X51: 0.3178 | Y51: 0.0526 | Z51: 0.5861
V52: Loll | W52: 0.2121 | X52: 0.3388 | Y52: 0.3266 | Z52: 0.2835
V53: NorthBreeze | W53: 0.043 | X53: 0.2279 | Y53: =1-SUM(Y50:Y52) -> 0.22 | Z53: 0.0574
X92: Market Share Per Region - Purchased for Quarter 11
V94: Market Share | W94: Region 1 | X94: Region 2 | Y94: Region 3 | Z94: Region 4
V95: EcoChill | W95: 0.2921 | X95: 0.1008 | Y95: 0.3125 | Z95: 0.0969
V96: EcoBreeze | W96: 0.3442 | X96: 0.2679 | Y96: 0.0463 | Z96: 0.4921
V97: Loll | W97: 0.2442 | X97: 0.3355 | Y97: 0.3266 | Z97: 0.2412
V98: NorthBreeze | W98: 0.1196 | X98: 0.2959 | Y98: =1-SUM(Y95:Y97) -> 0.3146 | Z98: 0.1698

Sheet Reference
A1: Packing | B1: Plastic | C1: Motor & Cooling | D1: Electric
A2: Standard | B2: Plastinjet | C2: Motojister | D2: Chukchuk
A3: Premium | B3: Superplast | C3: Motormaster | D3: ConduiteElec
B4: IPLM | C4: InfinityParts | D4: Proline
C5: Freezpro
A6: Template
A7: Prediction
A8: Validation
A10: COGS
A11: Match
A12: Not Match
A14: Quarter
A15: 1
A16: 2
A17: 3
A18: 4
A19: 5
A20: 6
A21: 7
A22: 8
A23: 9
A24: 10
A25: 11
A26: 12
A28: Conservative
A29: Maximum Capacity
A31: Overtime
A32: Regular Hour

Sheet Information-Working
L2: 1 | M2: 2 | N2: 3 | O2: 4
K3: Q2
K4: EcoBreeze | L4: 1499 | M4: 1399 | N4: 1399 | O4: 1499
G5: Total | H5: conv | K5: EcoChill | L5: 1303 | N5: 1273
B6: Demand for Q2 spring | C6: 1344 | D6: 912 | E6: 1008 | F6: 1536 | G6: =SUM(C6:F6) -> 4800 | K6: LOLL | L6: 499 | M6: 469.99 | N6: 469.99 | O6: 499
B7: planned | C7: 150 | D7: 206 | E7: 100 | F7: 650 | G7: =SUM(C7:F7) -> 1106 | K7: NorthBreeze | L7: 999.99 | M7: 999.99 | N7: 949.99 | O7: 999.99
B8: sold | C8: 50 | D8: 103 | E8: 66 | F8: 325 | G8: =SUM(C8:F8) -> 544 | H8: =G8/G7 -> 0.49186257
B9: Conversion | C9: =C8/C7 -> 0.33333333 | D9: =D8/D7 -> 0.5 | E9: =E8/E7 -> 0.66 | F9: =F8/F7 -> 0.5 | G9: =G8/G7 -> 0.49186257 | K9: Average(EquallyPerInc.) | L9: =AVERAGE(L5:L7) -> 933.99667 | M9: =AVERAGE(M5:M7) -> 734.99 | N9: =AVERAGE(N5:N7) -> 897.66 | O9: =AVERAGE(O5:O7) -> 749.495
K10: UpperBound | L10: =L9*(1.3) -> 1214.1957 | M10: =M9*(1.3) -> 955.487 | N10: =N9*(1.3) -> 1166.958 | O10: =O9*(1.3) -> 974.3435 | S10: Conversion | T10: Variance | U10: Predicted variance
K11: LowerBound | L11: =L9*0.7 -> 653.79767 | M11: =M9*0.7 -> 514.493 | N11: =N9*0.7 -> 628.362 | O11: =O9*0.7 -> 524.6465 | R11: Q2 | S11: 0.33 | T11: 0.6 | U11: =-14.133*T11^4+28.203*T11^3-17.515*T11^2+2.9985*T11+0.704 -> 0.4579112
K12: % HigherThanUB | L12: =(L4-L10)/L10 -> 0.23456214 | M12: =(M4-M10)/M10 -> 0.46417481 | N12: =(N4-N10)/N10 -> 0.19884349 | O12: =(O4-O10)/O10 -> 0.5384718 | S12: 0.5 | T12: 0.9 | U12: =-14.133*T12^4+28.203*T12^3-17.515*T12^2+2.9985*T12+0.704 -> 0.5028257
K13: %HigherThanAverage | L13: =(L4-L9)/L9 -> 0.60493078 | M13: =(M4-M9)/M9 -> 0.90342726 | N13: =(N4-N9)/N9 -> 0.55849654 | O13: =(O4-O9)/O9 -> 1.0000133 | S13: 0.66 | T13: 0.56 | U13: =-14.133*T13^4+28.203*T13^3-17.515*T13^2+2.9985*T13+0.704 -> 0.45344473
S14: 0.5 | T14: 0.56 | U14: =-14.133*T14^4+28.203*T14^3-17.515*T14^2+2.9985*T14+0.704 -> 0.45344473
K15: Outcome of pricing : we got punished for being higher than 30% of the average market price. | R15: Q4 | S15: 0.51 | T15: 0.36 | U15: =-14.133*T15^4+28.203*T15^3-17.515*T15^2+2.9985*T15+0.704 -> 0.59197504
S16: 0.26 | T16: 0.39 | U16: =-14.133*T16^4+28.203*T16^3-17.515*T16^2+2.9985*T16+0.704 -> 0.55539864
S17: 0.61 | T17: 0.37 | U17: =-14.133*T17^4+28.203*T17^3-17.515*T17^2+2.9985*T17+0.704 -> 0.57933288
L18: 1 | M18: 2 | N18: 3 | O18: 4 | S18: 0.61 | T18: 0.36 | U18: =-14.133*T18^4+28.203*T18^3-17.515*T18^2+2.9985*T18+0.704 -> 0.59197504
B19: Demand in Q3-summer | C19: 1344 | D19: 912 | E19: 1008 | F19: 1536 | G19: =SUM(C19:F19) -> 4800 | K19: Q3 | R19: Q5 | S19: 0.91 | T19: 0.23 | U19: =-14.133*T19^4+28.203*T19^3-17.515*T19^2+2.9985*T19+0.704 -> 0.77070747
B20: planned | C20: 112 | D20: 300 | E20: 400 | F20: 900 | G20: =112+300+400+900 -> 1712 | K20: EcoBreeze | L20: 1699 | M20: 1699 | N20: 1649 | O20: 1699 | S20: 0.93 | T20: 0.04 | U20: =-14.133*T20^4+28.203*T20^3-17.515*T20^2+2.9985*T20+0.704 -> 0.79768481
B21: sold | C21: 99 | D21: 216 | E21: 207 | F21: 616 | G21: 1138 | H21: =G21/G20 -> 0.66471963 | S21: 0.73 | T21: 0.25 | U21: =-14.133*T21^4+28.203*T21^3-17.515*T21^2+2.9985*T21+0.704 -> 0.74440234
B22: Conversion | C22: =C21/C20 -> 0.88392857 | D22: =D21/D20 -> 0.72 | E22: =E21/E20 -> 0.5175 | F22: =F21/F20 -> 0.68444444 | G22: =G21/G20 -> 0.66471963 | S22: 0.98 | T22: 0.21 | U22: =-14.133*T22^4+28.203*T22^3-17.515*T22^2+2.9985*T22+0.704 -> 0.79497548
B23: Demand in Q4 -fall | C23: 1142 | D23: 775 | E23: 857 | F23: 1306 | G23: =SUM(C23:F23) -> 4080 | L23: 1 | M23: 2 | N23: 3 | O23: 4 | R23: Q6 | S23: 0.92 | T23: 0.22 | U23: =-14.133*T23^4+28.203*T23^3-17.515*T23^2+2.9985*T23+0.704 -> 0.78314214
B24: planned | C24: 414 | D24: 300 | E24: 200 | F24: 800 | G24: =SUM(C24:F24) -> 1714 | H24: 0.52 | K24: Q4 | S24: 0.92 | T24: 0.04 | U24: =-14.133*T24^4+28.203*T24^3-17.515*T24^2+2.9985*T24+0.704 -> 0.79768481
B25: sold | C25: 210 | D25: 79 | E25: 121 | F25: 485 | G25: =SUM(C25:F25) -> 895 | K25: EcoBreeze | L25: 1890 | M25: 1890 | N25: 1845 | O25: 1890 | S25: 0.46 | T25: 0.23 | U25: =-14.133*T25^4+28.203*T25^3-17.515*T25^2+2.9985*T25+0.704 -> 0.77070747
B26: Conversion | C26: =C25/C24 -> 0.50724638 | D26: =D25/D24 -> 0.26333333 | E26: =E25/E24 -> 0.605 | F26: =F25/F24 -> 0.60625 | G26: =G25/G24 -> 0.52217036 | K26: EcoChill | L26: 1179.98 | M26: 1179.98 | N26: 1149.98 | O26: 1189.98 | S26: 0.92 | T26: 0.2 | U26: =-14.133*T26^4+28.203*T26^3-17.515*T26^2+2.9985*T26+0.704 -> 0.8061112
K27: LOLL | L27: 1550 | M27: 1499 | N27: 1499 | O27: 1550 | R27: Q7 | S27: 0.82 | T27: 0.25 | U27: =-14.133*T27^4+28.203*T27^3-17.515*T27^2+2.9985*T27+0.704 -> 0.74440234
K28: NorthBreeze | L28: 1429 | M28: 1399 | N28: 1379 | O28: 1423.99 | S28: 0.85 | T28: 0.06 | U28: =-14.133*T28^4+28.203*T28^3-17.515*T28^2+2.9985*T28+0.704 -> 0.82676468
B29: My reasoning is that we need to increase publicity index in each area to get the highest conversion | S29: 0.91 | T29: 0.25 | U29: =-14.133*T29^4+28.203*T29^3-17.515*T29^2+2.9985*T29+0.704 -> 0.74440234
K30: Average(EquallyPerInc.) | L30: =AVERAGE(L26:L28) -> 1386.3267 | M30: =AVERAGE(M26:M28) -> 1359.3267 | N30: =AVERAGE(N26:N28) -> 1342.66 | O30: =AVERAGE(O26:O28) -> 1387.99 | S30: 0.92 | T30: 0.23 | U30: =-14.133*T30^4+28.203*T30^3-17.515*T30^2+2.9985*T30+0.704 -> 0.77070747
B31: My reasoning is that we need to double the intended planned sales to get the number we want in each area | K31: UpperBound | L31: =L30*(1.3) -> 1802.2247 | M31: =M30*(1.3) -> 1767.1247 | N31: =N30*(1.3) -> 1745.458 | O31: =O30*(1.3) -> 1804.387 | R31: Q8 | S31: 0.68 | T31: 0.28 | U31: =-14.133*T31^4+28.203*T31^3-17.515*T31^2+2.9985*T31+0.704 -> 0.70264692
K32: LowerBound | L32: =L30*0.7 -> 970.42867 | M32: =M30*0.7 -> 951.52867 | N32: =N30*0.7 -> 939.862 | O32: =O30*0.7 -> 971.593 | S32: 0.51 | T32: 0.09 | U32: =-14.133*T32^4+28.203*T32^3-17.515*T32^2+2.9985*T32+0.704 -> 0.85162622
K33: % HigherThanUB | L33: =(L25-L31)/L31 -> 0.04870388 | M33: =(M25-M31)/M31 -> 0.069534049 | N33: =(N25-N31)/N31 -> 0.057029158 | O33: =(O25-O31)/O31 -> 0.047447139 | S33: 0.63 | T33: 0.3 | U33: =-14.133*T33^4+28.203*T33^3-17.515*T33^2+2.9985*T33+0.704 -> 0.6742037
K34: %HigherThanAverage | L34: =(L25-L30)/L30 -> 0.36331504 | M34: =(M25-M30)/M30 -> 0.39039426 | N34: =(N25-N30)/N30 -> 0.37413791 | O34: =(O25-O30)/O30 -> 0.36168128 | S34: 0.64 | T34: 0.27 | U34: =-14.133*T34^4+28.203*T34^3-17.515*T34^2+2.9985*T34+0.704 -> 0.71676259 | W34: Conversion Optimization
R35: Q9 | S35: 0.78 | T35: 0.14 | U35: =-14.133*T35^4+28.203*T35^3-17.515*T35^2+2.9985*T35+0.704 -> 0.8524557 | X35: variance
L36: Still above the 30%: Try to be more conservative | S36: 0.81 | T36: 0.08 | U36: =-14.133*T36^4+28.203*T36^3-17.515*T36^2+2.9985*T36+0.704 -> 0.84564505 | W36: Optimal solution | X36: 0.11516998
S37: 0.81 | T37: 0.17 | U37: =-14.133*T37^4+28.203*T37^3-17.515*T37^2+2.9985*T37+0.704 -> 0.83431882
S38: 0.77 | T38: 0.14 | U38: =-14.133*T38^4+28.203*T38^3-17.515*T38^2+2.9985*T38+0.704 -> 0.8524557
L39: 1 | M39: 2 | N39: 3 | O39: 4 | R39: Q11 | S39: 0.79 | T39: 0.2 | U39: =-14.133*T39^4+28.203*T39^3-17.515*T39^2+2.9985*T39+0.704 -> 0.8061112 | W39: objective function-conversion | Y39: =-14.133*X36^4+28.203*X36^3-17.515*X36^2+2.9985*X36+0.704 -> 0.85761325
K40: Q5 | S40: 0.84 | T40: 0.1 | U40: =-14.133*T40^4+28.203*T40^3-17.515*T40^2+2.9985*T40+0.704 -> 0.8554897
K41: EcoBreeze | L41: 2450 | M41: 1899 | N41: 2450 | O41: 2450 | S41: 0.84 | T41: 0.22 | U41: =-14.133*T41^4+28.203*T41^3-17.515*T41^2+2.9985*T41+0.704 -> 0.78314214
K42: EcoChill | L42: 1500 | M42: 1450 | N42: 1500 | O42: 1600 | S42: 0.82 | T42: 0.14 | U42: =-14.133*T42^4+28.203*T42^3-17.515*T42^2+2.9985*T42+0.704 -> 0.8524557
B43: Demand for Q5-winter | C43: 941 | D43: 638 | E43: 706 | F43: 1075 | G43: =SUM(C43:F43) -> 3360 | K43: LOLL | L43: 2099 | M43: 1999 | N43: 1999 | O43: 2099 | R43: Q12 | S43: 0.86 | T43: 0.2 | U43: =-14.133*T43^4+28.203*T43^3-17.515*T43^2+2.9985*T43+0.704 -> 0.8061112
B44: planned | C44: 320 | D44: 320 | E44: 160 | F44: 800 | G44: =SUM(C44:F44) -> 1600 | K44: NorthBreeze | L44: 1949.99 | M44: 1949.99 | N44: 1899.99 | O44: 1949.99 | S44: 0.79 | T44: 0.1 | U44: =-14.133*T44^4+28.203*T44^3-17.515*T44^2+2.9985*T44+0.704 -> 0.8554897
B45: Ad for each region | C45: 7 | D45: 7 | E45: 1 | F45: 7 | S45: 0.85 | T45: 0.12 | U45: =-14.133*T45^4+28.203*T45^3-17.515*T45^2+2.9985*T45+0.704 -> 0.85740817
B46: sold | C46: 292 | D46: 297 | E46: 117 | F46: 785 | G46: =SUM(C46:F46) -> 1491 | H46: =G46/G44 -> 0.931875 | K46: Average(EquallyPerInc.) | L46: =AVERAGE(L41:L44) -> 1999.7475 | M46: =AVERAGE(M41:M44) -> 1824.4975 | N46: =AVERAGE(N41:N44) -> 1962.2475 | O46: =AVERAGE(O41:O44) -> 2024.7475 | S46: 0.83 | T46: 0.19 | U46: =-14.133*T46^4+28.203*T46^3-17.515*T46^2+2.9985*T46+0.704 -> 0.81644961
B47: Conversion per area | C47: =C46/C44 -> 0.9125 | D47: =D46/D44 -> 0.928125 | E47: =E46/E44 -> 0.73125 | F47: =F46/F44 -> 0.98125 | K47: UpperBound | L47: =L46*(1.3) -> 2599.6717 | M47: =M46*(1.3) -> 2371.8468 | N47: =N46*(1.3) -> 2550.9217 | O47: =O46*(1.3) -> 2632.1717
K48: LowerBound | L48: =L46*0.7 -> 1399.8232 | M48: =M46*0.7 -> 1277.1482 | N48: =N46*0.7 -> 1373.5732 | O48: =O46*0.7 -> 1417.3232
K49: % HigherThanUB | L49: =(L41-L47)/L47 -> -0.057573326 | M49: =(M41-M47)/M47 -> -0.19935805 | N49: =(N41-N47)/N47 -> -0.039562856 | O49: =(O41-O47)/O47 -> -0.069209674
K50: %HigherThanAverage | L50: =(L41-L46)/L46 -> 0.22515468 | M50: =(M41-M46)/M46 -> 0.040834531 | N50: =(N41-N46)/N46 -> 0.24856829 | O50: =(O41-O46)/O46 -> 0.21002742
K52: After the realazation that the pricing strategy is wrong we made an assumption that other teams will have to raise their price
L54: 1 | M54: 2 | N54: 3 | O54: 4
K55: Q6
B56: Demaand for Q6-Spring | C56: 1344 | D56: 912 | E56: 1008 | F56: 1536 | G56: =SUM(C56:F56) -> 4800 | K56: EcoBreeze | L56: 2799 | M56: 2199 | N56: 2799 | O56: 2799
B57: Planned | C57: 163 | D57: 327 | E57: 54 | F57: 545 | G57: =SUM(C57:F57) -> 1089 | K57: EcoChill | L57: 1999.98 | M57: 1949.98 | N57: 1999.98 | O57: 2099.98
B58: sold | C58: 150 | D58: 301 | E58: 25 | F58: 501 | G58: =SUM(C58:F58) -> 977 | H58: =G58/G57 -> 0.89715335 | K58: LOLL | L58: 2099.99 | M58: 1999 | N58: 1999.99 | O58: 2099.99
B59: Conversion per area | C59: =C58/C57 -> 0.9202454 | D59: =D58/D57 -> 0.9204893 | E59: =E58/E57 -> 0.46296296 | F59: =F58/F57 -> 0.91926606 | K59: NorthBreeze | L59: 2299.99 | M59: 2299.99 | N59: 2269.99 | O59: 2299.99
K61: Average(EquallyPerInc.) | L61: =AVERAGE(L56:L59) -> 2299.74 | M61: =AVERAGE(M56:M59) -> 2111.9925 | N61: =AVERAGE(N56:N59) -> 2267.24 | O61: =AVERAGE(O56:O59) -> 2324.74
K62: UpperBound | L62: =L61*(1.3) -> 2989.662 | M62: =M61*(1.3) -> 2745.5902 | N62: =N61*(1.3) -> 2947.412 | O62: =O61*(1.3) -> 3022.162
K63: LowerBound | L63: =L61*0.7 -> 1609.818 | M63: =M61*0.7 -> 1478.3947 | N63: =N61*0.7 -> 1587.068 | O63: =O61*0.7 -> 1627.318
K64: % HigherThanUB | L64: =(L56-L62)/L62 -> -0.063773764 | M64: =(M56-M62)/M62 -> -0.19907932 | N64: =(N56-N62)/N62 -> -0.050353327 | O64: =(O56-O62)/O62 -> -0.073841839
K65: %HigherThanAverage | L65: =(L56-L61)/L61 -> 0.21709411 | M65: =(M56-M61)/M61 -> 0.041196879 | N65: =(N56-N61)/N61 -> 0.23454068 | O65: =(O56-O61)/O61 -> 0.20400561
B68: Demand in Q7-summer | C68: 1344 | D68: 912 | E68: 1008 | F68: 1536 | G68: =SUM(C68:F68) -> 4800 | L68: 1 | M68: 2 | N68: 3 | O68: 4
B69: planned | C69: 439 | D69: 249 | E69: 43 | F69: 732 | G69: =SUM(C69:F69) -> 1463 | K69: Q7
B70: sold | C70: 359 | D70: 212 | E70: 39 | F70: 674 | G70: =SUM(C70:F70) -> 1284 | H70: =G70/G69 -> 0.87764867 | K70: EcoBreeze | L70: 2899 | M70: 2399 | N70: 2899 | O70: 2899
C71: =C70/C69 -> 0.81776765 | D71: =D70/D69 -> 0.85140562 | E71: =E70/E69 -> 0.90697674 | F71: =F70/F69 -> 0.92076503 | K71: EcoChill | L71: 2049 | M71: 1999.9 | N71: 2049 | O71: 2149.98
K72: LOLL | L72: 2299 | M72: 2199 | N72: 2299 | O72: 2299
K73: NorthBreeze | L73: 2599 | M73: 2599.99 | N73: 2599 | O73: 2599
K75: Average(EquallyPerInc.) | L75: =AVERAGE(L71:L73) -> 2315.6667 | M75: =AVERAGE(M71:M73) -> 2266.2967 | N75: =AVERAGE(N71:N73) -> 2315.6667 | O75: =AVERAGE(O71:O73) -> 2349.3267
K76: UpperBound | L76: =L75*(1.3) -> 3010.3667 | M76: =M75*(1.3) -> 2946.1857 | N76: =N75*(1.3) -> 3010.3667 | O76: =O75*(1.3) -> 3054.1247
K77: LowerBound | L77: =L75*0.7 -> 1620.9667 | M77: =M75*0.7 -> 1586.4077 | N77: =N75*0.7 -> 1620.9667 | O77: =O75*0.7 -> 1644.5287
K78: % HigherThanUB | L78: =(L70-L76)/L76 -> -0.036994386 | M78: =(M70-M76)/M76 -> -0.18572681 | N78: =(N70-N76)/N76 -> -0.036994386 | O78: =(O70-O76)/O76 -> -0.050791858
K79: %HigherThanAverage | L79: =(L70-L75)/L75 -> 0.2519073 | M79: =(M70-M75)/M75 -> 0.058555147 | N79: =(N70-N75)/N75 -> 0.2519073 | O79: =(O70-O75)/O75 -> 0.23397058
L83: 1 | M83: 2 | N83: 3 | O83: 4
B84: Demand in Q8 -fall | C84: 1142 | D84: 775 | E84: 857 | F84: 1306 | G84: =SUM(C84:F84) -> 4080 | K84: Q8
B85: planned | C85: 390 | D85: 390 | E85: 80 | F85: 703 | G85: =SUM(C85:F85) -> 1563 | K85: EcoBreeze | L85: 2999 | M85: 2499 | N85: 2999 | O85: 2999
B86: Sold | C86: 264 | D86: 198 | E86: 50 | F86: 452 | G86: =SUM(C86:F86) -> 964 | K86: EcoChill | L86: 2099.98 | M86: 2049.98 | N86: 2099.98 | O86: 2149.98
B87: Conversion | C87: =C86/C85 -> 0.67692308 | D87: =D86/D85 -> 0.50769231 | E87: =E86/E85 -> 0.625 | F87: =F86/F85 -> 0.64295875 | G87: =G86/G85 -> 0.61676264 | K87: LOLL | L87: 2699 | M87: 2599 | N87: 2599 | O87: 2699
K88: NorthBreeze | L88: 2249.99 | M88: 2249 | N88: 2229.99 | O88: 2249.99
K90: Average(EquallyPerInc.) | L90: =AVERAGE(L86:L88) -> 2349.6567 | M90: =AVERAGE(M86:M88) -> 2299.3267 | N90: =AVERAGE(N86:N88) -> 2309.6567 | O90: =AVERAGE(O86:O88) -> 2366.3233
K91: UpperBound | L91: =L90*(1.3) -> 3054.5537 | M91: =M90*(1.3) -> 2989.1247 | N91: =N90*(1.3) -> 3002.5537 | O91: =O90*(1.3) -> 3076.2203
K92: LowerBound | L92: =L90*0.7 -> 1644.7597 | M92: =M90*0.7 -> 1609.5287 | N92: =N90*0.7 -> 1616.7597 | O92: =O90*0.7 -> 1656.4263
K93: % HigherThanUB | L93: =(L85-L91)/L91 -> -0.018187163 | M93: =(M85-M91)/M91 -> -0.1639693 | N93: =(N85-N91)/N91 -> -0.0011835481 | O93: =(O85-O91)/O91 -> -0.025102341
K94: %HigherThanAverage | L94: =(L85-L90)/L90 -> 0.27635669 | M94: =(M85-M90)/M90 -> 0.086839915 | N94: =(N85-N90)/N90 -> 0.29846139 | O94: =(O85-O90)/O90 -> 0.26736696
B98: Demand for Q9~Q5 | C98: 941 | D98: 638 | E98: 706 | F98: 1075 | G98: =SUM(C98:F98) -> 3360 | L98: 1 | M98: 2 | N98: 3 | O98: 4
B99: Planned | C99: 549 | D99: 336 | E99: 59 | F99: 990 | G99: =SUM(C99:F99) -> 1934 | K99: Q9
B100: ad index | C100: 7 | D100: 10 | E100: 1 | F100: 7 | K100: EcoBreeze | L100: 2799 | M100: 2599 | N100: 2799 | O100: 2799
B101: sold | C101: 427 | D101: 271 | E101: 48 | F101: 759 | G101: =SUM(C101:F101) -> 1505 | K101: EcoChill | L101: 2149 | M101: 2099 | N101: 2149 | O101: 2199
B102: Conversion | C102: =C101/C99 -> 0.77777778 | D102: =D101/D99 -> 0.80654762 | E102: =E101/E99 -> 0.81355932 | F102: =F101/F99 -> 0.76666667 | G102: =G101/G99 -> 0.77817994 | K102: LOLL | L102: 2799 | M102: 2699 | N102: 2699 | O102: 2799
K103: NorthBreeze | L103: 2399 | M103: 2399 | N103: 2359 | O103: 2399
K105: Average(EquallyPerInc.) | L105: =AVERAGE(L101:L103) -> 2449 | M105: =AVERAGE(M101:M103) -> 2399 | N105: =AVERAGE(N101:N103) -> 2402.3333 | O105: =AVERAGE(O101:O103) -> 2465.6667
K106: UpperBound | L106: =L105*(1.3) -> 3183.7 | M106: =M105*(1.3) -> 3118.7 | N106: =N105*(1.3) -> 3123.0333 | O106: =O105*(1.3) -> 3205.3667
K107: LowerBound | L107: =L105*0.7 -> 1714.3 | M107: =M105*0.7 -> 1679.3 | N107: =N105*0.7 -> 1681.6333 | O107: =O105*0.7 -> 1725.9667
K108: % HigherThanUB | L108: =(L100-L106)/L106 -> -0.12083425 | M108: =(M100-M106)/M106 -> -0.16663995 | N108: =(N100-N106)/N106 -> -0.10375596 | O108: =(O100-O106)/O106 -> -0.12677697
K109: %HigherThanAverage | L109: =(L100-L105)/L105 -> 0.14291548 | M109: =(M100-M105)/M105 -> 0.08336807 | N109: =(N100-N105)/N105 -> 0.16511725 | O109: =(O100-O105)/O105 -> 0.13518994
L114: 1 | M114: 2 | N114: 3 | O114: 4
K115: Q10
B116: Demand for Q10~Q6 Spring | C116: 1344 | D116: 912 | E116: 1008 | F116: 1536 | G116: =SUM(C116:F116) -> 4800 | K116: EcoBreeze | L116: 2899 | M116: 2599 | N116: 2899 | O116: 2899
B117: Planned | C117: 609 | D117: 406 | E117: 203 | F117: 814 | G117: =SUM(C117:F117) -> 2032 | K117: EcoChill
B118: ad index | C118: 7 | D118: 10 | E118: 1 | F118: 8 | K118: LOLL | L118: Forgot to buy a report
B119: sold | C119: 484 | D119: 302 | E119: 151 | F119: 668 | G119: =SUM(C119:F119) -> 1605 | K119: NorthBreeze
...

Sheet Pricing-Working
M1: Quarter | N1: 2
A2: Planned to sell unit | B2: ='Input_Q9-Predict'!C28 -> 1335 | C2: 222.91667 | D2: Grey part is the price example of the cheapest raw material | I2: DL | J2: 222.91667 | K2: 222.91667 | M2: Sales Income | N2: 798556
C3: 414.25 | I3: RM | J3: 572 | K3: 414.25 | M3: COGS | N3: 423285.9
A4: Variable cost per unit | B4: =('Q9-Predict'!C124)/B2 -> 1083.6631 | C4: =SUM(C2:C3) -> 637.16667 | I4: total before tax | J4: =SUM(J2:J3) -> 794.91667 | K4: =SUM(K2:K3) -> 637.16667 | M4: Gross Profit and Loss | N4: 375270.1
A5: total fixed cost | B5: =('Q9-Predict'!H125)/B2 -> 1437.5479 | C5: =C4*1.125 -> 716.8125 | H5: 0.2 | I5: add profit | J5: =(1+$H$5)*J4 -> 953.9 | K5: =(1+$H$5)*K4 -> 764.6
A6: planned production | C6: =C5*1.2 -> 860.175 | H6: 0.125 | I6: tax | J6: =J5*(1+$H$6) -> 1073.1375 | K6: =K5*(1+$H$6) -> 860.175 | M6: Production Fixed Cost | N6: 280000
M7: Salaries | N7: 272500
A8: Method | B8: Cost plus pricing | M8: Training Investments | N8: 30000
A9: Full cost | B9: `Variable cost per unit+ (Fixed costs/expected units) | M9: Fringe Benefits Investments | N9: 53590
A10: Breakeven Price | B10: =B4+B5 -> 2521.2109 | M10: CSR. Investments | N10: 4000
A11: Add markup | B11: 1.1 | C11: 1.2 | D11: 1.3 | E11: 1.4 | F11: 1.5 | M11: Profit Sharing Payment | N11: 0
A12: Selling price | B12: =$B$10*B11 -> 2773.332 | C12: =$B$10*C11 -> 3025.4531 | D12: =$B$10*D11 -> 3277.5742 | E12: =$B$10*E11 -> 3529.6953 | F12: =$B$10*F11 -> 3781.8164 | M12: Research & Development | N12: 45000
A13: CM | B13: =B12-$B$10 -> 252.12109 | C13: =C12-$B$10 -> 504.24218 | D13: =D12-$B$10 -> 756.36327 | E13: =E12-$B$10 -> 1008.4844 | F13: =F12-$B$10 -> 1260.6055 | M13: A&P Investiments | N13: 72902.82
A14: CM Ratio | B14: =B13/B12 -> 0.090909091 | C14: =C13/C12 -> 0.16666667 | D14: =D13/D12 -> 0.23076923 | E14: =E13/E12 -> 0.28571429 | F14: =F13/F12 -> 0.33333333 | M14: Raw Material Storage Costs | N14: 13633.042
A15: Breakeven Sales | B15: =(SUM($N$7+$N$8+$N$6+$N$9+$N$10+$N$12+$N$13+$N$14+$N$15+$N$16))/'Pricing-Working'!B14 -> 9626274.5 | C15: =(SUM($N$7+$N$8+$N$6+$N$9+$N$10+$N$12+$N$13+$N$14+$N$15+$N$16))/'Pricing-Working'!C14 -> 5250695.2 | D15: =(SUM($N$7+$N$8+$N$6+$N$9+$N$10+$N$12+$N$13+$N$14+$N$15+$N$16))/'Pricing-Working'!D14 -> 3792168.7 | E15: =(SUM($N$7+$N$8+$N$6+$N$9+$N$10+$N$12+$N$13+$N$14+$N$15+$N$16))/'Pricing-Working'!E14 -> 3062905.5 | F15: =(SUM($N$7+$N$8+$N$6+$N$9+$N$10+$N$12+$N$13+$N$14+$N$15+$N$16))/'Pricing-Working'!F14 -> 2625347.6 | M15: Information Report Purchase | N15: 80000
A16: Breakeven units | B16: =(SUM($N$7+$N$8+$N$6+$N$9+$N$10+$N$12+$N$13+$N$14+$N$15+$N$16))/B13 -> 3471.0141 | C16: =(SUM($N$7+$N$8+$N$6+$N$9+$N$10+$N$12+$N$13+$N$14+$N$15+$N$16))/C13 -> 1735.5071 | D16: =(SUM($N$7+$N$8+$N$6+$N$9+$N$10+$N$12+$N$13+$N$14+$N$15+$N$16))/D13 -> 1157.0047 | E16: =(SUM($N$7+$N$8+$N$6+$N$9+$N$10+$N$12+$N$13+$N$14+$N$15+$N$16))/E13 -> 867.75353 | F16: =(SUM($N$7+$N$8+$N$6+$N$9+$N$10+$N$12+$N$13+$N$14+$N$15+$N$16))/F13 -> 694.20282 | M16: Freight Costs | N16: 23490
M17: Loss & Damage | N17: 0
M18: Loan Interest | N18: 0
M19: Factoring Interest | N19: 0
M20: Decision Fine | N20: 0
M21: PROFIT & LOSS STATEMENT EXPENSES | N21: 875115.86
M23: (+) Income savings | N23: 0
M24: (+) Bonus Value | N24: 0
M26: Pretax Income | N26: -499845.76
M27: (-) IR | N27: 0
M28: NET PROFIT / LOSS | N28: -499845.76
M30: PREVIOUS QUARTER BALANCE | N30: -706786.36
M31: NET PROFIT / LOSS | N31: -1206632.1
... M33: PROFIT AND LOSS STATEMENT RESULTS | N33: -1206632.1

Sheet Data_Price
A2: Q2 Price | G2: Q4 Price | M2: Q5 Price | S2: Q6 Price | Y2: Q7 Price | AE2: Q8 Price | AK2: Q9 Price | AQ2: Q11 Price | AW2: Q12 Price
A3: Region | B3: 1 | C3: 2 | D3: 3 | E3: 4 | G3: Region | H3: 1 | I3: 2 | J3: 3 | K3: 4 | M3: Region | N3: 1 | O3: 2 | P3: 3 | Q3: 4 | S3: Region | T3: 1 | U3: 2 | V3: 3 | W3: 4 | Y3: Region | Z3: 1 | AA3: 2 | AB3: 3 | AC3: 4 | AE3: Region | AF3: 1 | AG3: 2 | AH3: 3 | AI3: 4 | AK3: Region | AL3: 1 | AM3: 2 | AN3: 3 | AO3: 4 | AQ3: Region | AR3: 1 | AS3: 2 | AT3: 3 | AU3: 4 | AW3: Region | AX3: 1 | AY3: 2 | AZ3: 3 | BA3: 4
A4: EcoBreeze | B4: 1499 | C4: 1399 | D4: 1399 | E4: 1499 | G4: EcoBreeze | H4: 1890 | I4: 1890 | J4: 1845 | K4: 1890 | M4: EcoBreeze | N4: 2450 | O4: 1899 | P4: 2450 | Q4: 2450 | S4: EcoBreeze | T4: 2799 | U4: 2199 | V4: 2799 | W4: 2799 | Y4: EcoBreeze | Z4: 2899 | AA4: 2399 | AB4: 2899 | AC4: 2899 | AE4: EcoBreeze | AF4: 2999 | AG4: 2499 | AH4: 2999 | AI4: 2999 | AK4: EcoBreeze | AL4: 2799 | AM4: 2599 | AN4: 2799 | AO4: 2799 | AQ4: EcoBreeze | AR4: 2899 | AS4: 2599 | AT4: 2899 | AU4: 2899 | AW4: EcoBreeze | AX4: 2899 | AY4: 2599 | AZ4: 2899 | BA4: 2899
A5: EcoChill | B5: 1303 | C5: 0 | D5: 1273 | E5: 0 | G5: EcoChill | H5: 1179.98 | I5: 1179.98 | J5: 1149.98 | K5: 1179.98 | M5: EcoChill | N5: 1500 | O5: 1450 | P5: 1500 | Q5: 1600 | S5: EcoChill | T5: 1999 | U5: 1949 | V5: 1999 | W5: 2099 | Y5: EcoChill | Z5: 2049 | AA5: 1999 | AB5: 2049 | AC5: 2149 | AE5: EcoChill | AF5: 2099 | AG5: 2049 | AH5: 2099 | AI5: 2149 | AK5: EcoChill | AL5: 2149.98 | AM5: 2099 | AN5: 2149 | AO5: 2199 | AQ5: EcoChill | AR5: 2249.98 | AS5: 2199.98 | AT5: 2249.98 | AU5: 2299.98 | AW5: EcoChill | AX5: 2050 | AY5: 2000 | AZ5: 2050 | BA5: 2100
A6: LOLL | B6: 499.99 | C6: 469.99 | D6: 469.99 | E6: 499.99 | G6: LOLL | H6: 1550 | I6: 1499 | J6: 1499 | K6: 1550 | M6: LOLL | N6: 2099 | O6: 1999 | P6: 1999 | Q6: 2099 | S6: LOLL | T6: 2099 | U6: 1999 | V6: 1999 | W6: 2099 | Y6: LOLL | Z6: 2299 | AA6: 2199 | AB6: 2299 | AC6: 2299 | AE6: LOLL | AF6: 2699 | AG6: 2599 | AH6: 2599 | AI6: 2699 | AK6: LOLL | AL6: 2799 | AM6: 2699 | AN6: 2699 | AO6: 2799 | AQ6: LOLL | AR6: 2399 | AS6: 2299 | AT6: 2299 | AU6: 2399 | AW6: LOLL | AX6: 2399 | AY6: 2299 | AZ6: 2299 | BA6: 2399
A7: NorthBreeze | B7: 999.99 | C7: 999.99 | D7: 949.99 | E7: 999.99 | G7: NorthBreeze | H7: 1429.99 | I7: 1399 | J7: 1379.99 | K7: 1429.99 | M7: NorthBreeze | N7: 1949 | O7: 1949 | P7: 1899 | Q7: 1949 | S7: NorthBreeze | T7: 2299 | U7: 2299 | V7: 2269 | W7: 2299 | Y7: NorthBreeze | Z7: 2599 | AA7: 2599 | AB7: 2599 | AC7: 2599 | AE7: NorthBreeze | AF7: 2249 | AG7: 2249 | AH7: 2229 | AI7: 2249 | AK7: NorthBreeze | AL7: 2399 | AM7: 2399 | AN7: 2359 | AO7: 2399 | AQ7: NorthBreeze | AR7: 2579 | AS7: 2579 | AT7: 2549 | AU7: 2579 | AW7: NorthBreeze | AX7: 2799 | AY7: 2799 | AZ7: 2799 | BA7: 2799
A23: EcoChill in Region 1 and 3

Sheet Data_Sales
B2: Sales
B3: Region\Quarter | C3: 1 | D3: 2 | E3: 3 | F3: 4 | G3: 5 | H3: 6 | I3: 7 | J3: 8 | K3: 9 | L3: 10 | M3: 11 | N3: 12
B4: 1 | C4: 0 | D4: 50 | E4: 99 | F4: 210 | G4: 292 | H4: 150 | I4: 359 | J4: 264 | K4: 427 | L4: 484 | M4: 577 | N4: 403
B5: 2 | C5: 0 | D5: 103 | E5: 216 | F5: 79 | G5: 297 | H5: 301 | I5: 212 | J5: 198 | K5: 271 | L5: 302 | M5: 327 | N5: 210
B6: 3 | C6: 0 | D6: 66 | E6: 207 | F6: 121 | G6: 117 | H6: 25 | I6: 39 | J6: 50 | K6: 48 | L6: 151 | M6: 57 | N6: 40
B7: 4 | C7: 0 | D7: 325 | E7: 616 | F7: 485 | G7: 785 | H7: 501 | I7: 674 | J7: 452 | K7: 759 | L7: 668 | M7: 889 | N7: 655
B8: Freight Cost | C8: 0 | D8: 23490 | E8: 47968 | F8: 41370 | G8: 61890 | H8: 36058 | I8: 55012 | J8: 38776 | K8: 63022 | L8: 64144 | M8: 76922 | N8: 55710
D10: =SUM(D4:D7) -> 544 | E10: =SUM(E4:E7) -> 1138 | F10: =SUM(F4:F7) -> 895 | G10: =SUM(G4:G7) -> 1491 | H10: =SUM(H4:H7) -> 977 | I10: =SUM(I4:I7) -> 1284 | J10: =SUM(J4:J7) -> 964 | K10: =SUM(K4:K7) -> 1505
B14: Demand
B15: Region\Quarter | C15: 1 | D15: 2 | E15: 3 | F15: 4 | G15: 5 | H15: 6 | I15: 7 | J15: 8 | K15: 9 | L15: 10 | M15: 11 | N15: 12
B16: 1 | C16: 0 | D16: 1344 | E16: 1142 | F16: 941
B17: 2 | C17: 0 | D17: 912 | E17: 775 | F17: 638
B18: 3 | C18: 0 | D18: 1008 | E18: 857 | F18: 706
B19: 4 | C19: 0 | D19: 1536 | E19: 1306 | F19: 1075
B21: Market Share
B22: Region\Quarter | C22: 1 | D22: 2 | E22: 3 | F22: 4 | G22: 5 | H22: 6 | I22: 7 | J22: 8 | K22: 9 | L22: 10 | M22: 11 | N22: 12
B23: 1 | C23: 0 | E23: 0.1134 | K23: 0.3544
B24: 2 | C24: 0 | E24: 0.3501 | K24: 0.3329
B25: 3 | C25: 0 | E25: 0.3103 | K25: 0.0536
B26: 4 | C26: 0 | E26: 0.5833 | K26: 0.5524

Sheet Data_CashFlows
A2: Cash Flows | B2: 1 | C2: 2 | D2: 3 | E2: 4 | F2: 5 | G2: 6 | H2: 7 | I2: 8 | J2: 9 | K2: 10 | L2: 11 | M2: 12
A3: Initial Balance | B3: 3200000 | C3: 437085.64 | D3: 100000 | E3: 100000 | F3: 100000 | G3: 214828.04 | H3: 348702.4 | I3: 592772.49 | J3: 215682.39 | K3: 660900.91 | L3: 1412002.7 | M3: 2884721.7
A5: Cash (+) | C5: 798556 | D5: 1923112 | E5: 1686105 | F5: 3489303 | G5: 2554023 | H5: 3616316 | I5: 2792036 | J5: 4158295 | K5: 4562295 | L5: 5265050 | M5: 3728892
A6: Trade Note Received | B6: 0 | C6: 0 | D6: 0 | E6: 0 | F6: 0 | G6: 0 | H6: 0 | I6: 0 | J6: 0 | K6: 0 | L6: 0 | M6: 0
A7: Factoring Amount | B7: 0 | C7: 0 | D7: 0 | E7: 0 | F7: 0 | G7: 0 | H7: 0 | I7: 0 | J7: 0 | K7: 0 | L7: 0 | M7: 0
A8: Borrowed Loan | B8: 0 | C8: 310000 | D8: 300000 | E8: 0 | F8: 0 | G8: 0 | H8: 0 | I8: 0 | J8: 0 | K8: 0 | L8: 0 | M8: 0
A9: Redemptions of Investment | B9: 0 | C9: 0 | D9: 0 | E9: 0 | F9: 0 | G9: 0 | H9: 0 | I9: 0 | J9: 0 | K9: 0 | L9: 0 | M9: 0
A10: Machinery Downgrade (Sell) | B10: 0 | C10: 0 | D10: 0 | E10: 0 | F10: 0 | G10: 0 | H10: 0 | I10: 0 | J10: 0 | K10: 0 | L10: 0 | M10: 0
A11: Bonus Amount | B11: 0 | C11: 0 | D11: 0 | E11: 0 | F11: 0 | G11: 0 | H11: 0 | I11: 0 | J11: 0 | K11: 0 | L11: 0 | M11: 0
A12: TOTAL INCOME (INC LOAN) | B12: 0 | C12: =SUM(C5:C11)+C3 -> 1545641.6 | D12: =SUM(D5:D11) +D3 -> 2323112 | E12: =SUM(E5:E11) +E3 -> 1786105 | F12: =SUM(F5:F11) +F3 -> 3589303 | G12: =SUM(G5:G11) +G3 -> 2768851 | H12: 3616316 | I12: 2792036 | J12: 4158295 | K12: 4562295 | L12: 5265050 | M12: 3728892
A14: Quarter Expenses (-) | B14: 706786.36 | C14: 875115.86 | D14: 1053653.6 | E14: 1087995.5 | F14: 1314655.5 | G14: 1130314.5 | H14: 1876807.3 | I14: 1848764.4 | J14: 2029148.4 | K14: 1947665.5 | L14: 2019182.2 | M14: 1974334.9
A15: Machinery Acquisition | B15: 1500000 | C15: 0 | D15: 0 | E15: 0 | F15: 0 | G15: 0 | H15: 0 | I15: 0 | J15: 0 | K15: 0 | L15: 0 | M15: 0
A16: Variable Cost | B16: 0 | C16: 131761.74 | D16: 435205.96 | E16: 311929.42 | F16: 645521.06 | G16: 472494.27 | H16: 669018.45 | I16: 516526.66 | J16: 769284.56 | K16: 901804.57 | L16: 974034.26 | M16: 689845.01
A17: Income Tax Amount | B17: 0 | C17: 0 | D17: 0 | E17: 0 | F17: 109517.16 | G17: 64147.46 | H17: 57361.12 | I17: 0 | J17: 83002.14 | K17: 127908.23 | L17: 192065.55 | M17: 54565.19
A18: Raw Material Purchase | B18: 556128 | C18: 599598 | D18: 643068 | E18: 579113.28 | F18: 332198.55 | G18: 753192.45 | H18: 769059 | I18: 803835 | J18: 831641.4 | K18: 833814.9 | L18: 607049.04 | M18: 95126.85
A19: Loan Payments | B19: 0 | C19: 0 | D19: 470833.96 | E19: 679649.48 | F19: 972582.67 | G19: 0 | H19: 0 | I19: 0 | J19: 0 | K19: 0 | L19: 0 | M19: 0
A20: Savings | B20: 0 | C20: 0 | D20: 0 | E20: 0 | F20: 0 | G20: 0 | H20: 0 | I20: 0 | J20: 0 | K20: 0 | L20: 0 | M20: 0
A21: Decision Fine | B21: 0 | C21: 0 | D21: 0 | E21: 0 | F21: 0 | G21: 0 | H21: 0 | I21: 0 | J21: 0 | K21: 0 | L21: 0 | M21: 0
A22: TOTAL PAYMENT | B22: =SUM(B14:B21) -> 2762914.4 | C22: =SUM(C14:C21) -> 1606475.6 | D22: =SUM(D14:D21) -> 2602761.5 | E22: =SUM(E14:E21) -> 2658687.7 | F22: =SUM(F14:F21) -> 3374475 | G22: =SUM(G14:G21) -> 2420148.6 | H22: 3372245.9 | I22: 3169126.1 | J22: 3713076.5 | K22: 3811193.2 | L22: 3792331.1 | M22: 2813872
A24: Quarter Final Balance | B24: =B3-B22 -> 437085.64 | C24: =C12-C22 -> -60833.96 | D24: =D12-D22 -> -279649.48 | E24: =E12-E22 -> -872582.67 | F24: =F12-F22 -> 214828.04 | G24: =G12-G22 -> 348702.4 | H24: 592772.49 | I24: 215682.39 | J24: 660900.91 | K24: 1412002.7 | L24: 2884721.7 | M24: 3799741.7
A25: Automatic Loan | B25: 0 | C25: 160833.96 | D25: 379649.48 | E25: 972582.67 | F25: 0 | G25: 0 | H25: 0 | I25: 0 | J25: 0 | K25: 0 | L25: 0 | M25: 0
A26: Adjusted Final Balance | B26: =SUM(B24:B25) -> 437085.64 | C26: =SUM(C24:C25) -> 100000 | D26: =SUM(D24:D25) -> 100000 | E26: =SUM(E24:E25) -> 100000 | F26: =SUM(F24:F25) -> 214828.04 | G26: =SUM(G24:G25) -> 348702.4 | H26: 592772.49 | I26: 215682.39 | J26: 660900.91 | K26: 1412002.7 | L26: 2884721.7 | M26: 3799741.7
A29: Initial Balance | B29: 3200000 | C29: 437085.64 | D29: 100000 | E29: 100000 | F29: 100000 | G29: 214828.04 | H29: =H3 -> 348702.4 | I29: =I3 -> 592772.49 | J29: =J3 -> 215682.39 | K29: =K3 -> 660900.91 | L29: =L3 -> 1412002.7 | M29: =M3 -> 2884721.7
A30: Quarter Final Balance | B30: 437085.64 | C30: -60833.96 | D30: -279649.48 | E30: -872582.67 | F30: 214828.04 | G30: 348702.4 | H30: =H26 -> 592772.49 | I30: =I26 -> 215682.39 | J30: =J26 -> 660900.91 | K30: =K26 -> 1412002.7 | L30: =L26 -> 2884721.7 | M30: =M26 -> 3799741.7

Sheet Data_Stock
A1: Inventory Flow
B2: Category/Quarter | C2: 1 | D2: 2 | E2: 3 | F2: 4 | G2: 5 | H2: 6 | I2: 7 | J2: 8 | K2: 9 | L2: 10 | M2: 11 | N2: 12
B3: Raw Material
B4: Used in Production | C4: 0 | D4: 1128 | E4: 1134 | F4: 1134 | G4: 750 | H4: 924 | I4: 1382 | J4: 1382 | K4: 1498 | L4: 1498 | M4: 1513 | N4: 1439
B5: Purchased | C5: 1200 | D5: 1200 | E5: 1200 | F5: 1062 | G5: 675 | H5: 1500 | I5: 1500 | J5: 1500 | K5: 1560 | L5: 1560 | M5: 1066 | N5: 0
B6: Left | C6: 1200 | D6: =D5+C6-D4 -> 1272 | E6: =E5+D6-E4 -> 1338 | F6: =F5+E6-F4 -> 1266 | G6: 1056 | H6: =G6+H5-H4 -> 1632 | I6: =H6+I5-I4 -> 1750 | J6: =I6+J5-J4 -> 1868 | K6: =J6+K5-K4 -> 1930 | L6: =K6+L5-L4 -> 1992 | M6: =L6+M5-M4 -> 1545 | N6: =M6+N5-N4 -> 106
B7: Finished Goods
B8: Produced | C8: =C4 -> 0 | D8: =D4 -> 1128 | E8: =E4 -> 1134 | F8: =F4 -> 1134 | G8: =G4 -> 750 | H8: =H4 -> 924 | I8: 1382 | J8: 1382 | K8: 1498 | L8: =L4 -> 1498 | M8: 1513 | N8: =N4 -> 1439
B9: Available to sell | C9: 0 | D9: =C11+D8 -> 1128 | E9: =D11+E8 -> 1718 | F9: =E11+F8 -> 1714 | G9: 1569 | H9: =G11+H8 -> 1002 | I9: =H11+I8 -> 1407 | J9: =I11+J8 -> 1505 | K9: =J11+K8 -> 2039 | L9: =K11+L8 -> 2032 | M9: =L11+M8 -> 1940 | N9: =M11+N8 -> 1529
B10: Sold | C10: 0 | D10: 544 | E10: 1138 | F10: 895 | G10: 1491 | H10: 977 | I10: 1284 | J10: 964 | K10: 1505 | L10: 1605 | M10: 1850 | N10: 1308
B11: Left Inventory | C11: =C9-C10 -> 0 | D11: =D9-D10 -> 584 | E11: =E9-E10 -> 580 | F11: =F9-F10 -> 819 | G11: =G9-G10 -> 78 | H11: =H9-H10 -> 25 | I11: =I9-I10 -> 123 | J11: =J9-J10 -> 541 | ... N11: =N9-N10 -> 221
B13: Issue | C13: Loss Material in Q5

Sheet Data_IncomeStatement
A1: Quarter | B1: 1 | C1: 2 | D1: 3 | E1: 4 | F1: 5 | G1: 6 | H1: 7 | I1: 8 | J1: 9 | K1: 10 | L1: 11 | M1: 12
A2: Sales Income | B2: ='Q1'!B90 -> 0 | C2: ='Q2'!B111 -> 798556 | D2: ='Q3-Validation'!C123 -> 1923112 | E2: ='Q4-Validation'!C123 -> 1686105 | F2: 3489303 | G2: ='Q6-Validation'!C123 -> 2554023 | H2: ='Q7-Validation'!C123 -> 3616316 | I2: ='Q8-Validation'!C123 -> 2792036 | J2: ='Q9-Validation'!C123 -> 4158295 | K2: ='Q10-Validation'!C123 -> 4562295 | L2: ='Q11-Validation'!C123 -> 5265050 | M2: ='Q12-Validation'!C123 -> 3728892
A3: COGS | B3: ='Q1'!B91 -> 0 | C3: ='Q2'!B112 -> 423285.9 | D3: ='Q3-Validation'!C124 -> 1045048.8 | E3: ='Q4-Validation'!C124 -> 791550.97 | F3: 1444533.1 | G3: ='Q6-Validation'!C124 -> 996058.8 | H3: ='Q7-Validation'!C124 -> 1357101.2 | I3: ='Q8-Validation'!C124 -> 1033124.6 | J3: ='Q9-Validation'!C124 -> 1575799 | K3: ='Q10-Validation'!C124 -> 1761908 | L3: ='Q11-Validation'!C124 -> 1965430.8 | M3: ='Q12-Validation'!C124 -> 1390789.1
A4: Gross Profit and Loss | B4: ='Q1'!B92 -> 0 | C4: ='Q2'!B113 -> 375270.1 | D4: ='Q3-Validation'!C125 -> 878063.22 | E4: ='Q4-Validation'!C125 -> 894554.03 | F4: 2044769.9 | G4: ='Q6-Validation'!C125 -> 1557964.2 | H4: ='Q7-Validation'!C125 -> 2259214.8 | I4: ='Q8-Validation'!C125 -> 1758911.4 | J4: ='Q9-Validation'!C125 -> 2582496 | K4: ='Q10-Validation'!C125 -> 2800387 | L4: ='Q11-Validation'!C125 -> 3299619.2 | M4: ='Q12-Validation'!C125 -> 2338102.9
G5: ='Q6-Validation'!C126 -> 0 | H5: ='Q7-Validation'!C126 -> 0 | I5: ='Q8-Validation'!C126 -> 0 | J5: ='Q9-Validation'!C126 -> 0 | K5: ='Q10-Validation'!C126 -> 0 | L5: ='Q11-Validation'!C126 -> 0 | M5: ='Q12-Validation'!C126 -> 0
A6: Production Fixed Cost | B6: ='Q1'!B94 -> 280000 | C6: ='Q2'!B115 -> 280000 | D6: ='Q3-Validation'!C127 -> 280000 | E6: ='Q4-Validation'!C127 -> 280000 | F6: 280000 | G6: ='Q6-Validation'!C127 -> 280000 | H6: ='Q7-Validation'!C127 -> 560000 | I6: ='Q8-Validation'!C127 -> 560000 | J6: ='Q9-Validation'!C127 -> 560000 | K6: ='Q10-Validation'!C127 -> 560000 | L6: ='Q11-Validation'!C127 -> 560000 | M6: ='Q12-Validation'!C127 -> 560000
A7: Salaries | B7: ='Q1'!B95 -> 267500 | C7: ='Q2'!B116 -> 272500 | D7: ='Q3-Validation'!C128 -> 282500 | E7: ='Q4-Validation'!C128 -> 287500 | F7: 304200 | G7: ='Q6-Validation'!C128 -> 304200 | H7: ='Q7-Validation'!C128 -> 608400 | I7: ='Q8-Validation'!C128 -> 608400 | J7: ='Q9-Validation'!C128 -> 608400 | K7: ='Q10-Validation'!C128 -> 608400 | L7: ='Q11-Validation'!C128 -> 608400 | M7: ='Q12-Validation'!C128 -> 608400
A8: Training Investments | B8: ='Q1'!B96 -> 20000 | C8: ='Q2'!B117 -> 30000 | D8: ='Q3-Validation'!C129 -> 40000 | E8: ='Q4-Validation'!C129 -> 40000 | F8: 70000 | G8: ='Q6-Validation'!C129 -> 70000 | H8: ='Q7-Validation'!C129 -> 70000 | I8: ='Q8-Validation'!C129 -> 70000 | J8: ='Q9-Validation'!C129 -> 70000 | K8: ='Q10-Validation'!C129 -> 70000 | L8: ='Q11-Validation'!C129 -> 50000 | M8: ='Q12-Validation'!C129 -> 50000
A9: Fringe Benefits Investments | B9: ='Q1'!B97 -> 52425 | C9: ='Q2'!B118 -> 53590 | D9: ='Q3-Validation'!C130 -> 55920 | E9: ='Q4-Validation'!C130 -> 57085 | F9: 47000 | G9: ='Q6-Validation'!C130 -> 47000 | H9: ='Q7-Validation'!C130 -> 47000 | I9: ='Q8-Validation'!C130 -> 47000 | J9: ='Q9-Validation'!C130 -> 47000 | K9: ='Q10-Validation'!C130 -> 47000 | L9: ='Q11-Validation'!C130 -> 47000 | M9: ='Q12-Validation'!C130 -> 47000
A10: CSR. Investments | B10: ='Q1'!B98 -> 4000 | C10: ='Q2'!B119 -> 4000 | D10: ='Q3-Validation'!C131 -> 8000 | E10: ='Q4-Validation'!C131 -> 8000 | F10: 10000 | G10: ='Q6-Validation'!C131 -> 10000 | H10: ='Q7-Validation'!C131 -> 10000 | I10: ='Q8-Validation'!C131 -> 10000 | J10: ='Q9-Validation'!C131 -> 18000 | K10: ='Q10-Validation'!C131 -> 18000 | L10: ='Q11-Validation'!C131 -> 18000 | M10: ='Q12-Validation'!C131 -> 18000
A11: Profit Sharing Payment | B11: ='Q1'!B99 -> 0 | C11: ='Q2'!B120 -> 0 | D11: ='Q3-Validation'!C132 -> 0 | E11: ='Q4-Validation'!C132 -> 0 | F11: 0 | G11: ='Q6-Validation'!C132 -> 0 | H11: ='Q7-Validation'!C132 -> 0 | I11: ='Q8-Validation'!C132 -> 0 | J11: ='Q9-Validation'!C132 -> 0 | K11: ='Q10-Validation'!C132 -> 0 | L11: ='Q11-Validation'!C132 -> 0 | M11: ='Q12-Validation'!C132 -> 0
A12: Research & Development | B12: ='Q1'!B100 -> 30000 | C12: ='Q2'!B121 -> 45000 | D12: ='Q3-Validation'!C133 -> 75000 | E12: ='Q4-Validation'!C133 -> 75000 | F12: 135000 | G12: ='Q6-Validation'!C133 -> 135000 | H12: ='Q7-Validation'!C133 -> 135000 | I12: ='Q8-Validation'!C133 -> 135000 | J12: ='Q9-Validation'!C133 -> 135000 | K12: ='Q10-Validation'!C133 -> 135000 | L12: ='Q11-Validation'!C133 -> 135000 | M12: ='Q12-Validation'!C133 -> 135000
A13: A&P Investiments | B13: ='Q1'!B101 -> 0 | C13: ='Q2'!B122 -> 72902.82 | D13: ='Q3-Validation'!C134 -> 145921.76 | E13: ='Q4-Validation'!C134 -> 165218.4 | F13: 238537.6 | G13: ='Q6-Validation'!C134 -> 190565.01 | H13: ='Q7-Validation'!C134 -> 292639.19 | I13: ='Q8-Validation'!C134 -> 319567.59 | J13: ='Q9-Validation'!C134 -> 427041.03 | K13: ='Q10-Validation'!C134 -> 423771.62 | L13: ='Q11-Validation'!C134 -> 427301.22 | M13: ='Q12-Validation'!C134 -> 349088.82
A14: Raw Material Storage Costs | B14: ='Q1'!B102 -> 12861.36 | C14: ='Q2'!B123 -> 13633.042 | D14: ='Q3-Validation'!C135 -> 14340.416 | E14: ='Q4-Validation'!C135 -> 13568.735 | F14: 11318 | G14: ='Q6-Validation'!C135 -> 17491.45 | H14: ='Q7-Validation'!C135 -> 18756.15 | I14: ='Q8-Validation'!C135 -> 20020.85 | J14: ='Q9-Validation'!C135 -> 20685.354 | K14: ='Q10-Validation'!C135 -> 21349.858 | L14: ='Q11-Validation'!C135 -> 16559.001 | M14: ='Q12-Validation'!C135 -> 1136.0868
A15: Information Report Purchase | B15: ='Q1'!B103 -> 40000 | C15: ='Q2'!B124 -> 80000 | D15: ='Q3-Validation'!C136 -> 80000 | E15: ='Q4-Validation'!C136 -> 80000 | F15: 40000 | G15: ='Q6-Validation'!C136 -> 40000 | H15: ='Q7-Validation'!C136 -> 80000 | I15: ='Q8-Validation'!C136 -> 40000 | J15: ='Q9-Validation'!C136 -> 80000 | K15: ='Q10-Validation'!C136 -> 0 | L15: ='Q11-Validation'!C136 -> 80000 | M15: ='Q12-Validation'!C136 -> 150000
A16: Freight Costs | B16: ='Q1'!B104 -> 0 | C16: ='Q2'!B125 -> 23490 | D16: ='Q3-Validation'!C137 -> 47968 | E16: ='Q4-Validation'!C137 -> 41370 | F16: 61890 | G16: ='Q6-Validation'!C137 -> 36058 | H16: ='Q7-Validation'!C137 -> 55012 | I16: ='Q8-Validation'!C137 -> 38776 | J16: ='Q9-Validation'!C137 -> 63022 | K16: ='Q10-Validation'!C137 -> 64144 | L16: ='Q11-Validation'!C137 -> 76922 | M16: ='Q12-Validation'!C137 -> 55710
A17: Loss & Damage | B17: ='Q1'!B105 -> 0 | C17: ='Q2'!B126 -> 0 | D17: ='Q3-Validation'!C138 -> 0 | E17: ='Q4-Validation'!C138 -> 0 | F17: 0 | G17: ='Q6-Validation'!C138 -> 0 | H17: ='Q7-Validation'!C138 -> 0 | I17: ='Q8-Validation'!C138 -> 0 | J17: ='Q9-Validation'!C138 -> 0 | K17: ='Q10-Validation'!C138 -> 0 | L17: ='Q11-Validation'!C138 -> 0 | M17: ='Q12-Validation'!C138 -> 0
... A21: PROFIT & LOSS STATEMENT EXPENSES | B21: ='Q1'!B109 -> 706786.36 | C21: ='Q2'!B130 -> 875115.86 | D21: ='Q3-Validation'!C142 -> 1053653.6 | E21: ='Q4-Validation'!C142 -> 1087995.5 | F21: 1314655.5 | G21: ='Q6-Validation'!C142 -> 1130314.5 | H21: ='Q7-Validation'!C142 -> 1876807.3 | I21: ='Q8-Validation'!C142 -> 1848764.4 | J21: ='Q9-Validation'!C142 -> 2029148.4 | K21: ='Q10-Validation'!C142 -> 1947665.5 | L21: ='Q11-Validation'!C142 -> 2019182.2 | M21: ='Q12-Validation'!C142 -> 1974334.9
G22: ='Q6-Validation'!C143 -> 0 | H22: ='Q7-Validation'!C143 -> 0 | I22: ='Q8-Validation'!C143 -> 0 | J22: ='Q9-Validation'!C143 -> 0 | K22: ='Q10-Validation'!C143 -> 0 | L22: ='Q11-Validation'!C143 -> 0 | M22: ='Q12-Validation'!C143 -> 0
A23: (+) Income savings | B23: ='Q1'!B111 -> 0 | C23: ='Q2'!B132 -> 0 | D23: ='Q3-Validation'!C144 -> 0 | E23: ='Q4-Validation'!C144 -> 0 | F23: 0 | G23: ='Q6-Validation'!C144 -> 0 | H23: ='Q7-Validation'!C144 -> 0 | I23: ='Q8-Validation'!C144 -> 0 | J23: ='Q9-Validation'!C144 -> 0 | K23: ='Q10-Validation'!C144 -> 0 | L23: ='Q11-Validation'!C144 -> 0 | M23: ='Q12-Validation'!C144 -> 0
A24: (+) Bonus Value | B24: ='Q1'!B112 -> 0 | C24: ='Q2'!B133 -> 0 | D24: ='Q3-Validation'!C145 -> 0 | E24: ='Q4-Validation'!C145 -> 0 | F24: 0 | G24: ='Q6-Validation'!C145 -> 0 | H24: ='Q7-Validation'!C145 -> 0 | I24: ='Q8-Validation'!C145 -> 0 | J24: ='Q9-Validation'!C145 -> 0 | K24: ='Q10-Validation'!C145 -> 0 | L24: ='Q11-Validation'!C145 -> 0 | M24: ='Q12-Validation'!C145 -> 0
G25: ='Q6-Validation'!C146 -> 0 | H25: ='Q7-Validation'!C146 -> 0 | I25: ='Q8-Validation'!C146 -> 0 | J25: ='Q9-Validation'!C146 -> 0 | K25: ='Q10-Validation'!C146 -> 0 | L25: ='Q11-Validation'!C146 -> 0 | M25: ='Q12-Validation'!C146 -> 0
A26: Pretax Income | B26: ='Q1'!B114 -> -706786.36 | C26: ='Q2'!B135 -> -499845.76 | D26: ='Q3-Validation'!C147 -> -175590.34 | E26: ='Q4-Validation'!C147 -> -193441.46 | F26: 730143.43 | G26: ='Q6-Validation'!C147 -> 427649.74 | H26: ='Q7-Validation'!C147 -> 382407.45 | I26: ='Q8-Validation'!C147 -> -89853.06 | J26: ='Q9-Validation'!C147 -> 553347.61 | K26: ='Q10-Validation'!C147 -> 852721.5 | L26: ='Q11-Validation'!C147 -> 1280437 | M26: ='Q12-Validation'!C147 -> 363767.96
A27: (-) IR | B27: ='Q1'!B115 -> 0 | C27: ='Q2'!B136 -> 0 | D27: ='Q3-Validation'!C148 -> 0 | E27: ='Q4-Validation'!C148 -> 0 | F27: 109517.16 | G27: ='Q6-Validation'!C148 -> 64147.461 | H27: ='Q7-Validation'!C148 -> 57361.118 | I27: ='Q8-Validation'!C148 -> 0 | J27: ='Q9-Validation'!C148 -> 83002.141 | K27: ='Q10-Validation'!C148 -> 127908.22 | L27: ='Q11-Validation'!C148 -> 192065.55 | M27: ='Q12-Validation'!C148 -> 54565.194
A28: NET PROFIT / LOSS | B28: ='Q1'!B116 -> -706786.36 | C28: ='Q2'!B137 -> -499845.76 | D28: ='Q3-Validation'!C149 -> -175590.34 | E28: ='Q4-Validation'!C149 -> -193441.46 | F28: 620597.27 | G28: ='Q6-Validation'!C149 -> 363502.28 | H28: ='Q7-Validation'!C149 -> 325046.33 | I28: ='Q8-Validation'!C149 -> -89853.06 | J28: ='Q9-Validation'!C149 -> 470345.47 | K28: ='Q10-Validation'!C149 -> 724813.27 | L28: ='Q11-Validation'!C149 -> 1088371.5 | M28: ='Q12-Validation'!C149 -> 309202.77
G29: ='Q6-Validation'!C150 -> 0 | H29: ='Q7-Validation'!C150 -> 0 | I29: ='Q8-Validation'!C150 -> 0 | J29: ='Q9-Validation'!C150 -> 0 | K29: ='Q10-Validation'!C150 -> 0 | L29: ='Q11-Validation'!C150 -> 0 | M29: ='Q12-Validation'!C150 -> 0
A30: PREVIOUS QUARTER BALANCE | B30: ='Q1'!B118 -> 0 | C30: ='Q2'!B139 -> -706786.36 | D30: ='Q3-Validation'!C151 -> -1206632.1 | E30: ='Q4-Validation'!C151 -> -1382222.5 | F30: -1575663.9 | G30: ='Q6-Validation'!C151 -> -955066.65 | H30: ='Q7-Validation'!C151 -> -591564.37 | I30: ='Q8-Validation'!C151 -> -266518.04 | J30: ='Q9-Validation'!C151 -> -356371.1 | K30: ='Q10-Validation'!C151 -> 113974.37 | L30: ='Q11-Validation'!C151 -> 838787.64 | M30: ='Q12-Validation'!C151 -> 1927159.1
A31: NET PROFIT / LOSS | B31: ='Q1'!B119 -> -706786.36 | C31: ='Q2'!B140 -> -1206632.1 | D31: ='Q3-Validation'!C152 -> -1382222.5 | E31: ='Q4-Validation'!C152 -> -1575663.9 | F31: 620597.27 | G31: ='Q6-Validation'!C152 -> 363502.28 | H31: ='Q7-Validation'!C152 -> 325046.33 | I31: ='Q8-Validation'!C152 -> -89853.06 | J31: ='Q9-Validation'!C152 -> 470345.47 | K31: ='Q10-Validation'!C152 -> 724813.27 | L31: ='Q11-Validation'!C152 -> 1088371.5 | M31: ='Q12-Validation'!C152 -> 309202.77
A32: Fixed sale variation | B32: ='Q1'!B120 -> 0 | C32: ='Q2'!B141 -> 0 | D32: ='Q3-Validation'!C153 -> 0 | E32: ='Q4-Validation'!C153 -> 0 | F32: 0 | G32: ='Q6-Validation'!C153 -> 0 | H32: ='Q7-Validation'!C153 -> 0 | I32: ='Q8-Validation'!C153 -> 0 | J32: ='Q9-Validation'!C153 -> 0 | K32: ='Q10-Validation'!C153 -> 0 | L32: ='Q11-Validation'!C153 -> 0 | M32: ='Q12-Validation'!C153 -> 0
A33: PROFIT AND LOSS STATEMENT RESULTS | B33: ='Q1'!B121 -> -706786.36 | C33: ='Q2'!B142 -> -1206632.1 | D33: ='Q3-Validation'!C154 -> -1382222.5 | E33: ='Q4-Validation'!C154 -> -1575663.9 | F33: -955066.65 | G33: ='Q6-Validation'!C154 -> -591564.37 | H33: ='Q7-Validation'!C154 -> -266518.04 | I33: ='Q8-Validation'!C154 -> -356371.1 | J33: ='Q9-Validation'!C154 -> 113974.37 | K33: ='Q10-Validation'!C154 -> 838787.64 | L33: ='Q11-Validation'!C154 -> 1927159.1 | M33: ='Q12-Validation'!C154 -> 2236361.9

Sheet Data_EmployeeNumber
A2: Active seller
A4: Quarter/Region | B4: 1 | C4: 2 | D4: 3 | E4: 4 | F4: Total
A5: 1 | B5: 1 | C5: 2 | D5: 0 | E5: 3 | F5: =SUM(B5:E5) -> 6
A6: 2 | B6: 1 | C6: 2 | D6: 1 | E6: 3 | F6: =SUM(B6:E6) -> 7
A7: 3 | B7: 1 | C7: 2 | D7: 2 | E7: 4 | F7: =SUM(B7:E7) -> 9
A8: 4 | B8: 2 | C8: 2 | D8: 2 | E8: 4 | F8: =SUM(B8:E8) -> 10
A9: 5 | B9: 2 | C9: 3 | D9: 2 | E9: 4 | F9: =SUM(B9:E9) -> 11
A10: 6 | B10: 2 | C10: 3 | D10: 2 | E10: 4 | F10: =SUM(B10:E10) -> 11 | G10: Validated-Q
A11: 7 | B11: 3 | C11: 3 | D11: 1 | E11: 4 | F11: =SUM(B11:E11) -> 11
A12: 8 | B12: 3 | C12: 3 | D12: 1 | E12: 4 | F12: =SUM(B12:E12) -> 11
A13: 9 | B13: 3 | C13: 3 | D13: 1 | E13: 4 | F13: =SUM(B13:E13) -> 11
A14: 10 | B14: 3 | C14: 3 | D14: 1 | E14: 4 | F14: =SUM(B14:E14) -> 11
A15: 11 | B15: 3 | C15: 3 | D15: 1 | E15: 4 | F15: =SUM(B15:E15) -> 11
A16: 12 | F16: =SUM(B16:E16) -> 0

Sheet Macro_Code

Sheet Q12-Validation
B2: Which Quarter:
B3: 12
B4: For:
B5: Validation
B6: Overtime?
B7: {=INDIRECT("'Input_Q"&B3&"-Predict'!C8")} -> Overtime
B9: From last Quarter
B10: Decicion Point
B11: Prediction
B14: 1. Operation
B16: Cost Overview
B17: Plant | C17: 0 | E17: Note: Raw material cost including the shipping fee related to each part
B18: Research & Development | C18: =F19*F20 -> 135000 | E18: Operation Cost Datasheet | I18: Q3 Order | K18: Type | L18: Unit Cost+Shipping | M18: Climatizer unit cost | N18: Order cost
B19: Raw Material | C19: =N23 -> 0 | E19: R&D | F19: 15000 | G19: /unit | J19: Packing | K19: Premium | L19: =VLOOKUP($K$19,$E$24:F59,2,FALSE) -> 36 | M19: =L19*$F$25 -> 36 | N19: =M19*$F$24 -> 0
B20: Raw Material Storage Costs | C20: =C34*0.02*M24 -> 1136.0868 | F20: {=INDIRECT("'Input_Q"&B3&"-Predict'!C38")} -> 9 | I20: Decision | J20: Plastic | K20: Superplast | L20: =VLOOKUP($K$20,$E$25:F60,2,FALSE) -> 44.52 | M20: =L20*$F$28 -> 89.04 | N20: =M20*$F$24 -> 0
B21: Production Fixed Cost | C21: 280000 | E21: MachineryModel | J21: Motor & Cooling | K21: Freezpro | L21: =VLOOKUP($K$21,$E$26:F63,2,FALSE) -> 187.2 | M21: =L21*$F$38 -> 374.4 | N21: =M21*$F$24 -> 0
C22: =SUM(C17:C21) -> 416136.09 | E22: Model1 | F22: 1300000 | J22: Electric | K22: Proline | L22: =VLOOKUP($K$22,$E$21:F60,2,FALSE) -> 24.15 | M22: =L22*$F$51 -> 72.45 | N22: =M22*$F$24 -> 0
E23: Model2 | F23: 1500000 | I23: unit climatizer cost | M23: =SUM(M19:M22) -> 571.89 | N23: =SUM(N19:N22) -> 0
E24: Raw Material | F24: {=INDIRECT("'Input_Q"&B3&"-Predict'!C36")} -> 0 | G24: # of climatizer RM | I24: Unit Value | M24: =M23-M19 -> 535.89 | N24: =M24*F24 -> 0
B25: Productivity | C25: {=IF(B5="Validation",'Q12-Validation'!C30/'Q12-Validation'!C29,INDIRECT("'Input_Q"&B3&"-Predict'!C34"))} -> 0.97019957 | E25: Packing | F25: 1 | G25: unit/climatizer
E26: Standard | F26: 20
B27: Climatizer Stock | C27: =INDEX(Data_Stock!B2:N11,MATCH("Left Inventory",Data_Stock!B2:B11,0),MATCH(VALUE(B3-1),Data_Stock!B2:N2,0)) -> 90 | E27: Premium | F27: 36
B28: Raw Material Available | C28: =INDEX(Data_Stock!B2:N11,MATCH("Left",Data_Stock!B2:B11,0),MATCH(VALUE(B3-1),Data_Stock!B2:N2,0)) -> 1545 | E28: Plastic | F28: 2 | G28: unit/climatizer
B29: Planned Production | C29: {=INDIRECT("'Input_Q"&B3&"-Predict'!C33")} -> 1483.2 | E29: Plastinjet | F29: =(1+F31)*F30 -> 43.2
B30: =IF(B5="Validation","Actual Production","Predict Production") -> Actual Production | C30: =INDEX(Data_Stock!B2:N11,MATCH("Produced",Data_Stock!B2:B11,0),MATCH(VALUE(B3),Data_Stock!B2:N2,0)) -> 1439 | E30: material | F30: 40
E31: Shipping | F31: 0.08
B32: Raw Material Left | E32: Superplast | F32: =(1+F34)*F33 -> 44.52
B33: Raw Material Purchased | C33: =F24 -> 0 | E33: material | F33: 42
B34: Raw Material Available for Q+1 | C34: =IF(B5="Validation",INDEX(Data_Stock!B2:N11,MATCH("Left",Data_Stock!B2:B11,0),MATCH('Q12-Validation'!B3,Data_Stock!B2:N2,0)),C28+F24-C30) -> 106 | E34: Shipping | F34: 0.06
B35: Total Inventory Value | C35: =C34*M24 -> 56804.34 | E35: IPLM | F35: =(1+F37)*F36 -> 56.1
E36: material | F36: 55
E37: Shipping | F37: 0.02
E38: Moter&Cooling | F38: 2 | G38: unit/climatizer
E39: Motojister | F39: =(1+F41)*F40 -> 117.7
E40: material | F40: 110
E41: Shipping | F41: 0.07
E42: Motormaster | F42: =(1+F44)*F43 -> 186.3
E43: material | F43: 162
E44: Shipping | F44: 0.15
E45: InfinityParts | F45: =(1+F47)*F46 -> 193.6
E46: material | F46: 176
E47: Shipping | F47: 0.1
E48: Freezpro | F48: =(1+F50)*F49 -> 187.2
E49: material | F49: 180
E50: Shipping | F50: 0.04
E51: ElectrocalKit | F51: 3 | G51: unit/climatizer
E52: Chukchuk | F52: =(1+F54)*F53 -> 21.6
E53: material | F53: 18
E54: Shipping | F54: 0.2
E55: ConduiteElec | F55: =(1+F57)*F56 -> 22
E56: material | F56: 20
E57: Shipping | F57: 0.1
E58: Proline | F58: =(1+F60)*F59 -> 24.15
E59: material | F59: 23
E60: Shipping | F60: 0.05
B65: 2. Market
B67: Cost Overview
B68: Sales Income | C68: =SUMPRODUCT(F73:I73,F71:I71) -> 3728892
B69: A&P Investiments | C69: =J75 -> 349088.82 | E69: =IF(B5="Validation","Actual S.C.R","Predict S.C.R") -> Actual S.C.R | F69: {=IF($B$5="Validation",F73/F72,INDIRECT("'Input_Q"&$B$3&"-Predict'!D29"))} -> 0.85562633 | G69: {=IF($B$5="Validation",G73/G72,INDIRECT("'Input_Q"&$B$3&"-Predict'!D30"))} -> 0.78651685 | H69: {=IF($B$5="Validation",H73/H72,INDIRECT("'Input_Q"&$B$3&"-Predict'!D31"))} -> 0.85106383 | I69: {=IF($B$5="Validation",I73/I72,INDIRECT("'Input_Q"&$B$3&"-Predict'!D32"))} -> 0.83121827
B70: Commision Total | C70: =C68*C74 -> 223733.52 | E70: Region | F70: 1 | G70: 2 | H70: 3 | I70: 4 | J70: Total
C71: =SUM(C68:C70) -> 4301714.3 | E71: Unit sale price | F71: {=INDIRECT("'Input_Q"&$B$3&"-Predict'!C10")} -> 2899 | G71: {=INDIRECT("'Input_Q"&$B$3&"-Predict'!C11")} -> 2599 | H71: {=INDIRECT("'Input_Q"&$B$3&"-Predict'!C12")} -> 2899 | I71: {=INDIRECT("'Input_Q"&$B$3&"-Predict'!C13")} -> 2899 | J71: /
E72: Planned Sale | F72: {=INDIRECT("'Input_Q"&$B$3&"-Predict'!C24")} -> 471 | G72: {=INDIRECT("'Input_Q"&$B$3&"-Predict'!C25")} -> 267 | H72: {=INDIRECT("'Input_Q"&$B$3&"-Predict'!C26")} -> 47 | I72: {=INDIRECT("'Input_Q"&$B$3&"-Predict'!C27")} -> 788 | J72: =SUM(F72:I72) -> 1573
E73: =IF(B5="Validation","Actual Sale","Predict Sale") -> Actual Sale | F73: =IF($E$73="Actual Sale",INDEX(Data_Sales!$B$3:$N$8,MATCH(F70,Data_Sales!$B$3:$B$8,0),MATCH($B$3,Data_Sales!$B$3:$N$3,0)),ROUNDDOWN(F69*F72,0)) -> 403 | G73: =IF($E$73="Actual Sale",INDEX(Data_Sales!$B$3:$N$8,MATCH(G70,Data_Sales!$B$3:$B$8,0),MATCH($B$3,Data_Sales!$B$3:$N$3,0)),ROUNDDOWN(G69*G72,0)) -> 210 | H73: =IF($E$73="Actual Sale",INDEX(Data_Sales!$B$3:$N$8,MATCH(H70,Data_Sales!$B$3:$B$8,0),MATCH($B$3,Data_Sales!$B$3:$N$3,0)),ROUNDDOWN(H69*H72,0)) -> 40 | I73: =IF($E$73="Actual Sale",INDEX(Data_Sales!$B$3:$N$8,MATCH(I70,Data_Sales!$B$3:$B$8,0),MATCH($B$3,Data_Sales!$B$3:$N$3,0)),ROUNDDOWN(I69*I72,0)) -> 655 | J73: =SUM(F73:I73) -> 1308
B74: Commision | C74: {=INDIRECT("'Input_Q"&B3&"-Predict'!C39")} -> 0.06 | E74: Advertisement unit | F74: {=INDIRECT("'Input_Q"&$B$3&"-Predict'!C41")} -> 7 | G74: {=INDIRECT("'Input_Q"&$B$3&"-Predict'!C42")} -> 10 | H74: {=INDIRECT("'Input_Q"&$B$3&"-Predict'!C43")} -> 1 | I74: {=INDIRECT("'Input_Q"&$B$3&"-Predict'!C44")} -> 8
B75: Planned sale | C75: =J72 -> 1573 | E75: A&P Investment | F75: =F72*F71*F74/100 -> 95580.03 | G75: =G72*G71*G74/100 -> 69393.3 | H75: =H72*H71*H74/100 -> 1362.53 | I75: =I72*I71*I74/100 -> 182752.96 | J75: =SUM(F75:I75) -> 349088.82
B76: Predicted sale | C76: =J73 -> 1308 | E76: New Hired sales | F76: {=INDIRECT("'Input_Q"&$B$3&"-Predict'!C46")} -> 0 | G76: {=INDIRECT("'Input_Q"&$B$3&"-Predict'!C47")} -> 0 | H76: {=INDIRECT("'Input_Q"&$B$3&"-Predict'!C48")} -> 0 | I76: {=INDIRECT("'Input_Q"&$B$3&"-Predict'!C49")} -> 0 | J76: /
B77: left finished good | C77: =C75-C76 -> 265 | E77: Active Sales Force | F77: =INDEX(Data_EmployeeNumber!$A$4:$E$16,MATCH('Q12-Validation'!$B$3-1,Data_EmployeeNumber!$A$4:$A$16,0),MATCH('Q12-Validation'!F70,Data_EmployeeNumber!$A$4:$E$4,0))+'Q12-Validation'!F76 -> 3 | G77: =INDEX(Data_EmployeeNumber!$A$4:$E$16,MATCH('Q12-Validation'!$B$3-1,Data_EmployeeNumber!$A$4:$A$16,0),MATCH('Q12-Validation'!G70,Data_EmployeeNumber!$A$4:$E$4,0))+'Q12-Validation'!G76 -> 3 | H77: =INDEX(Data_EmployeeNumber!$A$4:$E$16,MATCH('Q12-Validation'!$B$3-1,Data_EmployeeNumber!$A$4:$A$16,0),MATCH('Q12-Validation'!H70,Data_EmployeeNumber!$A$4:$E$4,0))+'Q12-Validation'!H76 -> 1 | I77: =INDEX(Data_EmployeeNumber!$A$4:$E$16,MATCH('Q12-Validation'!$B$3-1,Data_EmployeeNumber!$A$4:$A$16,0),MATCH('Q12-Validation'!I70,Data_EmployeeNumber!$A$4:$E$4,0))+'Q12-Validation'!I76 -> 4 | J77: =SUM(F77:I77) -> 11
E78: Total Region Demand | J78: From Report
E79: Market Share by Region | J79: From Report
E80: Feight Cost | F80: 39.23 | G80: 0 | H80: 45.3 | I80: 57
B89: 3. Human Resource
B91: Cost Overview
B92: Salaries | C92: =I98 -> 304200 | E92: Base Salary | F92: {=INDIRECT("'Input_Q"&$B$3&"-Predict'!C50")} -> 5200 | H92: Base Salary | I92: salary per position | J92: Number of employee | K92: Multiplier | L92: Total For 1
B93: Training Investments | C93: =K103 -> 50000 | H93: Manager | I93: =$F$92*K93 -> 26000 | J93: 1 | K93: 5 | L93: =J93*K93 -> 5
B94: CSR. Investments | C94: =K104 -> 18000 | E94: Investment | H94: Operators | I94: =$F$92*K94 -> 5200 | J94: 35 | K94: 1 | L94: =J94*K94 -> 35
B95: Fringe Benefits Investments | C95: =K105 -> 47000 | E95: Training | F95: 10000 | H95: Supervisors | I95: =$F$92*K95 -> 13000 | J95: 3 | K95: 2.5 | L95: =J95*K95 -> 7.5
C96: =SUM(C92:C95) -> 419200 | E96: Unit | F96: {=INDIRECT("'Input_Q"&$B$3&"-Predict'!C51")} -> 5 | H96: Sellers | I96: =$F$92*K96 -> 5200 | J96: =J77 -> 11 | K96: 1 | L96: =J96*K96 -> 11
E97: CSR | F97: 2000 | H97: Total | I97: / | J97: =SUM(J93:J96) -> 50 | K97: / | L97: =SUM(L93:L96) -> 58.5
B98: Employee Satisfaction | E98: Unit | F98: {=INDIRECT("'Input_Q"&$B$3&"-Predict'!C52")} -> 9 | H98: Total Salary paid | I98: =L97*F92 -> 304200
H100: Other Investment and Expense
E101: Fringe Benefit | I101: Unit | J101: Number | K101: Total
E102: Dental | F102: 165 | H102: Salary | I102: =F92 -> 5200 | J102: =L97 -> 58.5 | K102: =I102*J102 -> 304200
E103: Food | F103: 175 | H103: Training | I103: =F95 -> 10000 | J103: =F96 -> 5 | K103: =F95*J103 -> 50000
E104: Tuition | F104: 400 | H104: CSR | I104: =F97 -> 2000 | J104: =F98 -> 9 | K104: =F97*J104 -> 18000
E105: Retirement | F105: 280 | H105: Fringe benefit | I105: =F102+F106+F107+F108 -> 940 | J105: =J97 -> 50 | K105: =I105*J105 -> 47000
E106: Medical | F106: 350 | K106: =SUM(K102:K105) -> 419200
E107: Life Insurance | F107: 135
E108: Transportation | F108: 290
B111: 4. Finance
B113: Contracted Loan | C113: 0
B114: Interest Rate | C114: 0
B115: Interest | C115: =C113*C114 -> 0
B116: Information Report Purchase | C116: {=INDIRECT("'Input_Q"&$B$3&"-Predict'!C53")} -> 150000
B120: Our income statement based on the predicted sales , not the planned sale
B123: Sales Income | C123: =IFERROR(VLOOKUP(B123,$B$14:$C$121,2,FALSE),0) -> 3728892
B124: COGS | C124: =IF(D124="Match",(C74+0.125)*C123+J73*M23,E124) -> 1390789.1 | D124: Not Match | E124: 1390789.1 | G124: DL | I124: =H124/$H$128 -> 0
B125: Gross Profit and Loss | C125: =C123-C124 -> 2338102.9 | G125: FC | H125: =SUMIF(D127:D139,"FC",C127:C139) -> 1871624.9 | I125: =H125/$H$128 -> 1430.9059
G126: COGS | H126: =C124 -> 1390789.1 | I126: =H126/$H$128 -> 1063.2944
B127: Production Fixed Cost | C127: =IF(B7="Overtime",560000,280000) -> 560000 | D127: FC | G127: Full Cost | H127: =SUM(H124:H126) -> 3262414
B128: Salaries | C128: =IF(B7="Overtime",VALUE(IFERROR(VLOOKUP(B128,$B$14:$C$121,2,FALSE),0))*2,VALUE(IFERROR(VLOOKUP(B128,$B$14:$C$121,2,FALSE),0))) -> 608400 | D128: FC | G128: Unit Sold | H128: =C76 -> 1308
...

Sheet Q12-Predict
B2: Which Quarter:
B3: 12
B4: For:
B5: Prediction
B6: Overtime?
B7: {=INDIRECT("'Input_Q"&B3&"-Predict'!C8")} -> Overtime
B9: From last Quarter
B10: Decicion Point
B11: Prediction
B14: 1. Operation
B16: Cost Overview
B17: Plant | C17: 0 | E17: Note: Raw material cost including the shipping fee related to each part
B18: Research & Development | C18: =F19*F20 -> 135000 | E18: Operation Cost Datasheet | I18: Q3 Order | K18: Type | L18: Unit Cost+Shipping | M18: Climatizer unit cost | N18: Order cost
B19: Raw Material | C19: =N23 -> 0 | E19: R&D | F19: 15000 | G19: /unit | J19: Packing | K19: Premium | L19: =VLOOKUP($K$19,$E$24:F59,2,FALSE) -> 36 | M19: =L19*$F$25 -> 36 | N19: =M19*$F$24 -> 0
B20: Raw Material Storage Costs | C20: =C34*0.02*M24 -> 1136.0868 | F20: {=INDIRECT("'Input_Q"&B3&"-Predict'!C38")} -> 9 | I20: Decision | J20: Plastic | K20: Superplast | L20: =VLOOKUP($K$20,$E$25:F60,2,FALSE) -> 44.52 | M20: =L20*$F$28 -> 89.04 | N20: =M20*$F$24 -> 0
B21: Production Fixed Cost | C21: 280000 | E21: MachineryModel | J21: Motor & Cooling | K21: Freezpro | L21: =VLOOKUP($K$21,$E$26:F63,2,FALSE) -> 187.2 | M21: =L21*$F$38 -> 374.4 | N21: =M21*$F$24 -> 0
C22: =SUM(C17:C21) -> 416136.09 | E22: Model1 | F22: 1300000 | J22: Electric | K22: Proline | L22: =VLOOKUP($K$22,$E$21:F60,2,FALSE) -> 24.15 | M22: =L22*$F$51 -> 72.45 | N22: =M22*$F$24 -> 0
E23: Model2 | F23: 1500000 | I23: unit climatizer cost | M23: =SUM(M19:M22) -> 571.89 | N23: =SUM(N19:N22) -> 0
E24: Raw Material | F24: {=INDIRECT("'Input_Q"&B3&"-Predict'!C36")} -> 0 | G24: # of climatizer RM | I24: Unit Value | M24: =M23-M19 -> 535.89 | N24: =M24*F24 -> 0
B25: Productivity | C25: {=IF(B5="Validation",'Q12-Predict'!C30/'Q12-Predict'!C29,INDIRECT("'Input_Q"&B3&"-Predict'!C34"))} -> 0.96 | E25: Packing | F25: 1 | G25: unit/climatizer
E26: Standard | F26: 20
B27: Climatizer Stock | C27: =INDEX(Data_Stock!B2:N11,MATCH("Left Inventory",Data_Stock!B2:B11,0),MATCH(VALUE(B3-1),Data_Stock!B2:N2,0)) -> 90 | E27: Premium | F27: 36
B28: Raw Material Available | C28: =INDEX(Data_Stock!B2:N11,MATCH("Left",Data_Stock!B2:B11,0),MATCH(VALUE(B3-1),Data_Stock!B2:N2,0)) -> 1545 | E28: Plastic | F28: 2 | G28: unit/climatizer
B29: Planned Production | C29: {=INDIRECT("'Input_Q"&B3&"-Predict'!C33")} -> 1483.2 | E29: Plastinjet | F29: =(1+F31)*F30 -> 43.2
B30: =IF(B5="Validation","Actual Production","Predict Production") -> Predict Production | C30: =INDEX(Data_Stock!B2:N11,MATCH("Produced",Data_Stock!B2:B11,0),MATCH(VALUE(B3),Data_Stock!B2:N2,0)) -> 1439 | E30: material | F30: 40
E31: Shipping | F31: 0.08
B32: Raw Material Left | E32: Superplast | F32: =(1+F34)*F33 -> 44.52
B33: Raw Material Purchased | C33: =F24 -> 0 | E33: material | F33: 42
B34: Raw Material Available for Q+1 | C34: =IF(B5="Validation",INDEX(Data_Stock!B2:N11,MATCH("Left",Data_Stock!B2:B11,0),MATCH('Q12-Predict'!B3,Data_Stock!B2:N2,0)),C28+F24-C30) -> 106 | E34: Shipping | F34: 0.06
B35: Total Inventory Value | C35: =C34*M24 -> 56804.34 | E35: IPLM | F35: =(1+F37)*F36 -> 56.1
E36: material | F36: 55
E37: Shipping | F37: 0.02
E38: Moter&Cooling | F38: 2 | G38: unit/climatizer
E39: Motojister | F39: =(1+F41)*F40 -> 117.7
E40: material | F40: 110
E41: Shipping | F41: 0.07
E42: Motormaster | F42: =(1+F44)*F43 -> 186.3
E43: material | F43: 162
E44: Shipping | F44: 0.15
E45: InfinityParts | F45: =(1+F47)*F46 -> 193.6
E46: material | F46: 176
E47: Shipping | F47: 0.1
E48: Freezpro | F48: =(1+F50)*F49 -> 187.2
E49: material | F49: 180
E50: Shipping | F50: 0.04
E51: ElectrocalKit | F51: 3 | G51: unit/climatizer
E52: Chukchuk | F52: =(1+F54)*F53 -> 21.6
E53: material | F53: 18
E54: Shipping | F54: 0.2
E55: ConduiteElec | F55: =(1+F57)*F56 -> 22
E56: material | F56: 20
E57: Shipping | F57: 0.1
E58: Proline | F58: =(1+F60)*F59 -> 24.15
E59: material | F59: 23
E60: Shipping | F60: 0.05
B65: 2. Market
B67: Cost Overview
B68: Sales Income | C68: =SUMPRODUCT(F73:I73,F71:I71) -> 4027186
B69: A&P Investiments | C69: =J75 -> 349088.82 | E69: =IF(B5="Validation","Actual S.C.R","Predict S.C.R") -> Predict S.C.R | F69: {=IF($B$5="Validation",F73/F72,INDIRECT("'Input_Q"&$B$3&"-Predict'!D29"))} -> 0.9 | G69: {=IF($B$5="Validation",G73/G72,INDIRECT("'Input_Q"&$B$3&"-Predict'!D30"))} -> 0.9 | H69: {=IF($B$5="Validation",H73/H72,INDIRECT("'Input_Q"&$B$3&"-Predict'!D31"))} -> 0.9 | I69: {=IF($B$5="Validation",I73/I72,INDIRECT("'Input_Q"&$B$3&"-Predict'!D32"))} -> 0.9
B70: Commision Total | C70: =C68*C74 -> 241631.16 | E70: Region | F70: 1 | G70: 2 | H70: 3 | I70: 4 | J70: Total
C71: =SUM(C68:C70) -> 4617906 | E71: Unit sale price | F71: {=INDIRECT("'Input_Q"&$B$3&"-Predict'!C10")} -> 2899 | G71: {=INDIRECT("'Input_Q"&$B$3&"-Predict'!C11")} -> 2599 | H71: {=INDIRECT("'Input_Q"&$B$3&"-Predict'!C12")} -> 2899 | I71: {=INDIRECT("'Input_Q"&$B$3&"-Predict'!C13")} -> 2899 | J71: /
E72: Planned Sale | F72: {=INDIRECT("'Input_Q"&$B$3&"-Predict'!C24")} -> 471 | G72: {=INDIRECT("'Input_Q"&$B$3&"-Predict'!C25")} -> 267 | H72: {=INDIRECT("'Input_Q"&$B$3&"-Predict'!C26")} -> 47 | I72: {=INDIRECT("'Input_Q"&$B$3&"-Predict'!C27")} -> 788 | J72: =SUM(F72:I72) -> 1573
E73: =IF(B5="Validation","Actual Sale","Predict Sale") -> Predict Sale | F73: =IF($E$73="Actual Sale",INDEX(Data_Sales!$B$3:$N$8,MATCH(F70,Data_Sales!$B$3:$B$8,0),MATCH($B$3,Data_Sales!$B$3:$N$3,0)),ROUNDDOWN(F69*F72,0)) -> 423 | G73: =IF($E$73="Actual Sale",INDEX(Data_Sales!$B$3:$N$8,MATCH(G70,Data_Sales!$B$3:$B$8,0),MATCH($B$3,Data_Sales!$B$3:$N$3,0)),ROUNDDOWN(G69*G72,0)) -> 240 | H73: =IF($E$73="Actual Sale",INDEX(Data_Sales!$B$3:$N$8,MATCH(H70,Data_Sales!$B$3:$B$8,0),MATCH($B$3,Data_Sales!$B$3:$N$3,0)),ROUNDDOWN(H69*H72,0)) -> 42 | I73: =IF($E$73="Actual Sale",INDEX(Data_Sales!$B$3:$N$8,MATCH(I70,Data_Sales!$B$3:$B$8,0),MATCH($B$3,Data_Sales!$B$3:$N$3,0)),ROUNDDOWN(I69*I72,0)) -> 709 | J73: =SUM(F73:I73) -> 1414
B74: Commision | C74: {=INDIRECT("'Input_Q"&B3&"-Predict'!C39")} -> 0.06 | E74: Advertisement unit | F74: {=INDIRECT("'Input_Q"&$B$3&"-Predict'!C41")} -> 7 | G74: {=INDIRECT("'Input_Q"&$B$3&"-Predict'!C42")} -> 10 | H74: {=INDIRECT("'Input_Q"&$B$3&"-Predict'!C43")} -> 1 | I74: {=INDIRECT("'Input_Q"&$B$3&"-Predict'!C44")} -> 8
B75: Planned sale | C75: =J72 -> 1573 | E75: A&P Investment | F75: =F72*F71*F74/100 -> 95580.03 | G75: =G72*G71*G74/100 -> 69393.3 | H75: =H72*H71*H74/100 -> 1362.53 | I75: =I72*I71*I74/100 -> 182752.96 | J75: =SUM(F75:I75) -> 349088.82
B76: Predicted sale | C76: =J73 -> 1414 | E76: New Hired sales | F76: {=INDIRECT("'Input_Q"&$B$3&"-Predict'!C46")} -> 0 | G76: {=INDIRECT("'Input_Q"&$B$3&"-Predict'!C47")} -> 0 | H76: {=INDIRECT("'Input_Q"&$B$3&"-Predict'!C48")} -> 0 | I76: {=INDIRECT("'Input_Q"&$B$3&"-Predict'!C49")} -> 0 | J76: /
B77: left finished good | C77: =C75-C76 -> 159 | E77: Active Sales Force | F77: =INDEX(Data_EmployeeNumber!$A$4:$E$16,MATCH('Q12-Predict'!$B$3-1,Data_EmployeeNumber!$A$4:$A$16,0),MATCH('Q12-Predict'!F70,Data_EmployeeNumber!$A$4:$E$4,0))+'Q12-Predict'!F76 -> 3 | G77: =INDEX(Data_EmployeeNumber!$A$4:$E$16,MATCH('Q12-Predict'!$B$3-1,Data_EmployeeNumber!$A$4:$A$16,0),MATCH('Q12-Predict'!G70,Data_EmployeeNumber!$A$4:$E$4,0))+'Q12-Predict'!G76 -> 3 | H77: =INDEX(Data_EmployeeNumber!$A$4:$E$16,MATCH('Q12-Predict'!$B$3-1,Data_EmployeeNumber!$A$4:$A$16,0),MATCH('Q12-Predict'!H70,Data_EmployeeNumber!$A$4:$E$4,0))+'Q12-Predict'!H76 -> 1 | I77: =INDEX(Data_EmployeeNumber!$A$4:$E$16,MATCH('Q12-Predict'!$B$3-1,Data_EmployeeNumber!$A$4:$A$16,0),MATCH('Q12-Predict'!I70,Data_EmployeeNumber!$A$4:$E$4,0))+'Q12-Predict'!I76 -> 4 | J77: =SUM(F77:I77) -> 11
E78: Total Region Demand | J78: From Report
E79: Market Share by Region | J79: From Report
E80: Feight Cost | F80: 39.23 | G80: 0 | H80: 45.3 | I80: 57
B89: 3. Human Resource
B91: Cost Overview
B92: Salaries | C92: =I98 -> 304200 | E92: Base Salary | F92: {=INDIRECT("'Input_Q"&$B$3&"-Predict'!C50")} -> 5200 | H92: Base Salary | I92: salary per position | J92: Number of employee | K92: Multiplier | L92: Total For 1
B93: Training Investments | C93: =K103 -> 50000 | H93: Manager | I93: =$F$92*K93 -> 26000 | J93: 1 | K93: 5 | L93: =J93*K93 -> 5
B94: CSR. Investments | C94: =K104 -> 18000 | E94: Investment | H94: Operators | I94: =$F$92*K94 -> 5200 | J94: 35 | K94: 1 | L94: =J94*K94 -> 35
B95: Fringe Benefits Investments | C95: =K105 -> 47000 | E95: Training | F95: 10000 | H95: Supervisors | I95: =$F$92*K95 -> 13000 | J95: 3 | K95: 2.5 | L95: =J95*K95 -> 7.5
C96: =SUM(C92:C95) -> 419200 | E96: Unit | F96: {=INDIRECT("'Input_Q"&$B$3&"-Predict'!C51")} -> 5 | H96: Sellers | I96: =$F$92*K96 -> 5200 | J96: =J77 -> 11 | K96: 1 | L96: =J96*K96 -> 11
E97: CSR | F97: 2000 | H97: Total | I97: / | J97: =SUM(J93:J96) -> 50 | K97: / | L97: =SUM(L93:L96) -> 58.5
B98: Employee Satisfaction | E98: Unit | F98: {=INDIRECT("'Input_Q"&$B$3&"-Predict'!C52")} -> 9 | H98: Total Salary paid | I98: =L97*F92 -> 304200
H100: Other Investment and Expense
E101: Fringe Benefit | I101: Unit | J101: Number | K101: Total
E102: Dental | F102: 165 | H102: Salary | I102: =F92 -> 5200 | J102: =L97 -> 58.5 | K102: =I102*J102 -> 304200
E103: Food | F103: 175 | H103: Training | I103: =F95 -> 10000 | J103: =F96 -> 5 | K103: =F95*J103 -> 50000
E104: Tuition | F104: 400 | H104: CSR | I104: =F97 -> 2000 | J104: =F98 -> 9 | K104: =F97*J104 -> 18000
E105: Retirement | F105: 280 | H105: Fringe benefit | I105: =F102+F106+F107+F108 -> 940 | J105: =J97 -> 50 | K105: =I105*J105 -> 47000
E106: Medical | F106: 350 | K106: =SUM(K102:K105) -> 419200
E107: Life Insurance | F107: 135
E108: Transportation | F108: 290
B111: 4. Finance
B113: Contracted Loan | C113: 0
B114: Interest Rate | C114: 0
B115: Interest | C115: =C113*C114 -> 0
B116: Information Report Purchase | C116: {=INDIRECT("'Input_Q"&$B$3&"-Predict'!C53")} -> 150000
B120: Our income statement based on the predicted sales , not the planned sale
B123: Sales Income | C123: =IFERROR(VLOOKUP(B123,$B$14:$C$121,2,FALSE),0) -> 4027186
B124: COGS | C124: =IF(D124="Match",(C74+0.125)*C123+J73*M23,E124) -> 1965430.8 | D124: Not Match | E124: 1965430.8 | G124: DL | I124: =H124/$H$128 -> 0
B125: Gross Profit and Loss | C125: =C123-C124 -> 2061755.2 | G125: FC | H125: =SUMIF(D127:D139,"FC",C127:C139) -> 1871624.9 | I125: =H125/$H$128 -> 1323.6385
G126: COGS | H126: =C124 -> 1965430.8 | I126: =H126/$H$128 -> 1389.9793
B127: Production Fixed Cost | C127: =IF(B7="Overtime",560000,280000) -> 560000 | D127: FC | G127: Full Cost | H127: =SUM(H124:H126) -> 3837055.7
B128: Salaries | C128: =IF(B7="Overtime",VALUE(IFERROR(VLOOKUP(B128,$B$14:$C$121,2,FALSE),0))*2,VALUE(IFERROR(VLOOKUP(B128,$B$14:$C$121,2,FALSE),0))) -> 608400 | D128: FC | G128: Unit Sold | H128: =C76 -> 1414
...

Sheet Input_Q12-Predict
B1: Preparasion for next quarter prediction
B2: TRUE | C2: 1. Validate data from previous quarter ( By QingQing)
B3: TRUE | C3: 2. Update Data_ Sheets( Need cash flow update By Seb)
B4: TRUE | C4: 3.Create new prediction sheet for new quarter+ Validation ( QingQing)
B5: TRUE | C5: 4. Choose the Number of current quarter in B6
B6: Quarter | C6: 12
B7: Strategy | C7: Maximum Capacity | E7: Note: Conservasive strategy have a constrain which will only keep the next quarter RM unit =1200
B8: Working Hour | C8: Overtime
B9: SalePrice | F9: Predicted Sale
B10: 1 | C10: 2899 | F10: =C28 -> 0
B11: 2 | C11: 2599 | F11: BreakEven unit
B12: 3 | C12: 2899 | F12: {=INDIRECT("'Q"&C6&"-Predict'!C165")} -> 1357
B13: 4 | C13: 2899 | F13: =IF(F12>F10,"Need Adjustment","All Good") -> Need Adjustment
B14: NET PROFIT / LOSS | C14: {=INDIRECT("'Q"&C6&"-Predict'!C149")} -> 71587.377
B15: PROFIT AND LOSS STATEMENT RESULTS | C15: {=INDIRECT("'Q"&C6&"-Predict'!C154")} -> 1998746.5
B17: Previous Quarter balance | C17: =INDEX(Data_IncomeStatement!A1:M33,MATCH("PROFIT AND LOSS STATEMENT RESULTS", Data_IncomeStatement!A1:A33, 0),MATCH(VALUE(C6-1), Data_IncomeStatement!A1:M1, 0)) -> 1927159.1 | E17: DO NOT CHANGE THIS CELL!!
B18: Loan interest | C18: 0 | E18: Given
B19: Climatizer Stock | C19: =INDEX(Data_Stock!B2:N11,MATCH("Left Inventory",Data_Stock!B2:B11,0),MATCH(VALUE(C6-1),Data_Stock!B2:N2,0)) -> 90 | E19: DO NOT CHANGE THIS CELL!!
B20: Raw Material Available | C20: =INDEX(Data_Stock!B2:N11,MATCH("Left",Data_Stock!B2:B11,0),MATCH(VALUE(C6-1),Data_Stock!B2:N2,0)) -> 1545 | E20: DO NOT CHANGE THIS CELL!!
B21: Maximum Sell unit | C21: =IF(C8="Overtime",MIN((1560*C34+C19),(C19+(C20*C34))),MIN((1200*C34+C19),(C19+(C20*C34)))) -> 1573.2
B22: Plan to Sell | C22: =C21 -> 1573.2 | E22: # Prediction based on the demand
B23: ="----------------------------------------------->>" -> ----------------------------------------------->> | C23: =MIN(C22,C21) -> 1573.2 | E23: #Capped by the maximum sell unit
B24: 1 | C24: =ROUNDDOWN($C$23*D24,0) -> 471 | D24: 0.3 | E24: # Plan to have more market share
B25: 2 | C25: =ROUNDDOWN($C$23*D25,0) -> 267 | D25: 0.17 | E25: # Focus
B26: 3 | C26: =ROUNDDOWN($C$23*D26,0) -> 47 | D26: =1-D27-D25-D24 -> 0.03
B27: 4 | C27: 788 | D27: 0.5 | E27: # Leader | F27: =C23-C24-C25-C26 -> 788.2
B28: Predicted Sale | E28: #Based on the predicted conversion rate
B29: 1 | C29: =ROUNDDOWN(C24*D29,0) -> 423 | D29: 0.9
B30: 2 | C30: =ROUNDDOWN(C25*D30,0) -> 240 | D30: 0.9
B31: 3 | C31: =ROUNDDOWN(C26*D31,0) -> 42 | D31: 0.9
B32: 4 | C32: =ROUNDDOWN(C27*D32,0) -> 709 | D32: 0.9
B33: Plan to produce | C33: =C23-C19 -> 1483.2 | E33: # = plan to sale - finish good stock
B34: Productivity | C34: 0.96
B35: Predicted Produced | C35: =ROUNDDOWN(C33*C34,0) -> 1423
B36: Raw Material to purchase | C36: 0
B37: ="------------------------------->" -> -------------------------------> | C37: =IF(C7="Conservasive",1200-(C20-C35),C36) -> 0 | E37: # = 1200 - (Raw material available - real produce)
B38: R&D | C38: 9
B39: Commision | C39: 0.06
B40: Advertisement | C40: Level
B41: 1 | C41: 7
B42: 2 | C42: 10
B43: 3 | C43: 1
B44: 4 | C44: 8
B45: New Hire
B46: 1 | C46: 0
B47: 2 | C47: 0
B48: 3 | C48: 0
B49: 4 | C49: 0
B50: Base Salary | C50: 5200
B51: Training | C51: 5
B52: C&R | C52: 9
B53: Total information | C53: 150000 | E53: #Manually Calculate+input

Sheet Q11-Validation
B2: Which Quarter:
B3: 11
B4: For:
B5: Validation
B6: Overtime?
B7: {=INDIRECT("'Input_Q"&B3&"-Predict'!C8")} -> Overtime
B9: From last Quarter
B10: Decicion Point
B11: Prediction
B14: 1. Operation
B16: Cost Overview
B17: Plant | C17: 0 | E17: Note: Raw material cost including the shipping fee related to each part
B18: Research & Development | C18: =F19*F20 -> 135000 | E18: Operation Cost Datasheet | I18: Q3 Order | K18: Type | L18: Unit Cost+Shipping | M18: Climatizer unit cost | N18: Order cost
B19: Raw Material | C19: =N23 -> 609634.74 | E19: R&D | F19: 15000 | G19: /unit | J19: Packing | K19: Premium | L19: =VLOOKUP($K$19,$E$24:F59,2,FALSE) -> 36 | M19: =L19*$F$25 -> 36 | N19: =M19*$F$24 -> 38376
B20: Raw Material Storage Costs | C20: =C34*0.02*M24 -> 16559.001 | F20: {=INDIRECT("'Input_Q"&B3&"-Predict'!C38")} -> 9 | I20: Decision | J20: Plastic | K20: Superplast | L20: =VLOOKUP($K$20,$E$25:F60,2,FALSE) -> 44.52 | M20: =L20*$F$28 -> 89.04 | N20: =M20*$F$24 -> 94916.64
B21: Production Fixed Cost | C21: 280000 | E21: MachineryModel | J21: Motor & Cooling | K21: Freezpro | L21: =VLOOKUP($K$21,$E$26:F63,2,FALSE) -> 187.2 | M21: =L21*$F$38 -> 374.4 | N21: =M21*$F$24 -> 399110.4
C22: =SUM(C17:C21) -> 1041193.7 | E22: Model1 | F22: 1300000 | J22: Electric | K22: Proline | L22: =VLOOKUP($K$22,$E$21:F60,2,FALSE) -> 24.15 | M22: =L22*$F$51 -> 72.45 | N22: =M22*$F$24 -> 77231.7
E23: Model2 | F23: 1500000 | I23: unit climatizer cost | M23: =SUM(M19:M22) -> 571.89 | N23: =SUM(N19:N22) -> 609634.74
E24: Raw Material | F24: {=INDIRECT("'Input_Q"&B3&"-Predict'!C36")} -> 1066 | G24: # of climatizer RM | I24: Unit Value | M24: =M23-M19 -> 535.89 | N24: =M24*F24 -> 571258.74
B25: Productivity | C25: {=IF(B5="Validation",'Q11-Validation'!C30/'Q11-Validation'!C29,INDIRECT("'Input_Q"&B3&"-Predict'!C34"))} -> 1.0102831 | E25: Packing | F25: 1 | G25: unit/climatizer
E26: Standard | F26: 20
B27: Climatizer Stock | C27: =INDEX(Data_Stock!B2:N11,MATCH("Left Inventory",Data_Stock!B2:B11,0),MATCH(VALUE(B3-1),Data_Stock!B2:N2,0)) -> 427 | E27: Premium | F27: 36
B28: Raw Material Available | C28: =INDEX(Data_Stock!B2:N11,MATCH("Left",Data_Stock!B2:B11,0),MATCH(VALUE(B3-1),Data_Stock!B2:N2,0)) -> 1992 | E28: Plastic | F28: 2 | G28: unit/climatizer
B29: Planned Production | C29: {=INDIRECT("'Input_Q"&B3&"-Predict'!C33")} -> 1497.6 | E29: Plastinjet | F29: =(1+F31)*F30 -> 43.2
B30: =IF(B5="Validation","Actual Production","Predict Production") -> Actual Production | C30: =INDEX(Data_Stock!B2:N11,MATCH("Produced",Data_Stock!B2:B11,0),MATCH(VALUE(B3),Data_Stock!B2:N2,0)) -> 1513 | E30: material | F30: 40
E31: Shipping | F31: 0.08
B32: Raw Material Left | E32: Superplast | F32: =(1+F34)*F33 -> 44.52
B33: Raw Material Purchased | C33: =F24 -> 1066 | E33: material | F33: 42
B34: Raw Material Available for Q+1 | C34: =IF(B5="Validation",INDEX(Data_Stock!B2:N11,MATCH("Left",Data_Stock!B2:B11,0),MATCH('Q11-Validation'!B3,Data_Stock!B2:N2,0)),C28+F24-C30) -> 1545 | E34: Shipping | F34: 0.06
B35: Total Inventory Value | C35: =C34*M24 -> 827950.05 | E35: IPLM | F35: =(1+F37)*F36 -> 56.1
E36: material | F36: 55
E37: Shipping | F37: 0.02
E38: Moter&Cooling | F38: 2 | G38: unit/climatizer
E39: Motojister | F39: =(1+F41)*F40 -> 117.7
E40: material | F40: 110
E41: Shipping | F41: 0.07
E42: Motormaster | F42: =(1+F44)*F43 -> 186.3
E43: material | F43: 162
E44: Shipping | F44: 0.15
E45: InfinityParts | F45: =(1+F47)*F46 -> 193.6
E46: material | F46: 176
E47: Shipping | F47: 0.1
E48: Freezpro | F48: =(1+F50)*F49 -> 187.2
E49: material | F49: 180
E50: Shipping | F50: 0.04
E51: ElectrocalKit | F51: 3 | G51: unit/climatizer
E52: Chukchuk | F52: =(1+F54)*F53 -> 21.6
E53: material | F53: 18
E54: Shipping | F54: 0.2
E55: ConduiteElec | F55: =(1+F57)*F56 -> 22
E56: material | F56: 20
E57: Shipping | F57: 0.1
E58: Proline | F58: =(1+F60)*F59 -> 24.15
E59: material | F59: 23
E60: Shipping | F60: 0.05
B65: 2. Market
B67: Cost Overview
B68: Sales Income | C68: =SUMPRODUCT(F73:I73,F71:I71) -> 5265050
B69: A&P Investiments | C69: =J75 -> 427301.22 | E69: =IF(B5="Validation","Actual S.C.R","Predict S.C.R") -> Actual S.C.R | F69: {=IF($B$5="Validation",F73/F72,INDIRECT("'Input_Q"&$B$3&"-Predict'!D29"))} -> 1 | G69: {=IF($B$5="Validation",G73/G72,INDIRECT("'Input_Q"&$B$3&"-Predict'!D30"))} -> 1 | H69: {=IF($B$5="Validation",H73/H72,INDIRECT("'Input_Q"&$B$3&"-Predict'!D31"))} -> 1 | I69: {=IF($B$5="Validation",I73/I72,INDIRECT("'Input_Q"&$B$3&"-Predict'!D32"))} -> 0.92219917
B70: Commision Total | C70: =C68*C74 -> 315903 | E70: Region | F70: 1 | G70: 2 | H70: 3 | I70: 4 | J70: Total
C71: =SUM(C68:C70) -> 6008254.2 | E71: Unit sale price | F71: {=INDIRECT("'Input_Q"&$B$3&"-Predict'!C10")} -> 2899 | G71: {=INDIRECT("'Input_Q"&$B$3&"-Predict'!C11")} -> 2599 | H71: {=INDIRECT("'Input_Q"&$B$3&"-Predict'!C12")} -> 2899 | I71: {=INDIRECT("'Input_Q"&$B$3&"-Predict'!C13")} -> 2899 | J71: /
E72: Planned Sale | F72: {=INDIRECT("'Input_Q"&$B$3&"-Predict'!C24")} -> 577 | G72: {=INDIRECT("'Input_Q"&$B$3&"-Predict'!C25")} -> 327 | H72: {=INDIRECT("'Input_Q"&$B$3&"-Predict'!C26")} -> 57 | I72: {=INDIRECT("'Input_Q"&$B$3&"-Predict'!C27")} -> 964 | J72: =SUM(F72:I72) -> 1925
E73: =IF(B5="Validation","Actual Sale","Predict Sale") -> Actual Sale | F73: =IF($E$73="Actual Sale",INDEX(Data_Sales!$B$3:$N$8,MATCH(F70,Data_Sales!$B$3:$B$8,0),MATCH($B$3,Data_Sales!$B$3:$N$3,0)),ROUNDDOWN(F69*F72,0)) -> 577 | G73: =IF($E$73="Actual Sale",INDEX(Data_Sales!$B$3:$N$8,MATCH(G70,Data_Sales!$B$3:$B$8,0),MATCH($B$3,Data_Sales!$B$3:$N$3,0)),ROUNDDOWN(G69*G72,0)) -> 327 | H73: =IF($E$73="Actual Sale",INDEX(Data_Sales!$B$3:$N$8,MATCH(H70,Data_Sales!$B$3:$B$8,0),MATCH($B$3,Data_Sales!$B$3:$N$3,0)),ROUNDDOWN(H69*H72,0)) -> 57 | I73: =IF($E$73="Actual Sale",INDEX(Data_Sales!$B$3:$N$8,MATCH(I70,Data_Sales!$B$3:$B$8,0),MATCH($B$3,Data_Sales!$B$3:$N$3,0)),ROUNDDOWN(I69*I72,0)) -> 889 | J73: =SUM(F73:I73) -> 1850
B74: Commision | C74: {=INDIRECT("'Input_Q"&B3&"-Predict'!C39")} -> 0.06 | E74: Advertisement unit | F74: {=INDIRECT("'Input_Q"&$B$3&"-Predict'!C41")} -> 7 | G74: {=INDIRECT("'Input_Q"&$B$3&"-Predict'!C42")} -> 10 | H74: {=INDIRECT("'Input_Q"&$B$3&"-Predict'!C43")} -> 1 | I74: {=INDIRECT("'Input_Q"&$B$3&"-Predict'!C44")} -> 8
B75: Planned sale | C75: =J72 -> 1925 | E75: A&P Investment | F75: =F72*F71*F74/100 -> 117090.61 | G75: =G72*G71*G74/100 -> 84987.3 | H75: =H72*H71*H74/100 -> 1652.43 | I75: =I72*I71*I74/100 -> 223570.88 | J75: =SUM(F75:I75) -> 427301.22
B76: Predicted sale | C76: =J73 -> 1850 | E76: New Hired sales | F76: {=INDIRECT("'Input_Q"&$B$3&"-Predict'!C46")} -> 0 | G76: {=INDIRECT("'Input_Q"&$B$3&"-Predict'!C47")} -> 0 | H76: {=INDIRECT("'Input_Q"&$B$3&"-Predict'!C48")} -> 0 | I76: {=INDIRECT("'Input_Q"&$B$3&"-Predict'!C49")} -> 0 | J76: /
B77: left finished good | C77: =C75-C76 -> 75 | E77: Active Sales Force | F77: =INDEX(Data_EmployeeNumber!$A$4:$E$16,MATCH('Q11-Validation'!$B$3-1,Data_EmployeeNumber!$A$4:$A$16,0),MATCH('Q11-Validation'!F70,Data_EmployeeNumber!$A$4:$E$4,0))+'Q11-Validation'!F76 -> 3 | G77: =INDEX(Data_EmployeeNumber!$A$4:$E$16,MATCH('Q11-Validation'!$B$3-1,Data_EmployeeNumber!$A$4:$A$16,0),MATCH('Q11-Validation'!G70,Data_EmployeeNumber!$A$4:$E$4,0))+'Q11-Validation'!G76 -> 3 | H77: =INDEX(Data_EmployeeNumber!$A$4:$E$16,MATCH('Q11-Validation'!$B$3-1,Data_EmployeeNumber!$A$4:$A$16,0),MATCH('Q11-Validation'!H70,Data_EmployeeNumber!$A$4:$E$4,0))+'Q11-Validation'!H76 -> 1 | I77: =INDEX(Data_EmployeeNumber!$A$4:$E$16,MATCH('Q11-Validation'!$B$3-1,Data_EmployeeNumber!$A$4:$A$16,0),MATCH('Q11-Validation'!I70,Data_EmployeeNumber!$A$4:$E$4,0))+'Q11-Validation'!I76 -> 4 | J77: =SUM(F77:I77) -> 11
E78: Total Region Demand | J78: From Report
E79: Market Share by Region | J79: From Report
E80: Feight Cost | F80: 39.23 | G80: 0 | H80: 45.3 | I80: 57
B89: 3. Human Resource
B91: Cost Overview
B92: Salaries | C92: =I98 -> 304200 | E92: Base Salary | F92: {=INDIRECT("'Input_Q"&$B$3&"-Predict'!C50")} -> 5200 | H92: Base Salary | I92: salary per position | J92: Number of employee | K92: Multiplier | L92: Total For 1
B93: Training Investments | C93: =K103 -> 50000 | H93: Manager | I93: =$F$92*K93 -> 26000 | J93: 1 | K93: 5 | L93: =J93*K93 -> 5
B94: CSR. Investments | C94: =K104 -> 18000 | E94: Investment | H94: Operators | I94: =$F$92*K94 -> 5200 | J94: 35 | K94: 1 | L94: =J94*K94 -> 35
B95: Fringe Benefits Investments | C95: =K105 -> 47000 | E95: Training | F95: 10000 | H95: Supervisors | I95: =$F$92*K95 -> 13000 | J95: 3 | K95: 2.5 | L95: =J95*K95 -> 7.5
C96: =SUM(C92:C95) -> 419200 | E96: Unit | F96: {=INDIRECT("'Input_Q"&$B$3&"-Predict'!C51")} -> 5 | H96: Sellers | I96: =$F$92*K96 -> 5200 | J96: =J77 -> 11 | K96: 1 | L96: =J96*K96 -> 11
E97: CSR | F97: 2000 | H97: Total | I97: / | J97: =SUM(J93:J96) -> 50 | K97: / | L97: =SUM(L93:L96) -> 58.5
B98: Employee Satisfaction | E98: Unit | F98: {=INDIRECT("'Input_Q"&$B$3&"-Predict'!C52")} -> 9 | H98: Total Salary paid | I98: =L97*F92 -> 304200
H100: Other Investment and Expense
E101: Fringe Benefit | I101: Unit | J101: Number | K101: Total
E102: Dental | F102: 165 | H102: Salary | I102: =F92 -> 5200 | J102: =L97 -> 58.5 | K102: =I102*J102 -> 304200
E103: Food | F103: 175 | H103: Training | I103: =F95 -> 10000 | J103: =F96 -> 5 | K103: =F95*J103 -> 50000
E104: Tuition | F104: 400 | H104: CSR | I104: =F97 -> 2000 | J104: =F98 -> 9 | K104: =F97*J104 -> 18000
E105: Retirement | F105: 280 | H105: Fringe benefit | I105: =F102+F106+F107+F108 -> 940 | J105: =J97 -> 50 | K105: =I105*J105 -> 47000
E106: Medical | F106: 350 | K106: =SUM(K102:K105) -> 419200
E107: Life Insurance | F107: 135
E108: Transportation | F108: 290
B111: 4. Finance
B113: Contracted Loan | C113: 0
B114: Interest Rate | C114: 0
B115: Interest | C115: =C113*C114 -> 0
B116: Information Report Purchase | C116: {=INDIRECT("'Input_Q"&$B$3&"-Predict'!C53")} -> 80000
B120: Our income statement based on the predicted sales , not the planned sale
B123: Sales Income | C123: =IFERROR(VLOOKUP(B123,$B$14:$C$121,2,FALSE),0) -> 5265050
B124: COGS | C124: =IF(D124="Match",(C74+0.125)*C123+J73*M23,E124) -> 1965430.8 | D124: Not Match | E124: 1965430.8 | G124: DL | I124: =H124/$H$128 -> 0
B125: Gross Profit and Loss | C125: =C123-C124 -> 3299619.2 | G125: FC | H125: =SUMIF(D127:D139,"FC",C127:C139) -> 1895260.2 | I125: =H125/$H$128 -> 1024.465
G126: COGS | H126: =C124 -> 1965430.8 | I126: =H126/$H$128 -> 1062.395
B127: Production Fixed Cost | C127: =IF(B7="Overtime",560000,280000) -> 560000 | D127: FC | G127: Full Cost | H127: =SUM(H124:H126) -> 3860691
B128: Salaries | C128: =IF(B7="Overtime",VALUE(IFERROR(VLOOKUP(B128,$B$14:$C$121,2,FALSE),0))*2,VALUE(IFERROR(VLOOKUP(B128,$B$14:$C$121,2,FALSE),0))) -> 608400 | D128: FC | G128: Unit Sold | H128: =C76 -> 1850
...

Sheet Q11-Predict
B2: Which Quarter:
B3: 11
B4: For:
B5: Prediction
B6: Overtime?
B7: {=INDIRECT("'Input_Q"&B3&"-Predict'!C8")} -> Overtime
B9: From last Quarter
B10: Decicion Point
B11: Prediction
B14: 1. Operation
B16: Cost Overview
B17: Plant | C17: 0 | E17: Note: Raw material cost including the shipping fee related to each part
B18: Research & Development | C18: =F19*F20 -> 135000 | E18: Operation Cost Datasheet | I18: Q3 Order | K18: Type | L18: Unit Cost+Shipping | M18: Climatizer unit cost | N18: Order cost
B19: Raw Material | C19: =N23 -> 609634.74 | E19: R&D | F19: 15000 | G19: /unit | J19: Packing | K19: Premium | L19: =VLOOKUP($K$19,$E$24:F59,2,FALSE) -> 36 | M19: =L19*$F$25 -> 36 | N19: =M19*$F$24 -> 38376
B20: Raw Material Storage Costs | C20: =C34*0.02*M24 -> 16559.001 | F20: {=INDIRECT("'Input_Q"&B3&"-Predict'!C38")} -> 9 | I20: Decision | J20: Plastic | K20: Superplast | L20: =VLOOKUP($K$20,$E$25:F60,2,FALSE) -> 44.52 | M20: =L20*$F$28 -> 89.04 | N20: =M20*$F$24 -> 94916.64
B21: Production Fixed Cost | C21: 280000 | E21: MachineryModel | J21: Motor & Cooling | K21: Freezpro | L21: =VLOOKUP($K$21,$E$26:F63,2,FALSE) -> 187.2 | M21: =L21*$F$38 -> 374.4 | N21: =M21*$F$24 -> 399110.4
C22: =SUM(C17:C21) -> 1041193.7 | E22: Model1 | F22: 1300000 | J22: Electric | K22: Proline | L22: =VLOOKUP($K$22,$E$21:F60,2,FALSE) -> 24.15 | M22: =L22*$F$51 -> 72.45 | N22: =M22*$F$24 -> 77231.7
E23: Model2 | F23: 1500000 | I23: unit climatizer cost | M23: =SUM(M19:M22) -> 571.89 | N23: =SUM(N19:N22) -> 609634.74
E24: Raw Material | F24: {=INDIRECT("'Input_Q"&B3&"-Predict'!C36")} -> 1066 | G24: # of climatizer RM | I24: Unit Value | M24: =M23-M19 -> 535.89 | N24: =M24*F24 -> 571258.74
B25: Productivity | C25: {=IF(B5="Validation",'Q11-Predict'!C30/'Q11-Predict'!C29,INDIRECT("'Input_Q"&B3&"-Predict'!C34"))} -> 0.96 | E25: Packing | F25: 1 | G25: unit/climatizer
E26: Standard | F26: 20
B27: Climatizer Stock | C27: =INDEX(Data_Stock!B2:N11,MATCH("Left Inventory",Data_Stock!B2:B11,0),MATCH(VALUE(B3-1),Data_Stock!B2:N2,0)) -> 427 | E27: Premium | F27: 36
B28: Raw Material Available | C28: =INDEX(Data_Stock!B2:N11,MATCH("Left",Data_Stock!B2:B11,0),MATCH(VALUE(B3-1),Data_Stock!B2:N2,0)) -> 1992 | E28: Plastic | F28: 2 | G28: unit/climatizer
B29: Planned Production | C29: {=INDIRECT("'Input_Q"&B3&"-Predict'!C33")} -> 1497.6 | E29: Plastinjet | F29: =(1+F31)*F30 -> 43.2
B30: =IF(B5="Validation","Actual Production","Predict Production") -> Predict Production | C30: =INDEX(Data_Stock!B2:N11,MATCH("Produced",Data_Stock!B2:B11,0),MATCH(VALUE(B3),Data_Stock!B2:N2,0)) -> 1513 | E30: material | F30: 40
E31: Shipping | F31: 0.08
B32: Raw Material Left | E32: Superplast | F32: =(1+F34)*F33 -> 44.52
B33: Raw Material Purchased | C33: =F24 -> 1066 | E33: material | F33: 42
B34: Raw Material Available for Q+1 | C34: =IF(B5="Validation",INDEX(Data_Stock!B2:N11,MATCH("Left",Data_Stock!B2:B11,0),MATCH('Q11-Predict'!B3,Data_Stock!B2:N2,0)),C28+F24-C30) -> 1545 | E34: Shipping | F34: 0.06
B35: Total Inventory Value | C35: =C34*M24 -> 827950.05 | E35: IPLM | F35: =(1+F37)*F36 -> 56.1
E36: material | F36: 55
E37: Shipping | F37: 0.02
E38: Moter&Cooling | F38: 2 | G38: unit/climatizer
E39: Motojister | F39: =(1+F41)*F40 -> 117.7
E40: material | F40: 110
E41: Shipping | F41: 0.07
E42: Motormaster | F42: =(1+F44)*F43 -> 186.3
E43: material | F43: 162
E44: Shipping | F44: 0.15
E45: InfinityParts | F45: =(1+F47)*F46 -> 193.6
E46: material | F46: 176
E47: Shipping | F47: 0.1
E48: Freezpro | F48: =(1+F50)*F49 -> 187.2
E49: material | F49: 180
E50: Shipping | F50: 0.04
E51: ElectrocalKit | F51: 3 | G51: unit/climatizer
E52: Chukchuk | F52: =(1+F54)*F53 -> 21.6
E53: material | F53: 18
E54: Shipping | F54: 0.2
E55: ConduiteElec | F55: =(1+F57)*F56 -> 22
E56: material | F56: 20
E57: Shipping | F57: 0.1
E58: Proline | F58: =(1+F60)*F59 -> 24.15
E59: material | F59: 23
E60: Shipping | F60: 0.05
B65: 2. Market
B67: Cost Overview
B68: Sales Income | C68: =SUMPRODUCT(F73:I73,F71:I71) -> 4106858
B69: A&P Investiments | C69: =J75 -> 427301.22 | E69: =IF(B5="Validation","Actual S.C.R","Predict S.C.R") -> Predict S.C.R | F69: {=IF($B$5="Validation",F73/F72,INDIRECT("'Input_Q"&$B$3&"-Predict'!D29"))} -> 0.75 | G69: {=IF($B$5="Validation",G73/G72,INDIRECT("'Input_Q"&$B$3&"-Predict'!D30"))} -> 0.75 | H69: {=IF($B$5="Validation",H73/H72,INDIRECT("'Input_Q"&$B$3&"-Predict'!D31"))} -> 0.75 | I69: {=IF($B$5="Validation",I73/I72,INDIRECT("'Input_Q"&$B$3&"-Predict'!D32"))} -> 0.75
B70: Commision Total | C70: =C68*C74 -> 246411.48 | E70: Region | F70: 1 | G70: 2 | H70: 3 | I70: 4 | J70: Total
C71: =SUM(C68:C70) -> 4780570.7 | E71: Unit sale price | F71: {=INDIRECT("'Input_Q"&$B$3&"-Predict'!C10")} -> 2899 | G71: {=INDIRECT("'Input_Q"&$B$3&"-Predict'!C11")} -> 2599 | H71: {=INDIRECT("'Input_Q"&$B$3&"-Predict'!C12")} -> 2899 | I71: {=INDIRECT("'Input_Q"&$B$3&"-Predict'!C13")} -> 2899 | J71: /
E72: Planned Sale | F72: {=INDIRECT("'Input_Q"&$B$3&"-Predict'!C24")} -> 577 | G72: {=INDIRECT("'Input_Q"&$B$3&"-Predict'!C25")} -> 327 | H72: {=INDIRECT("'Input_Q"&$B$3&"-Predict'!C26")} -> 57 | I72: {=INDIRECT("'Input_Q"&$B$3&"-Predict'!C27")} -> 964 | J72: =Archived_Testing_Q5!B19 -> 1600
E73: =IF(B5="Validation","Actual Sale","Predict Sale") -> Predict Sale | F73: =IF($E$73="Actual Sale",INDEX(Data_Sales!$B$3:$N$8,MATCH(F70,Data_Sales!$B$3:$B$8,0),MATCH($B$3,Data_Sales!$B$3:$N$3,0)),ROUNDDOWN(F69*F72,0)) -> 432 | G73: =IF($E$73="Actual Sale",INDEX(Data_Sales!$B$3:$N$8,MATCH(G70,Data_Sales!$B$3:$B$8,0),MATCH($B$3,Data_Sales!$B$3:$N$3,0)),ROUNDDOWN(G69*G72,0)) -> 245 | H73: =IF($E$73="Actual Sale",INDEX(Data_Sales!$B$3:$N$8,MATCH(H70,Data_Sales!$B$3:$B$8,0),MATCH($B$3,Data_Sales!$B$3:$N$3,0)),ROUNDDOWN(H69*H72,0)) -> 42 | I73: =IF($E$73="Actual Sale",INDEX(Data_Sales!$B$3:$N$8,MATCH(I70,Data_Sales!$B$3:$B$8,0),MATCH($B$3,Data_Sales!$B$3:$N$3,0)),ROUNDDOWN(I69*I72,0)) -> 723 | J73: =SUM(F73:I73) -> 1442
B74: Commision | C74: {=INDIRECT("'Input_Q"&B3&"-Predict'!C39")} -> 0.06 | E74: Advertisement unit | F74: {=INDIRECT("'Input_Q"&$B$3&"-Predict'!C41")} -> 7 | G74: {=INDIRECT("'Input_Q"&$B$3&"-Predict'!C42")} -> 10 | H74: {=INDIRECT("'Input_Q"&$B$3&"-Predict'!C43")} -> 1 | I74: {=INDIRECT("'Input_Q"&$B$3&"-Predict'!C44")} -> 8
B75: Planned sale | C75: =J72 -> 1600 | E75: A&P Investment | F75: =F72*F71*F74/100 -> 117090.61 | G75: =G72*G71*G74/100 -> 84987.3 | H75: =H72*H71*H74/100 -> 1652.43 | I75: =I72*I71*I74/100 -> 223570.88 | J75: =SUM(F75:I75) -> 427301.22
B76: Predicted sale | C76: =J73 -> 1442 | E76: New Hired sales | F76: {=INDIRECT("'Input_Q"&$B$3&"-Predict'!C46")} -> 0 | G76: {=INDIRECT("'Input_Q"&$B$3&"-Predict'!C47")} -> 0 | H76: {=INDIRECT("'Input_Q"&$B$3&"-Predict'!C48")} -> 0 | I76: {=INDIRECT("'Input_Q"&$B$3&"-Predict'!C49")} -> 0 | J76: /
B77: left finished good | C77: =C75-C76 -> 158 | E77: Active Sales Force | F77: =INDEX(Data_EmployeeNumber!$A$4:$E$16,MATCH('Q11-Predict'!$B$3-1,Data_EmployeeNumber!$A$4:$A$16,0),MATCH('Q11-Predict'!F70,Data_EmployeeNumber!$A$4:$E$4,0))+'Q11-Predict'!F76 -> 3 | G77: =INDEX(Data_EmployeeNumber!$A$4:$E$16,MATCH('Q11-Predict'!$B$3-1,Data_EmployeeNumber!$A$4:$A$16,0),MATCH('Q11-Predict'!G70,Data_EmployeeNumber!$A$4:$E$4,0))+'Q11-Predict'!G76 -> 3 | H77: =INDEX(Data_EmployeeNumber!$A$4:$E$16,MATCH('Q11-Predict'!$B$3-1,Data_EmployeeNumber!$A$4:$A$16,0),MATCH('Q11-Predict'!H70,Data_EmployeeNumber!$A$4:$E$4,0))+'Q11-Predict'!H76 -> 1 | I77: =INDEX(Data_EmployeeNumber!$A$4:$E$16,MATCH('Q11-Predict'!$B$3-1,Data_EmployeeNumber!$A$4:$A$16,0),MATCH('Q11-Predict'!I70,Data_EmployeeNumber!$A$4:$E$4,0))+'Q11-Predict'!I76 -> 4 | J77: =SUM(F77:I77) -> 11
E78: Total Region Demand | J78: From Report
E79: Market Share by Region | J79: From Report
E80: Feight Cost | F80: 39.23 | G80: 0 | H80: 45.3 | I80: 57
B89: 3. Human Resource
B91: Cost Overview
B92: Salaries | C92: =I98 -> 304200 | E92: Base Salary | F92: {=INDIRECT("'Input_Q"&$B$3&"-Predict'!C50")} -> 5200 | H92: Base Salary | I92: salary per position | J92: Number of employee | K92: Multiplier | L92: Total For 1
B93: Training Investments | C93: =K103 -> 50000 | H93: Manager | I93: =$F$92*K93 -> 26000 | J93: 1 | K93: 5 | L93: =J93*K93 -> 5
B94: CSR. Investments | C94: =K104 -> 18000 | E94: Investment | H94: Operators | I94: =$F$92*K94 -> 5200 | J94: 35 | K94: 1 | L94: =J94*K94 -> 35
B95: Fringe Benefits Investments | C95: =K105 -> 47000 | E95: Training | F95: 10000 | H95: Supervisors | I95: =$F$92*K95 -> 13000 | J95: 3 | K95: 2.5 | L95: =J95*K95 -> 7.5
C96: =SUM(C92:C95) -> 419200 | E96: Unit | F96: {=INDIRECT("'Input_Q"&$B$3&"-Predict'!C51")} -> 5 | H96: Sellers | I96: =$F$92*K96 -> 5200 | J96: =J77 -> 11 | K96: 1 | L96: =J96*K96 -> 11
E97: CSR | F97: 2000 | H97: Total | I97: / | J97: =SUM(J93:J96) -> 50 | K97: / | L97: =SUM(L93:L96) -> 58.5
B98: Employee Satisfaction | E98: Unit | F98: {=INDIRECT("'Input_Q"&$B$3&"-Predict'!C52")} -> 9 | H98: Total Salary paid | I98: =L97*F92 -> 304200
H100: Other Investment and Expense
E101: Fringe Benefit | I101: Unit | J101: Number | K101: Total
E102: Dental | F102: 165 | H102: Salary | I102: =F92 -> 5200 | J102: =L97 -> 58.5 | K102: =I102*J102 -> 304200
E103: Food | F103: 175 | H103: Training | I103: =F95 -> 10000 | J103: =F96 -> 5 | K103: =F95*J103 -> 50000
E104: Tuition | F104: 400 | H104: CSR | I104: =F97 -> 2000 | J104: =F98 -> 9 | K104: =F97*J104 -> 18000
E105: Retirement | F105: 280 | H105: Fringe benefit | I105: =F102+F106+F107+F108 -> 940 | J105: =J97 -> 50 | K105: =I105*J105 -> 47000
E106: Medical | F106: 350 | K106: =SUM(K102:K105) -> 419200
E107: Life Insurance | F107: 135
E108: Transportation | F108: 290
B111: 4. Finance
B113: Contracted Loan | C113: 0
B114: Interest Rate | C114: 0
B115: Interest | C115: =C113*C114 -> 0
B116: Information Report Purchase | C116: {=INDIRECT("'Input_Q"&$B$3&"-Predict'!C53")} -> 80000
B120: Our income statement based on the predicted sales , not the planned sale
B123: Sales Income | C123: =IFERROR(VLOOKUP(B123,$B$14:$C$121,2,FALSE),0) -> 4106858
B124: COGS | C124: =IF(D124="Match",(C74+0.125)*C123+J73*M23,E124) -> 1584434.1 | D124: Match | E124: 996058.8 | G124: DL | I124: =H124/$H$128 -> 0
B125: Gross Profit and Loss | C125: =C123-C124 -> 2522423.9 | G125: FC | H125: =SUMIF(D127:D139,"FC",C127:C139) -> 1895260.2 | I125: =H125/$H$128 -> 1314.3275
G126: COGS | H126: =C124 -> 1584434.1 | I126: =H126/$H$128 -> 1098.7754
B127: Production Fixed Cost | C127: =IF(B7="Overtime",560000,280000) -> 560000 | D127: FC | G127: Full Cost | H127: =SUM(H124:H126) -> 3479694.3
B128: Salaries | C128: =IF(B7="Overtime",VALUE(IFERROR(VLOOKUP(B128,$B$14:$C$121,2,FALSE),0))*2,VALUE(IFERROR(VLOOKUP(B128,$B$14:$C$121,2,FALSE),0))) -> 608400 | D128: FC | G128: Unit Sold | H128: =C76 -> 1442
...

Sheet Input_Q11-Predict
B1: Preparasion for next quarter prediction
B2: FALSE | C2: 1. Validate data from previous quarter ( By QingQing)
B3: FALSE | C3: 2. Update Data_ Sheets( Need cash flow update By Seb)
B4: FALSE | C4: 3.Create new prediction sheet for new quarter+ Validation ( QingQing)
B5: FALSE | C5: 4. Choose the Number of current quarter in B6
B6: Quarter | C6: 11
B7: Strategy | C7: Maximum Capacity | E7: Note: Conservasive strategy have a constrain which will only keep the next quarter RM unit =1200
B8: Working Hour | C8: Overtime
B9: SalePrice | F9: Predicted Sale
B10: 1 | C10: 2899 | F10: =C28 -> 1442
B11: 2 | C11: 2599 | F11: BreakEven unit
B12: 3 | C12: 2899 | F12: {=INDIRECT("'Q"&C6&"-Predict'!C165")} -> 1145
B13: 4 | C13: 2899 | F13: =IF(F12>F10,"Need Adjustment","All Good") -> All Good
B14: NET PROFIT / LOSS | C14: {=INDIRECT("'Q"&C6&"-Predict'!C149")} -> 442087.3
B15: PROFIT AND LOSS STATEMENT RESULTS | C15: {=INDIRECT("'Q"&C6&"-Predict'!C154")} -> 1280874.9
B17: Previous Quarter balance | C17: =INDEX(Data_IncomeStatement!A1:M33,MATCH("PROFIT AND LOSS STATEMENT RESULTS", Data_IncomeStatement!A1:A33, 0),MATCH(VALUE(C6-1), Data_IncomeStatement!A1:M1, 0)) -> 838787.64 | E17: DO NOT CHANGE THIS CELL!!
B18: Loan interest | C18: 0 | E18: Given
B19: Climatizer Stock | C19: =INDEX(Data_Stock!B2:N11,MATCH("Left Inventory",Data_Stock!B2:B11,0),MATCH(VALUE(C6-1),Data_Stock!B2:N2,0)) -> 427 | E19: DO NOT CHANGE THIS CELL!!
B20: Raw Material Available | C20: =INDEX(Data_Stock!B2:N11,MATCH("Left",Data_Stock!B2:B11,0),MATCH(VALUE(C6-1),Data_Stock!B2:N2,0)) -> 1992 | E20: DO NOT CHANGE THIS CELL!!
B21: Maximum Sell unit | C21: =IF(C8="Overtime",MIN((1560*C34+C19),(C19+(C20*C34))),MIN((1200*C34+C19),(C19+(C20*C34)))) -> 1924.6
B22: Plan to Sell | C22: =C21 -> 1924.6 | E22: # Prediction based on the demand
B23: ="----------------------------------------------->>" -> ----------------------------------------------->> | C23: =MIN(C22,C21) -> 1924.6 | E23: #Capped by the maximum sell unit
B24: 1 | C24: =ROUNDDOWN($C$23*D24,0) -> 577 | D24: 0.3 | E24: # Plan to have more market share
B25: 2 | C25: =ROUNDDOWN($C$23*D25,0) -> 327 | D25: 0.17 | E25: # Focus
B26: 3 | C26: =ROUNDDOWN($C$23*D26,0) -> 57 | D26: =1-D27-D25-D24 -> 0.03
B27: 4 | C27: 964 | D27: 0.5 | E27: # Leader | F27: =C23-C24-C25-C26 -> 963.6
B28: Predicted Sale | C28: =SUM(C29:C32) -> 1442 | E28: #Based on the predicted conversion rate
B29: 1 | C29: =ROUNDDOWN(C24*D29,0) -> 432 | D29: 0.75
B30: 2 | C30: =ROUNDDOWN(C25*D30,0) -> 245 | D30: 0.75
B31: 3 | C31: =ROUNDDOWN(C26*D31,0) -> 42 | D31: 0.75
B32: 4 | C32: =ROUNDDOWN(C27*D32,0) -> 723 | D32: 0.75
B33: Plan to produce | C33: =C23-C19 -> 1497.6 | E33: # = plan to sale - finish good stock
B34: Productivity | C34: 0.96
B35: Predicted Produced | C35: =ROUNDDOWN(C33*C34,0) -> 1437
B36: Raw Material to purchase | C36: 1066
B37: ="------------------------------->" -> -------------------------------> | C37: =IF(C7="Conservasive",1200-(C20-C35),C36) -> 1066 | E37: # = 1200 - (Raw material available - real produce)
B38: R&D | C38: 9
B39: Commision | C39: 0.06
B40: Advertisement | C40: Level
B41: 1 | C41: 7
B42: 2 | C42: 10
B43: 3 | C43: 1
B44: 4 | C44: 8
B45: New Hire
B46: 1 | C46: 0
B47: 2 | C47: 0
B48: 3 | C48: 0
B49: 4 | C49: 0
B50: Base Salary | C50: 5200
B51: Training | C51: 5
B52: C&R | C52: 9
B53: Total information | C53: 80000 | E53: #Manually Calculate+input

Sheet Input_Q10-Predict
B1: Preparasion for next quarter prediction
B2: TRUE | C2: 1. Validate data from previous quarter ( By QingQing)
B3: TRUE | C3: 2. Update Data_ Sheets( Need cash flow update By Seb)
B4: TRUE | C4: 3.Create new prediction sheet for new quarter+ Validation ( QingQing)
B5: TRUE | C5: 4. Choose the Number of current quarter in B6
B6: Quarter | C6: 10
B7: Strategy | C7: Maximum Capacity | E7: Note: Conservasive strategy have a constrain which will only keep the next quarter RM unit =1200
B8: Working Hour | C8: Overtime
B9: SalePrice | F9: Predicted Sale
B10: 1 | C10: 2899 | F10: =C28 -> 1015
B11: 2 | C11: 2599 | F11: BreakEven unit
B12: 3 | C12: 2899 | F12: {=INDIRECT("'Q"&C6&"-Predict'!C165")} -> 1105
B13: 4 | C13: 2899 | F13: =IF(F12>F10,"Need Adjustment","All Good") -> Need Adjustment
B14: NET PROFIT / LOSS | C14: {=INDIRECT("'Q"&C6&"-Predict'!C149")} -> -155198.27
B15: PROFIT AND LOSS STATEMENT RESULTS | C15: {=INDIRECT("'Q"&C6&"-Predict'!C154")} -> -41223.906
B17: Previous Quarter balance | C17: =INDEX(Data_IncomeStatement!A1:M33,MATCH("PROFIT AND LOSS STATEMENT RESULTS", Data_IncomeStatement!A1:A33, 0),MATCH(VALUE(C6-1), Data_IncomeStatement!A1:M1, 0)) -> 113974.37 | E17: DO NOT CHANGE THIS CELL!!
B18: Loan interest | C18: 0 | E18: Given
B19: Climatizer Stock | C19: =INDEX(Data_Stock!B2:N11,MATCH("Left Inventory",Data_Stock!B2:B11,0),MATCH(VALUE(C6-1),Data_Stock!B2:N2,0)) -> 534 | E19: DO NOT CHANGE THIS CELL!!
B20: Raw Material Available | C20: =INDEX(Data_Stock!B2:N11,MATCH("Left",Data_Stock!B2:B11,0),MATCH(VALUE(C6-1),Data_Stock!B2:N2,0)) -> 1930 | E20: DO NOT CHANGE THIS CELL!!
B21: Maximum Sell unit | C21: =IF(C8="Overtime",MIN((1560*C34+C19),(C19+(C20*C34))),MIN((1200*C34+C19),(C19+(C20*C34)))) -> 2031.6
B22: Plan to Sell | C22: =C21 -> 2031.6 | E22: # Prediction based on the demand
B23: ="----------------------------------------------->>" -> ----------------------------------------------->> | C23: =MIN(C22,C21) -> 2031.6 | E23: #Capped by the maximum sell unit
B24: 1 | C24: =ROUNDDOWN($C$23*D24,0) -> 609 | D24: 0.3 | E24: # Plan to have more market share
B25: 2 | C25: =ROUNDDOWN($C$23*D25,0) -> 406 | D25: 0.2 | E25: # Focus
B26: 3 | C26: =ROUNDDOWN($C$23*D26,0) -> 203 | D26: =1-D24-D25-D27 -> 0.1
B27: 4 | C27: 814 | D27: 0.4 | E27: # Leader
B28: Predicted Sale | C28: =SUM(C29:C32) -> 1015 | E28: #Based on the predicted conversion rate
B29: 1 | C29: =ROUNDDOWN(C24*D29,0) -> 304 | D29: 0.5
B30: 2 | C30: =ROUNDDOWN(C25*D30,0) -> 203 | D30: 0.5
B31: 3 | C31: =ROUNDDOWN(C26*D31,0) -> 101 | D31: 0.5
B32: 4 | C32: =ROUNDDOWN(C27*D32,0) -> 407 | D32: 0.5
B33: Plan to produce | C33: =C23-C19 -> 1497.6 | E33: # = plan to sale - finish good stock
B34: Productivity | C34: 0.96
B35: Predicted Produced | C35: =ROUNDDOWN(C33*C34,0) -> 1437
B36: Raw Material to purchase | C36: 1560
B37: ="------------------------------->" -> -------------------------------> | C37: =IF(C7="Conservasive",1200-(C20-C35),C36) -> 1560 | E37: # = 1200 - (Raw material available - real produce)
B38: R&D | C38: 9
B39: Commision | C39: 0.06
B40: Advertisement | C40: Level
B41: 1 | C41: 7
B42: 2 | C42: 10
B43: 3 | C43: 1
B44: 4 | C44: 8
B45: New Hire
B46: 1 | C46: 0
B47: 2 | C47: 0
B48: 3 | C48: 0
B49: 4 | C49: 0
B50: Base Salary | C50: 5200
B51: Training | C51: 7
B52: C&R | C52: 9
B53: Total information | C53: 0 | E53: #Manually Calculate+input

Sheet Q10-Validation
B2: Which Quarter:
B3: 10
B4: For:
B5: Validation
B6: Overtime?
B7: {=INDIRECT("'Input_Q"&B3&"-Predict'!C8")} -> Overtime
B9: From last Quarter
B10: Decicion Point
B11: Prediction
B14: 1. Operation
B16: Cost Overview
B17: Plant | C17: 0 | E17: Note: Raw material cost including the shipping fee related to each part
B18: Research & Development | C18: =F19*F20 -> 135000 | E18: Operation Cost Datasheet | I18: Q3 Order | K18: Type | L18: Unit Cost+Shipping | M18: Climatizer unit cost | N18: Order cost
B19: Raw Material | C19: =N23 -> 892148.4 | E19: R&D | F19: 15000 | G19: /unit | J19: Packing | K19: Premium | L19: =VLOOKUP($K$19,$E$24:F59,2,FALSE) -> 36 | M19: =L19*$F$25 -> 36 | N19: =M19*$F$24 -> 56160
B20: Raw Material Storage Costs | C20: =C34*0.02*M24 -> 21349.858 | F20: {=INDIRECT("'Input_Q"&B3&"-Predict'!C38")} -> 9 | I20: Decision | J20: Plastic | K20: Superplast | L20: =VLOOKUP($K$20,$E$25:F60,2,FALSE) -> 44.52 | M20: =L20*$F$28 -> 89.04 | N20: =M20*$F$24 -> 138902.4
B21: Production Fixed Cost | C21: 280000 | E21: MachineryModel | J21: Motor & Cooling | K21: Freezpro | L21: =VLOOKUP($K$21,$E$26:F63,2,FALSE) -> 187.2 | M21: =L21*$F$38 -> 374.4 | N21: =M21*$F$24 -> 584064
C22: =SUM(C17:C21) -> 1328498.3 | E22: Model1 | F22: 1300000 | J22: Electric | K22: Proline | L22: =VLOOKUP($K$22,$E$21:F60,2,FALSE) -> 24.15 | M22: =L22*$F$51 -> 72.45 | N22: =M22*$F$24 -> 113022
E23: Model2 | F23: 1500000 | I23: unit climatizer cost | M23: =SUM(M19:M22) -> 571.89 | N23: =SUM(N19:N22) -> 892148.4
E24: Raw Material | F24: {=INDIRECT("'Input_Q"&B3&"-Predict'!C36")} -> 1560 | G24: # of climatizer RM | I24: Unit Value | M24: =M23-M19 -> 535.89 | N24: =M24*F24 -> 835988.4
B25: Productivity | C25: {=IF(B5="Validation",'Q10-Validation'!C30/'Q10-Validation'!C29,INDIRECT("'Input_Q"&B3&"-Predict'!C34"))} -> 1.0002671 | E25: Packing | F25: 1 | G25: unit/climatizer
E26: Standard | F26: 20
B27: Climatizer Stock | C27: =INDEX(Data_Stock!B2:N11,MATCH("Left Inventory",Data_Stock!B2:B11,0),MATCH(VALUE(B3-1),Data_Stock!B2:N2,0)) -> 534 | E27: Premium | F27: 36
B28: Raw Material Available | C28: =INDEX(Data_Stock!B2:N11,MATCH("Left",Data_Stock!B2:B11,0),MATCH(VALUE(B3-1),Data_Stock!B2:N2,0)) -> 1930 | E28: Plastic | F28: 2 | G28: unit/climatizer
B29: Planned Production | C29: {=INDIRECT("'Input_Q"&B3&"-Predict'!C33")} -> 1497.6 | E29: Plastinjet | F29: =(1+F31)*F30 -> 43.2
B30: =IF(B5="Validation","Actual Production","Predict Production") -> Actual Production | C30: =INDEX(Data_Stock!B2:N11,MATCH("Produced",Data_Stock!B2:B11,0),MATCH(VALUE(B3),Data_Stock!B2:N2,0)) -> 1498 | E30: material | F30: 40
E31: Shipping | F31: 0.08
B32: Raw Material Left | E32: Superplast | F32: =(1+F34)*F33 -> 44.52
B33: Raw Material Purchased | C33: =F24 -> 1560 | E33: material | F33: 42
B34: Raw Material Available for Q+1 | C34: =IF(B5="Validation",INDEX(Data_Stock!B2:N11,MATCH("Left",Data_Stock!B2:B11,0),MATCH('Q10-Validation'!B3,Data_Stock!B2:N2,0)),C28+F24-C30) -> 1992 | E34: Shipping | F34: 0.06
B35: Total Inventory Value | C35: =C34*M24 -> 1067492.9 | E35: IPLM | F35: =(1+F37)*F36 -> 56.1
E36: material | F36: 55
E37: Shipping | F37: 0.02
E38: Moter&Cooling | F38: 2 | G38: unit/climatizer
E39: Motojister | F39: =(1+F41)*F40 -> 117.7
E40: material | F40: 110
E41: Shipping | F41: 0.07
E42: Motormaster | F42: =(1+F44)*F43 -> 186.3
E43: material | F43: 162
E44: Shipping | F44: 0.15
E45: InfinityParts | F45: =(1+F47)*F46 -> 193.6
E46: material | F46: 176
E47: Shipping | F47: 0.1
E48: Freezpro | F48: =(1+F50)*F49 -> 187.2
E49: material | F49: 180
E50: Shipping | F50: 0.04
E51: ElectrocalKit | F51: 3 | G51: unit/climatizer
E52: Chukchuk | F52: =(1+F54)*F53 -> 21.6
E53: material | F53: 18
E54: Shipping | F54: 0.2
E55: ConduiteElec | F55: =(1+F57)*F56 -> 22
E56: material | F56: 20
E57: Shipping | F57: 0.1
E58: Proline | F58: =(1+F60)*F59 -> 24.15
E59: material | F59: 23
E60: Shipping | F60: 0.05
B65: 2. Market
B67: Cost Overview
B68: Sales Income | C68: =SUMPRODUCT(F73:I73,F71:I71) -> 4562295
B69: A&P Investiments | C69: =J75 -> 423771.62 | E69: =IF(B5="Validation","Actual S.C.R","Predict S.C.R") -> Actual S.C.R | F69: {=IF($B$5="Validation",F73/F72,INDIRECT("'Input_Q"&$B$3&"-Predict'!D29"))} -> 0.79474548 | G69: {=IF($B$5="Validation",G73/G72,INDIRECT("'Input_Q"&$B$3&"-Predict'!D30"))} -> 0.74384236 | H69: {=IF($B$5="Validation",H73/H72,INDIRECT("'Input_Q"&$B$3&"-Predict'!D31"))} -> 0.74384236 | I69: {=IF($B$5="Validation",I73/I72,INDIRECT("'Input_Q"&$B$3&"-Predict'!D32"))} -> 0.82063882
B70: Commision Total | C70: =C68*C74 -> 273737.7 | E70: Region | F70: 1 | G70: 2 | H70: 3 | I70: 4 | J70: Total
C71: =SUM(C68:C70) -> 5259804.3 | E71: Unit sale price | F71: {=INDIRECT("'Input_Q"&$B$3&"-Predict'!C10")} -> 2899 | G71: {=INDIRECT("'Input_Q"&$B$3&"-Predict'!C11")} -> 2599 | H71: {=INDIRECT("'Input_Q"&$B$3&"-Predict'!C12")} -> 2899 | I71: {=INDIRECT("'Input_Q"&$B$3&"-Predict'!C13")} -> 2899 | J71: /
E72: Planned Sale | F72: {=INDIRECT("'Input_Q"&$B$3&"-Predict'!C24")} -> 609 | G72: {=INDIRECT("'Input_Q"&$B$3&"-Predict'!C25")} -> 406 | H72: {=INDIRECT("'Input_Q"&$B$3&"-Predict'!C26")} -> 203 | I72: {=INDIRECT("'Input_Q"&$B$3&"-Predict'!C27")} -> 814 | J72: =Archived_Testing_Q5!B19 -> 1600
E73: =IF(B5="Validation","Actual Sale","Predict Sale") -> Actual Sale | F73: =IF($E$73="Actual Sale",INDEX(Data_Sales!$B$3:$N$8,MATCH(F70,Data_Sales!$B$3:$B$8,0),MATCH($B$3,Data_Sales!$B$3:$N$3,0)),ROUNDDOWN(F69*F72,0)) -> 484 | G73: =IF($E$73="Actual Sale",INDEX(Data_Sales!$B$3:$N$8,MATCH(G70,Data_Sales!$B$3:$B$8,0),MATCH($B$3,Data_Sales!$B$3:$N$3,0)),ROUNDDOWN(G69*G72,0)) -> 302 | H73: =IF($E$73="Actual Sale",INDEX(Data_Sales!$B$3:$N$8,MATCH(H70,Data_Sales!$B$3:$B$8,0),MATCH($B$3,Data_Sales!$B$3:$N$3,0)),ROUNDDOWN(H69*H72,0)) -> 151 | I73: =IF($E$73="Actual Sale",INDEX(Data_Sales!$B$3:$N$8,MATCH(I70,Data_Sales!$B$3:$B$8,0),MATCH($B$3,Data_Sales!$B$3:$N$3,0)),ROUNDDOWN(I69*I72,0)) -> 668 | J73: =SUM(F73:I73) -> 1605
B74: Commision | C74: {=INDIRECT("'Input_Q"&B3&"-Predict'!C39")} -> 0.06 | E74: Advertisement unit | F74: {=INDIRECT("'Input_Q"&$B$3&"-Predict'!C41")} -> 7 | G74: {=INDIRECT("'Input_Q"&$B$3&"-Predict'!C42")} -> 10 | H74: {=INDIRECT("'Input_Q"&$B$3&"-Predict'!C43")} -> 1 | I74: {=INDIRECT("'Input_Q"&$B$3&"-Predict'!C44")} -> 8
B75: Planned sale | C75: =J72 -> 1600 | E75: A&P Investment | F75: =F72*F71*F74/100 -> 123584.37 | G75: =G72*G71*G74/100 -> 105519.4 | H75: =H72*H71*H74/100 -> 5884.97 | I75: =I72*I71*I74/100 -> 188782.88 | J75: =SUM(F75:I75) -> 423771.62
B76: Predicted sale | C76: =J73 -> 1605 | E76: New Hired sales | F76: {=INDIRECT("'Input_Q"&$B$3&"-Predict'!C46")} -> 0 | G76: {=INDIRECT("'Input_Q"&$B$3&"-Predict'!C47")} -> 0 | H76: {=INDIRECT("'Input_Q"&$B$3&"-Predict'!C48")} -> 0 | I76: {=INDIRECT("'Input_Q"&$B$3&"-Predict'!C49")} -> 0 | J76: /
B77: left finished good | C77: =C75-C76 -> -5 | E77: Active Sales Force | F77: =INDEX(Data_EmployeeNumber!$A$4:$E$16,MATCH('Q10-Validation'!$B$3-1,Data_EmployeeNumber!$A$4:$A$16,0),MATCH('Q10-Validation'!F70,Data_EmployeeNumber!$A$4:$E$4,0))+'Q10-Validation'!F76 -> 3 | G77: =INDEX(Data_EmployeeNumber!$A$4:$E$16,MATCH('Q10-Validation'!$B$3-1,Data_EmployeeNumber!$A$4:$A$16,0),MATCH('Q10-Validation'!G70,Data_EmployeeNumber!$A$4:$E$4,0))+'Q10-Validation'!G76 -> 3 | H77: =INDEX(Data_EmployeeNumber!$A$4:$E$16,MATCH('Q10-Validation'!$B$3-1,Data_EmployeeNumber!$A$4:$A$16,0),MATCH('Q10-Validation'!H70,Data_EmployeeNumber!$A$4:$E$4,0))+'Q10-Validation'!H76 -> 1 | I77: =INDEX(Data_EmployeeNumber!$A$4:$E$16,MATCH('Q10-Validation'!$B$3-1,Data_EmployeeNumber!$A$4:$A$16,0),MATCH('Q10-Validation'!I70,Data_EmployeeNumber!$A$4:$E$4,0))+'Q10-Validation'!I76 -> 4 | J77: =SUM(F77:I77) -> 11
E78: Total Region Demand | J78: From Report
E79: Market Share by Region | J79: From Report
E80: Feight Cost | F80: 39.23 | G80: 0 | H80: 45.3 | I80: 57
B89: 3. Human Resource
B91: Cost Overview
B92: Salaries | C92: =I98 -> 304200 | E92: Base Salary | F92: {=INDIRECT("'Input_Q"&$B$3&"-Predict'!C50")} -> 5200 | H92: Base Salary | I92: salary per position | J92: Number of employee | K92: Multiplier | L92: Total For 1
B93: Training Investments | C93: =K103 -> 70000 | H93: Manager | I93: =$F$92*K93 -> 26000 | J93: 1 | K93: 5 | L93: =J93*K93 -> 5
B94: CSR. Investments | C94: =K104 -> 18000 | E94: Investment | H94: Operators | I94: =$F$92*K94 -> 5200 | J94: 35 | K94: 1 | L94: =J94*K94 -> 35
B95: Fringe Benefits Investments | C95: =K105 -> 47000 | E95: Training | F95: 10000 | H95: Supervisors | I95: =$F$92*K95 -> 13000 | J95: 3 | K95: 2.5 | L95: =J95*K95 -> 7.5
C96: =SUM(C92:C95) -> 439200 | E96: Unit | F96: {=INDIRECT("'Input_Q"&$B$3&"-Predict'!C51")} -> 7 | H96: Sellers | I96: =$F$92*K96 -> 5200 | J96: =J77 -> 11 | K96: 1 | L96: =J96*K96 -> 11
E97: CSR | F97: 2000 | H97: Total | I97: / | J97: =SUM(J93:J96) -> 50 | K97: / | L97: =SUM(L93:L96) -> 58.5
B98: Employee Satisfaction | E98: Unit | F98: {=INDIRECT("'Input_Q"&$B$3&"-Predict'!C52")} -> 9 | H98: Total Salary paid | I98: =L97*F92 -> 304200
H100: Other Investment and Expense
E101: Fringe Benefit | I101: Unit | J101: Number | K101: Total
E102: Dental | F102: 165 | H102: Salary | I102: =F92 -> 5200 | J102: =L97 -> 58.5 | K102: =I102*J102 -> 304200
E103: Food | F103: 175 | H103: Training | I103: =F95 -> 10000 | J103: =F96 -> 7 | K103: =F95*J103 -> 70000
E104: Tuition | F104: 400 | H104: CSR | I104: =F97 -> 2000 | J104: =F98 -> 9 | K104: =F97*J104 -> 18000
E105: Retirement | F105: 280 | H105: Fringe benefit | I105: =F102+F106+F107+F108 -> 940 | J105: =J97 -> 50 | K105: =I105*J105 -> 47000
E106: Medical | F106: 350 | K106: =SUM(K102:K105) -> 439200
E107: Life Insurance | F107: 135
E108: Transportation | F108: 290
B111: 4. Finance
B113: Contracted Loan | C113: 0
B114: Interest Rate | C114: 0
B115: Interest | C115: =C113*C114 -> 0
B116: Information Report Purchase | C116: {=INDIRECT("'Input_Q"&$B$3&"-Predict'!C53")} -> 0
B120: Our income statement based on the predicted sales , not the planned sale
B123: Sales Income | C123: =IFERROR(VLOOKUP(B123,$B$14:$C$121,2,FALSE),0) -> 4562295
B124: COGS | C124: =IF(D124="Match",(C74+0.125)*C123+J73*M23,E124) -> 1761908 | D124: Match | E124: 996058.8 | G124: DL | I124: =H124/$H$128 -> 0
B125: Gross Profit and Loss | C125: =C123-C124 -> 2800387 | G125: FC | H125: =SUMIF(D127:D139,"FC",C127:C139) -> 1836521.5 | I125: =H125/$H$128 -> 1144.2501
G126: COGS | H126: =C124 -> 1761908 | I126: =H126/$H$128 -> 1097.762
B127: Production Fixed Cost | C127: =IF(B7="Overtime",560000,280000) -> 560000 | D127: FC | G127: Full Cost | H127: =SUM(H124:H126) -> 3598429.5
B128: Salaries | C128: =IF(B7="Overtime",VALUE(IFERROR(VLOOKUP(B128,$B$14:$C$121,2,FALSE),0))*2,VALUE(IFERROR(VLOOKUP(B128,$B$14:$C$121,2,FALSE),0))) -> 608400 | D128: FC | G128: Unit Sold | H128: =C76 -> 1605
...

Sheet Q10-Predict
B2: Which Quarter:
B3: 10
B4: For:
B5: Prediction
B6: Overtime?
B7: {=INDIRECT("'Input_Q"&B3&"-Predict'!C8")} -> Overtime
B9: From last Quarter
B10: Decicion Point
B11: Prediction
B14: 1. Operation
B16: Cost Overview
B17: Plant | C17: 0 | E17: Note: Raw material cost including the shipping fee related to each part
B18: Research & Development | C18: =F19*F20 -> 135000 | E18: Operation Cost Datasheet | I18: Q3 Order | K18: Type | L18: Unit Cost+Shipping | M18: Climatizer unit cost | N18: Order cost
B19: Raw Material | C19: =N23 -> 892148.4 | E19: R&D | F19: 15000 | G19: /unit | J19: Packing | K19: Premium | L19: =VLOOKUP($K$19,$E$24:F59,2,FALSE) -> 36 | M19: =L19*$F$25 -> 36 | N19: =M19*$F$24 -> 56160
B20: Raw Material Storage Costs | C20: =C34*0.02*M24 -> 21349.858 | F20: {=INDIRECT("'Input_Q"&B3&"-Predict'!C38")} -> 9 | I20: Decision | J20: Plastic | K20: Superplast | L20: =VLOOKUP($K$20,$E$25:F60,2,FALSE) -> 44.52 | M20: =L20*$F$28 -> 89.04 | N20: =M20*$F$24 -> 138902.4
B21: Production Fixed Cost | C21: 280000 | E21: MachineryModel | J21: Motor & Cooling | K21: Freezpro | L21: =VLOOKUP($K$21,$E$26:F63,2,FALSE) -> 187.2 | M21: =L21*$F$38 -> 374.4 | N21: =M21*$F$24 -> 584064
C22: =SUM(C17:C21) -> 1328498.3 | E22: Model1 | F22: 1300000 | J22: Electric | K22: Proline | L22: =VLOOKUP($K$22,$E$21:F60,2,FALSE) -> 24.15 | M22: =L22*$F$51 -> 72.45 | N22: =M22*$F$24 -> 113022
E23: Model2 | F23: 1500000 | I23: unit climatizer cost | M23: =SUM(M19:M22) -> 571.89 | N23: =SUM(N19:N22) -> 892148.4
E24: Raw Material | F24: {=INDIRECT("'Input_Q"&B3&"-Predict'!C36")} -> 1560 | G24: # of climatizer RM | I24: Unit Value | M24: =M23-M19 -> 535.89 | N24: =M24*F24 -> 835988.4
B25: Productivity | C25: {=IF(B5="Validation",'Q10-Predict'!C30/'Q10-Predict'!C29,INDIRECT("'Input_Q"&B3&"-Predict'!C34"))} -> 0.96 | E25: Packing | F25: 1 | G25: unit/climatizer
E26: Standard | F26: 20
B27: Climatizer Stock | C27: =INDEX(Data_Stock!B2:N11,MATCH("Left Inventory",Data_Stock!B2:B11,0),MATCH(VALUE(B3-1),Data_Stock!B2:N2,0)) -> 534 | E27: Premium | F27: 36
B28: Raw Material Available | C28: =INDEX(Data_Stock!B2:N11,MATCH("Left",Data_Stock!B2:B11,0),MATCH(VALUE(B3-1),Data_Stock!B2:N2,0)) -> 1930 | E28: Plastic | F28: 2 | G28: unit/climatizer
B29: Planned Production | C29: {=INDIRECT("'Input_Q"&B3&"-Predict'!C33")} -> 1497.6 | E29: Plastinjet | F29: =(1+F31)*F30 -> 43.2
B30: =IF(B5="Validation","Actual Production","Predict Production") -> Predict Production | C30: =INDEX(Data_Stock!B2:N11,MATCH("Produced",Data_Stock!B2:B11,0),MATCH(VALUE(B3),Data_Stock!B2:N2,0)) -> 1498 | E30: material | F30: 40
E31: Shipping | F31: 0.08
B32: Raw Material Left | E32: Superplast | F32: =(1+F34)*F33 -> 44.52
B33: Raw Material Purchased | C33: =F24 -> 1560 | E33: material | F33: 42
B34: Raw Material Available for Q+1 | C34: =IF(B5="Validation",INDEX(Data_Stock!B2:N11,MATCH("Left",Data_Stock!B2:B11,0),MATCH('Q10-Predict'!B3,Data_Stock!B2:N2,0)),C28+F24-C30) -> 1992 | E34: Shipping | F34: 0.06
B35: Total Inventory Value | C35: =C34*M24 -> 1067492.9 | E35: IPLM | F35: =(1+F37)*F36 -> 56.1
E36: material | F36: 55
E37: Shipping | F37: 0.02
E38: Moter&Cooling | F38: 2 | G38: unit/climatizer
E39: Motojister | F39: =(1+F41)*F40 -> 117.7
E40: material | F40: 110
E41: Shipping | F41: 0.07
E42: Motormaster | F42: =(1+F44)*F43 -> 186.3
E43: material | F43: 162
E44: Shipping | F44: 0.15
E45: InfinityParts | F45: =(1+F47)*F46 -> 193.6
E46: material | F46: 176
E47: Shipping | F47: 0.1
E48: Freezpro | F48: =(1+F50)*F49 -> 187.2
E49: material | F49: 180
E50: Shipping | F50: 0.04
E51: ElectrocalKit | F51: 3 | G51: unit/climatizer
E52: Chukchuk | F52: =(1+F54)*F53 -> 21.6
E53: material | F53: 18
E54: Shipping | F54: 0.2
E55: ConduiteElec | F55: =(1+F57)*F56 -> 22
E56: material | F56: 20
E57: Shipping | F57: 0.1
E58: Proline | F58: =(1+F60)*F59 -> 24.15
E59: material | F59: 23
E60: Shipping | F60: 0.05
B65: 2. Market
B67: Cost Overview
B68: Sales Income | C68: =SUMPRODUCT(F73:I73,F71:I71) -> 2881585
B69: A&P Investiments | C69: =J75 -> 423771.62 | E69: =IF(B5="Validation","Actual S.C.R","Predict S.C.R") -> Predict S.C.R | F69: {=IF($B$5="Validation",F73/F72,INDIRECT("'Input_Q"&$B$3&"-Predict'!D29"))} -> 0.5 | G69: {=IF($B$5="Validation",G73/G72,INDIRECT("'Input_Q"&$B$3&"-Predict'!D30"))} -> 0.5 | H69: {=IF($B$5="Validation",H73/H72,INDIRECT("'Input_Q"&$B$3&"-Predict'!D31"))} -> 0.5 | I69: {=IF($B$5="Validation",I73/I72,INDIRECT("'Input_Q"&$B$3&"-Predict'!D32"))} -> 0.5
B70: Commision Total | C70: =C68*C74 -> 172895.1 | E70: Region | F70: 1 | G70: 2 | H70: 3 | I70: 4 | J70: Total
C71: =SUM(C68:C70) -> 3478251.7 | E71: Unit sale price | F71: {=INDIRECT("'Input_Q"&$B$3&"-Predict'!C10")} -> 2899 | G71: {=INDIRECT("'Input_Q"&$B$3&"-Predict'!C11")} -> 2599 | H71: {=INDIRECT("'Input_Q"&$B$3&"-Predict'!C12")} -> 2899 | I71: {=INDIRECT("'Input_Q"&$B$3&"-Predict'!C13")} -> 2899 | J71: /
E72: Planned Sale | F72: {=INDIRECT("'Input_Q"&$B$3&"-Predict'!C24")} -> 609 | G72: {=INDIRECT("'Input_Q"&$B$3&"-Predict'!C25")} -> 406 | H72: {=INDIRECT("'Input_Q"&$B$3&"-Predict'!C26")} -> 203 | I72: {=INDIRECT("'Input_Q"&$B$3&"-Predict'!C27")} -> 814 | J72: =Archived_Testing_Q5!B19 -> 1600
E73: =IF(B5="Validation","Actual Sale","Predict Sale") -> Predict Sale | F73: =IF($E$73="Actual Sale",INDEX(Data_Sales!$B$3:$N$8,MATCH(F70,Data_Sales!$B$3:$B$8,0),MATCH($B$3,Data_Sales!$B$3:$N$3,0)),ROUNDDOWN(F69*F72,0)) -> 304 | G73: =IF($E$73="Actual Sale",INDEX(Data_Sales!$B$3:$N$8,MATCH(G70,Data_Sales!$B$3:$B$8,0),MATCH($B$3,Data_Sales!$B$3:$N$3,0)),ROUNDDOWN(G69*G72,0)) -> 203 | H73: =IF($E$73="Actual Sale",INDEX(Data_Sales!$B$3:$N$8,MATCH(H70,Data_Sales!$B$3:$B$8,0),MATCH($B$3,Data_Sales!$B$3:$N$3,0)),ROUNDDOWN(H69*H72,0)) -> 101 | I73: =IF($E$73="Actual Sale",INDEX(Data_Sales!$B$3:$N$8,MATCH(I70,Data_Sales!$B$3:$B$8,0),MATCH($B$3,Data_Sales!$B$3:$N$3,0)),ROUNDDOWN(I69*I72,0)) -> 407 | J73: =SUM(F73:I73) -> 1015
B74: Commision | C74: {=INDIRECT("'Input_Q"&B3&"-Predict'!C39")} -> 0.06 | E74: Advertisement unit | F74: {=INDIRECT("'Input_Q"&$B$3&"-Predict'!C41")} -> 7 | G74: {=INDIRECT("'Input_Q"&$B$3&"-Predict'!C42")} -> 10 | H74: {=INDIRECT("'Input_Q"&$B$3&"-Predict'!C43")} -> 1 | I74: {=INDIRECT("'Input_Q"&$B$3&"-Predict'!C44")} -> 8
B75: Planned sale | C75: =J72 -> 1600 | E75: A&P Investment | F75: =F72*F71*F74/100 -> 123584.37 | G75: =G72*G71*G74/100 -> 105519.4 | H75: =H72*H71*H74/100 -> 5884.97 | I75: =I72*I71*I74/100 -> 188782.88 | J75: =SUM(F75:I75) -> 423771.62
B76: Predicted sale | C76: =J73 -> 1015 | E76: New Hired sales | F76: {=INDIRECT("'Input_Q"&$B$3&"-Predict'!C46")} -> 0 | G76: {=INDIRECT("'Input_Q"&$B$3&"-Predict'!C47")} -> 0 | H76: {=INDIRECT("'Input_Q"&$B$3&"-Predict'!C48")} -> 0 | I76: {=INDIRECT("'Input_Q"&$B$3&"-Predict'!C49")} -> 0 | J76: /
B77: left finished good | C77: =C75-C76 -> 585 | E77: Active Sales Force | F77: =INDEX(Data_EmployeeNumber!$A$4:$E$16,MATCH('Q10-Predict'!$B$3-1,Data_EmployeeNumber!$A$4:$A$16,0),MATCH('Q10-Predict'!F70,Data_EmployeeNumber!$A$4:$E$4,0))+'Q10-Predict'!F76 -> 3 | G77: =INDEX(Data_EmployeeNumber!$A$4:$E$16,MATCH('Q10-Predict'!$B$3-1,Data_EmployeeNumber!$A$4:$A$16,0),MATCH('Q10-Predict'!G70,Data_EmployeeNumber!$A$4:$E$4,0))+'Q10-Predict'!G76 -> 3 | H77: =INDEX(Data_EmployeeNumber!$A$4:$E$16,MATCH('Q10-Predict'!$B$3-1,Data_EmployeeNumber!$A$4:$A$16,0),MATCH('Q10-Predict'!H70,Data_EmployeeNumber!$A$4:$E$4,0))+'Q10-Predict'!H76 -> 1 | I77: =INDEX(Data_EmployeeNumber!$A$4:$E$16,MATCH('Q10-Predict'!$B$3-1,Data_EmployeeNumber!$A$4:$A$16,0),MATCH('Q10-Predict'!I70,Data_EmployeeNumber!$A$4:$E$4,0))+'Q10-Predict'!I76 -> 4 | J77: =SUM(F77:I77) -> 11
E78: Total Region Demand | J78: From Report
E79: Market Share by Region | J79: From Report
E80: Feight Cost | F80: 39.23 | G80: 0 | H80: 45.3 | I80: 57
B89: 3. Human Resource
B91: Cost Overview
B92: Salaries | C92: =I98 -> 304200 | E92: Base Salary | F92: {=INDIRECT("'Input_Q"&$B$3&"-Predict'!C50")} -> 5200 | H92: Base Salary | I92: salary per position | J92: Number of employee | K92: Multiplier | L92: Total For 1
B93: Training Investments | C93: =K103 -> 70000 | H93: Manager | I93: =$F$92*K93 -> 26000 | J93: 1 | K93: 5 | L93: =J93*K93 -> 5
B94: CSR. Investments | C94: =K104 -> 18000 | E94: Investment | H94: Operators | I94: =$F$92*K94 -> 5200 | J94: 35 | K94: 1 | L94: =J94*K94 -> 35
B95: Fringe Benefits Investments | C95: =K105 -> 47000 | E95: Training | F95: 10000 | H95: Supervisors | I95: =$F$92*K95 -> 13000 | J95: 3 | K95: 2.5 | L95: =J95*K95 -> 7.5
C96: =SUM(C92:C95) -> 439200 | E96: Unit | F96: {=INDIRECT("'Input_Q"&$B$3&"-Predict'!C51")} -> 7 | H96: Sellers | I96: =$F$92*K96 -> 5200 | J96: =J77 -> 11 | K96: 1 | L96: =J96*K96 -> 11
E97: CSR | F97: 2000 | H97: Total | I97: / | J97: =SUM(J93:J96) -> 50 | K97: / | L97: =SUM(L93:L96) -> 58.5
B98: Employee Satisfaction | E98: Unit | F98: {=INDIRECT("'Input_Q"&$B$3&"-Predict'!C52")} -> 9 | H98: Total Salary paid | I98: =L97*F92 -> 304200
H100: Other Investment and Expense
E101: Fringe Benefit | I101: Unit | J101: Number | K101: Total
E102: Dental | F102: 165 | H102: Salary | I102: =F92 -> 5200 | J102: =L97 -> 58.5 | K102: =I102*J102 -> 304200
E103: Food | F103: 175 | H103: Training | I103: =F95 -> 10000 | J103: =F96 -> 7 | K103: =F95*J103 -> 70000
E104: Tuition | F104: 400 | H104: CSR | I104: =F97 -> 2000 | J104: =F98 -> 9 | K104: =F97*J104 -> 18000
E105: Retirement | F105: 280 | H105: Fringe benefit | I105: =F102+F106+F107+F108 -> 940 | J105: =J97 -> 50 | K105: =I105*J105 -> 47000
E106: Medical | F106: 350 | K106: =SUM(K102:K105) -> 439200
E107: Life Insurance | F107: 135
E108: Transportation | F108: 290
B111: 4. Finance
B113: Contracted Loan | C113: 0
B114: Interest Rate | C114: 0
B115: Interest | C115: =C113*C114 -> 0
B116: Information Report Purchase | C116: {=INDIRECT("'Input_Q"&$B$3&"-Predict'!C53")} -> 0
B120: Our income statement based on the predicted sales , not the planned sale
B123: Sales Income | C123: =IFERROR(VLOOKUP(B123,$B$14:$C$121,2,FALSE),0) -> 2881585
B124: COGS | C124: =IF(D124="Match",(C74+0.125)*C123+J73*M23,E124) -> 1113561.6 | D124: Match | E124: 996058.8 | G124: DL | I124: =H124/$H$128 -> 0
B125: Gross Profit and Loss | C125: =C123-C124 -> 1768023.4 | G125: FC | H125: =SUMIF(D127:D139,"FC",C127:C139) -> 1836521.5 | I125: =H125/$H$128 -> 1809.3808
G126: COGS | H126: =C124 -> 1113561.6 | I126: =H126/$H$128 -> 1097.105
B127: Production Fixed Cost | C127: =IF(B7="Overtime",560000,280000) -> 560000 | D127: FC | G127: Full Cost | H127: =SUM(H124:H126) -> 2950083.1
B128: Salaries | C128: =IF(B7="Overtime",VALUE(IFERROR(VLOOKUP(B128,$B$14:$C$121,2,FALSE),0))*2,VALUE(IFERROR(VLOOKUP(B128,$B$14:$C$121,2,FALSE),0))) -> 608400 | D128: FC | G128: Unit Sold | H128: =C76 -> 1015
...

Sheet Q9-Validation
B2: Which Quarter:
B3: 9
B4: For:
B5: Validation
B6: Overtime?
B7: {=INDIRECT("'Input_Q"&B3&"-Predict'!C8")} -> Overtime
B9: From last Quarter
B10: Decicion Point
B11: Prediction
B14: 1. Operation
B16: Cost Overview
B17: Plant | C17: 0 | E17: Note: Raw material cost including the shipping fee related to each part
B18: Research & Development | C18: =F19*F20 -> 135000 | E18: Operation Cost Datasheet | I18: Q3 Order | K18: Type | L18: Unit Cost+Shipping | M18: Climatizer unit cost | N18: Order cost
B19: Raw Material | C19: =N23 -> 892148.4 | E19: R&D | F19: 15000 | G19: /unit | J19: Packing | K19: Premium | L19: =VLOOKUP($K$19,$E$24:F59,2,FALSE) -> 36 | M19: =L19*$F$25 -> 36 | N19: =M19*$F$24 -> 56160
B20: Raw Material Storage Costs | C20: =C34*0.02*M24 -> 20685.354 | F20: {=INDIRECT("'Input_Q"&B3&"-Predict'!C38")} -> 9 | I20: Decision | J20: Plastic | K20: Superplast | L20: =VLOOKUP($K$20,$E$25:F60,2,FALSE) -> 44.52 | M20: =L20*$F$28 -> 89.04 | N20: =M20*$F$24 -> 138902.4
B21: Production Fixed Cost | C21: 280000 | E21: MachineryModel | J21: Motor & Cooling | K21: Freezpro | L21: =VLOOKUP($K$21,$E$26:F63,2,FALSE) -> 187.2 | M21: =L21*$F$38 -> 374.4 | N21: =M21*$F$24 -> 584064
C22: =SUM(C17:C21) -> 1327833.8 | E22: Model1 | F22: 1300000 | J22: Electric | K22: Proline | L22: =VLOOKUP($K$22,$E$21:F60,2,FALSE) -> 24.15 | M22: =L22*$F$51 -> 72.45 | N22: =M22*$F$24 -> 113022
E23: Model2 | F23: 1500000 | I23: unit climatizer cost | M23: =SUM(M19:M22) -> 571.89 | N23: =SUM(N19:N22) -> 892148.4
E24: Raw Material | F24: {=INDIRECT("'Input_Q"&B3&"-Predict'!C36")} -> 1560 | G24: # of climatizer RM | I24: Unit Value | M24: =M23-M19 -> 535.89 | N24: =M24*F24 -> 835988.4
B25: Productivity | C25: {=IF(B5="Validation",'Q9-Validation'!C30/'Q9-Validation'!C29,INDIRECT("'Input_Q"&B3&"-Predict'!C34"))} -> 0.96025641 | E25: Packing | F25: 1 | G25: unit/climatizer
E26: Standard | F26: 20
B27: Climatizer Stock | C27: =INDEX(Data_Stock!B2:N11,MATCH("Left Inventory",Data_Stock!B2:B11,0),MATCH(VALUE(B3-1),Data_Stock!B2:N2,0)) -> 541 | E27: Premium | F27: 36
B28: Raw Material Available | C28: =INDEX(Data_Stock!B2:N11,MATCH("Left",Data_Stock!B2:B11,0),MATCH(VALUE(B3-1),Data_Stock!B2:N2,0)) -> 1868 | E28: Plastic | F28: 2 | G28: unit/climatizer
B29: Planned Production | C29: {=INDIRECT("'Input_Q"&B3&"-Predict'!C33")} -> 1560 | E29: Plastinjet | F29: =(1+F31)*F30 -> 43.2
B30: =IF(B5="Validation","Actual Production","Predict Production") -> Actual Production | C30: =INDEX(Data_Stock!B2:N11,MATCH("Produced",Data_Stock!B2:B11,0),MATCH(VALUE(B3),Data_Stock!B2:N2,0)) -> 1498 | E30: material | F30: 40
E31: Shipping | F31: 0.08
B32: Raw Material Left | E32: Superplast | F32: =(1+F34)*F33 -> 44.52
B33: Raw Material Purchased | C33: =F24 -> 1560 | E33: material | F33: 42
B34: Raw Material Available for Q+1 | C34: =IF(B5="Validation",INDEX(Data_Stock!B2:N11,MATCH("Left",Data_Stock!B2:B11,0),MATCH('Q9-Validation'!B3,Data_Stock!B2:N2,0)),C28+F24-C30) -> 1930 | E34: Shipping | F34: 0.06
B35: Total Inventory Value | C35: =C34*M24 -> 1034267.7 | E35: IPLM | F35: =(1+F37)*F36 -> 56.1
E36: material | F36: 55
E37: Shipping | F37: 0.02
E38: Moter&Cooling | F38: 2 | G38: unit/climatizer
E39: Motojister | F39: =(1+F41)*F40 -> 117.7
E40: material | F40: 110
E41: Shipping | F41: 0.07
E42: Motormaster | F42: =(1+F44)*F43 -> 186.3
E43: material | F43: 162
E44: Shipping | F44: 0.15
E45: InfinityParts | F45: =(1+F47)*F46 -> 193.6
E46: material | F46: 176
E47: Shipping | F47: 0.1
E48: Freezpro | F48: =(1+F50)*F49 -> 187.2
E49: material | F49: 180
E50: Shipping | F50: 0.04
E51: ElectrocalKit | F51: 3 | G51: unit/climatizer
E52: Chukchuk | F52: =(1+F54)*F53 -> 21.6
E53: material | F53: 18
E54: Shipping | F54: 0.2
E55: ConduiteElec | F55: =(1+F57)*F56 -> 22
E56: material | F56: 20
E57: Shipping | F57: 0.1
E58: Proline | F58: =(1+F60)*F59 -> 24.15
E59: material | F59: 23
E60: Shipping | F60: 0.05
B65: 2. Market
B67: Cost Overview
B68: Sales Income | C68: =SUMPRODUCT(F73:I73,F71:I71) -> 4158295
B69: A&P Investiments | C69: =J75 -> 427041.03 | E69: =IF(B5="Validation","Actual S.C.R","Predict S.C.R") -> Actual S.C.R | F69: {=IF($B$5="Validation",F73/F72,INDIRECT("'Input_Q"&$B$3&"-Predict'!D29"))} -> 0.71885522 | G69: {=IF($B$5="Validation",G73/G72,INDIRECT("'Input_Q"&$B$3&"-Predict'!D30"))} -> 0.80654762 | H69: {=IF($B$5="Validation",H73/H72,INDIRECT("'Input_Q"&$B$3&"-Predict'!D31"))} -> 0.81355932 | I69: {=IF($B$5="Validation",I73/I72,INDIRECT("'Input_Q"&$B$3&"-Predict'!D32"))} -> 0.76666667
B70: Commision Total | C70: =C68*C74 -> 249497.7 | E70: Region | F70: 1 | G70: 2 | H70: 3 | I70: 4 | J70: Total
C71: =SUM(C68:C70) -> 4834833.7 | E71: Unit sale price | F71: {=INDIRECT("'Input_Q"&$B$3&"-Predict'!C10")} -> 2799 | G71: {=INDIRECT("'Input_Q"&$B$3&"-Predict'!C11")} -> 2599 | H71: {=INDIRECT("'Input_Q"&$B$3&"-Predict'!C12")} -> 2799 | I71: {=INDIRECT("'Input_Q"&$B$3&"-Predict'!C13")} -> 2799 | J71: /
E72: Planned Sale | F72: {=INDIRECT("'Input_Q"&$B$3&"-Predict'!C24")} -> 594 | G72: {=INDIRECT("'Input_Q"&$B$3&"-Predict'!C25")} -> 336 | H72: {=INDIRECT("'Input_Q"&$B$3&"-Predict'!C26")} -> 59 | I72: {=INDIRECT("'Input_Q"&$B$3&"-Predict'!C27")} -> 990 | J72: =Archived_Testing_Q5!B19 -> 1600
E73: =IF(B5="Validation","Actual Sale","Predict Sale") -> Actual Sale | F73: =IF($E$73="Actual Sale",INDEX(Data_Sales!$B$3:$N$8,MATCH(F70,Data_Sales!$B$3:$B$8,0),MATCH($B$3,Data_Sales!$B$3:$N$3,0)),ROUNDDOWN(F69*F72,0)) -> 427 | G73: =IF($E$73="Actual Sale",INDEX(Data_Sales!$B$3:$N$8,MATCH(G70,Data_Sales!$B$3:$B$8,0),MATCH($B$3,Data_Sales!$B$3:$N$3,0)),ROUNDDOWN(G69*G72,0)) -> 271 | H73: =IF($E$73="Actual Sale",INDEX(Data_Sales!$B$3:$N$8,MATCH(H70,Data_Sales!$B$3:$B$8,0),MATCH($B$3,Data_Sales!$B$3:$N$3,0)),ROUNDDOWN(H69*H72,0)) -> 48 | I73: =IF($E$73="Actual Sale",INDEX(Data_Sales!$B$3:$N$8,MATCH(I70,Data_Sales!$B$3:$B$8,0),MATCH($B$3,Data_Sales!$B$3:$N$3,0)),ROUNDDOWN(I69*I72,0)) -> 759 | J73: =SUM(F73:I73) -> 1505
B74: Commision | C74: {=INDIRECT("'Input_Q"&B3&"-Predict'!C39")} -> 0.06 | E74: Advertisement unit | F74: {=INDIRECT("'Input_Q"&$B$3&"-Predict'!C41")} -> 7 | G74: {=INDIRECT("'Input_Q"&$B$3&"-Predict'!C42")} -> 10 | H74: {=INDIRECT("'Input_Q"&$B$3&"-Predict'!C43")} -> 1 | I74: {=INDIRECT("'Input_Q"&$B$3&"-Predict'!C44")} -> 8
B75: Planned sale | C75: =J72 -> 1600 | E75: A&P Investment | F75: =F72*F71*F74/100 -> 116382.42 | G75: =G72*G71*G74/100 -> 87326.4 | H75: =H72*H71*H74/100 -> 1651.41 | I75: =I72*I71*I74/100 -> 221680.8 | J75: =SUM(F75:I75) -> 427041.03
B76: Predicted sale | C76: =J73 -> 1505 | E76: New Hired sales | F76: {=INDIRECT("'Input_Q"&$B$3&"-Predict'!C46")} -> 0 | G76: {=INDIRECT("'Input_Q"&$B$3&"-Predict'!C47")} -> 0 | H76: {=INDIRECT("'Input_Q"&$B$3&"-Predict'!C48")} -> 0 | I76: {=INDIRECT("'Input_Q"&$B$3&"-Predict'!C49")} -> 0 | J76: /
B77: left finished good | C77: =C75-C76 -> 95 | E77: Active Sales Force | F77: =INDEX(Data_EmployeeNumber!$A$4:$E$16,MATCH('Q9-Validation'!$B$3-1,Data_EmployeeNumber!$A$4:$A$16,0),MATCH('Q9-Validation'!F70,Data_EmployeeNumber!$A$4:$E$4,0))+'Q9-Validation'!F76 -> 3 | G77: =INDEX(Data_EmployeeNumber!$A$4:$E$16,MATCH('Q9-Validation'!$B$3-1,Data_EmployeeNumber!$A$4:$A$16,0),MATCH('Q9-Validation'!G70,Data_EmployeeNumber!$A$4:$E$4,0))+'Q9-Validation'!G76 -> 3 | H77: =INDEX(Data_EmployeeNumber!$A$4:$E$16,MATCH('Q9-Validation'!$B$3-1,Data_EmployeeNumber!$A$4:$A$16,0),MATCH('Q9-Validation'!H70,Data_EmployeeNumber!$A$4:$E$4,0))+'Q9-Validation'!H76 -> 1 | I77: =INDEX(Data_EmployeeNumber!$A$4:$E$16,MATCH('Q9-Validation'!$B$3-1,Data_EmployeeNumber!$A$4:$A$16,0),MATCH('Q9-Validation'!I70,Data_EmployeeNumber!$A$4:$E$4,0))+'Q9-Validation'!I76 -> 4 | J77: =SUM(F77:I77) -> 11
E78: Total Region Demand | J78: From Report
E79: Market Share by Region | J79: From Report
E80: Feight Cost | F80: 39.23 | G80: 0 | H80: 45.3 | I80: 57
B89: 3. Human Resource
B91: Cost Overview
B92: Salaries | C92: =I98 -> 304200 | E92: Base Salary | F92: {=INDIRECT("'Input_Q"&$B$3&"-Predict'!C50")} -> 5200 | H92: Base Salary | I92: salary per position | J92: Number of employee | K92: Multiplier | L92: Total For 1
B93: Training Investments | C93: =K103 -> 70000 | H93: Manager | I93: =$F$92*K93 -> 26000 | J93: 1 | K93: 5 | L93: =J93*K93 -> 5
B94: CSR. Investments | C94: =K104 -> 18000 | E94: Investment | H94: Operators | I94: =$F$92*K94 -> 5200 | J94: 35 | K94: 1 | L94: =J94*K94 -> 35
B95: Fringe Benefits Investments | C95: =K105 -> 47000 | E95: Training | F95: 10000 | H95: Supervisors | I95: =$F$92*K95 -> 13000 | J95: 3 | K95: 2.5 | L95: =J95*K95 -> 7.5
C96: =SUM(C92:C95) -> 439200 | E96: Unit | F96: {=INDIRECT("'Input_Q"&$B$3&"-Predict'!C51")} -> 7 | H96: Sellers | I96: =$F$92*K96 -> 5200 | J96: =J77 -> 11 | K96: 1 | L96: =J96*K96 -> 11
E97: CSR | F97: 2000 | H97: Total | I97: / | J97: =SUM(J93:J96) -> 50 | K97: / | L97: =SUM(L93:L96) -> 58.5
B98: Employee Satisfaction | E98: Unit | F98: {=INDIRECT("'Input_Q"&$B$3&"-Predict'!C52")} -> 9 | H98: Total Salary paid | I98: =L97*F92 -> 304200
H100: Other Investment and Expense
E101: Fringe Benefit | I101: Unit | J101: Number | K101: Total
E102: Dental | F102: 165 | H102: Salary | I102: =F92 -> 5200 | J102: =L97 -> 58.5 | K102: =I102*J102 -> 304200
E103: Food | F103: 175 | H103: Training | I103: =F95 -> 10000 | J103: =F96 -> 7 | K103: =F95*J103 -> 70000
E104: Tuition | F104: 400 | H104: CSR | I104: =F97 -> 2000 | J104: =F98 -> 9 | K104: =F97*J104 -> 18000
E105: Retirement | F105: 280 | H105: Fringe benefit | I105: =F102+F106+F107+F108 -> 940 | J105: =J97 -> 50 | K105: =I105*J105 -> 47000
E106: Medical | F106: 350 | K106: =SUM(K102:K105) -> 439200
E107: Life Insurance | F107: 135
E108: Transportation | F108: 290
B111: 4. Finance
B113: Contracted Loan | C113: 0
B114: Interest Rate | C114: 0
B115: Interest | C115: =C113*C114 -> 0
B116: Information Report Purchase | C116: {=INDIRECT("'Input_Q"&$B$3&"-Predict'!C53")} -> 80000
B120: Our income statement based on the predicted sales , not the planned sale
B123: Sales Income | C123: =IFERROR(VLOOKUP(B123,$B$14:$C$121,2,FALSE),0) -> 4158295
B124: COGS | C124: =IF(D124="Match",(C74+0.125)*C123+J73*M23,E124) -> 1575799 | D124: Not Match | E124: 1575799 | G124: DL | I124: =H124/$H$128 -> 0
B125: Gross Profit and Loss | C125: =C123-C124 -> 2582496 | G125: FC | H125: =SUMIF(D127:D139,"FC",C127:C139) -> 1919126.4 | I125: =H125/$H$128 -> 1275.167
G126: COGS | H126: =C124 -> 1575799 | I126: =H126/$H$128 -> 1047.0425
B127: Production Fixed Cost | C127: =IF(B7="Overtime",560000,280000) -> 560000 | D127: FC | G127: Full Cost | H127: =SUM(H124:H126) -> 3494925.4
B128: Salaries | C128: =IF(B7="Overtime",VALUE(IFERROR(VLOOKUP(B128,$B$14:$C$121,2,FALSE),0))*2,VALUE(IFERROR(VLOOKUP(B128,$B$14:$C$121,2,FALSE),0))) -> 608400 | D128: FC | G128: Unit Sold | H128: =C76 -> 1505
...

Sheet Input_Q9-Predict
B1: Preparasion for next quarter prediction
B2: TRUE | C2: 1. Validate data from previous quarter ( By QingQing)
B3: FALSE | C3: 2. Update Data_ Sheets( Need cash flow update By Seb)
B4: FALSE | C4: 3.Create new prediction sheet for new quarter+ Validation ( QingQing)
B5: FALSE | C5: 4. Choose the Number of current quarter in B6
B6: Quarter | C6: 9
B7: Strategy | C7: Maximum Capacity | E7: Note: Conservasive strategy have a constrain which will only keep the next quarter RM unit =1200
B8: Working Hour | C8: Overtime
B9: SalePrice | F9: Predicted Sale
B10: 1 | C10: 2799 | F10: =C28 -> 1335
B11: 2 | C11: 2599 | F11: BreakEven unit
B12: 3 | C12: 2799 | F12: {=INDIRECT("'Q"&C6&"-Predict'!C165")} -> 1202
B13: 4 | C13: 2799 | F13: =IF(F12>F10,"Adjust Cost!!!!", "All Good") -> All Good
B14: NET PROFIT / LOSS | C14: {=INDIRECT("'Q"&C6&"-Predict'!C149")} -> 190300.77 | G14: 578000
B15: PROFIT AND LOSS STATEMENT RESULTS | C15: {=INDIRECT("'Q"&C6&"-Predict'!C154")} -> -166070.33 | G15: 670
B17: Previous Quarter balance | C17: =INDEX(Data_IncomeStatement!A1:M33,MATCH("PROFIT AND LOSS STATEMENT RESULTS", Data_IncomeStatement!A1:A33, 0),MATCH(VALUE(C6-1), Data_IncomeStatement!A1:M1, 0)) -> -356371.1 | E17: DO NOT CHANGE THIS CELL!!
B18: Loan interest | C18: 0 | E18: Given
B19: Climatizer Stock | C19: =INDEX(Data_Stock!B2:N11,MATCH("Left Inventory",Data_Stock!B2:B11,0),MATCH(VALUE(C6-1),Data_Stock!B2:N2,0)) -> 541 | E19: DO NOT CHANGE THIS CELL!!
B20: Raw Material Available | C20: =INDEX(Data_Stock!B2:N11,MATCH("Left",Data_Stock!B2:B11,0),MATCH(VALUE(C6-1),Data_Stock!B2:N2,0)) -> 1868 | E20: DO NOT CHANGE THIS CELL!!
B21: Maximum Sell unit | C21: =IF(C8="Overtime",MIN((1500*C34+C19),(C19+(C20*C34))),MIN((1200*C34+C19),(C19+(C20*C34)))) -> 1981 | D21: False/
B22: Plan to Sell | C22: =C21 -> 1981 | E22: # Prediction based on the demand
B23: ="----------------------------------------------->>" -> ----------------------------------------------->> | C23: =MIN(C22,C21) -> 1981 | E23: #Capped by the maximum sell unit
B24: 1 | C24: =ROUNDDOWN($C$23*D24,0) -> 594 | D24: 0.3 | E24: # Plan to have more market share
B25: 2 | C25: =ROUNDDOWN($C$23*D25,0) -> 336 | D25: 0.17 | E25: # Focus
B26: 3 | C26: =ROUNDDOWN($C$23*D26,0) -> 59 | D26: =1-D27-D25-D24 -> 0.03
B27: 4 | C27: =ROUNDDOWN($C$23*D27,0) -> 990 | D27: 0.5 | E27: # Leader
B28: Predicted Sale | C28: =SUM(C29:C32) -> 1335 | E28: #Based on the predicted conversion rate
B29: 1 | C29: =ROUNDDOWN(C24*D29,0) -> 386 | D29: 0.65 | E29: 1082 | F29: =C29/E29 -> 0.35674677
B30: 2 | C30: =ROUNDDOWN(C25*D30,0) -> 218 | D30: 0.65 | E30: 734 | F30: 0.3 | G30: =E30*F30 -> 220.2
B31: 3 | C31: =ROUNDDOWN(C26*D31,0) -> 38 | D31: 0.65 | E31: 811 | F31: =C31/E31 -> 0.046855734
B32: 4 | C32: =ROUNDDOWN(C27*D32,0) -> 693 | D32: 0.7 | E32: 1236 | F32: 0.6 | G32: =E32*0.6 -> 741.6
B33: Plan to produce | C33: 1560 | E33: # = plan to sale - finish good stock
B34: Productivity | C34: 0.96
B35: Predicted Produced | C35: =ROUNDDOWN(C33*C34,0) -> 1497
B36: Raw Material to purchase | C36: 1560
B37: ="------------------------------->" -> -------------------------------> | C37: =IF(C7="Conservative",1200-(C20-C35),C36) -> 1560 | E37: # = 1200 - (Raw material available - real produce)
B38: R&D | C38: 9
B39: Commision | C39: 0.06
B40: Advertisement | C40: Level
B41: 1 | C41: 7
B42: 2 | C42: 10
B43: 3 | C43: 1
B44: 4 | C44: 8
B45: New Hire
B46: 1 | C46: 0
B47: 2 | C47: 0
B48: 3 | C48: 0
B49: 4 | C49: 0
B50: Base Salary | C50: 5200
B51: Training | C51: 7
B52: C&R | C52: 9
B53: Total information | C53: 80000 | E53: #Manually Calculate+input

Sheet Q9-Predict
B2: Which Quarter:
B3: 9
B4: For:
B5: Prediction
B6: Overtime?
B7: {=INDIRECT("'Input_Q"&B3&"-Predict'!C8")} -> Overtime
B9: From last Quarter
B10: Decicion Point
B11: Prediction
B14: 1. Operation
B16: Cost Overview
B17: Plant | C17: 0 | E17: Note: Raw material cost including the shipping fee related to each part
B18: Research & Development | C18: =F19*F20 -> 135000 | E18: Operation Cost Datasheet | I18: Q3 Order | K18: Type | L18: Unit Cost+Shipping | M18: Climatizer unit cost | N18: Order cost
B19: Raw Material | C19: =N23 -> 892148.4 | E19: R&D | F19: 15000 | G19: /unit | J19: Packing | K19: Premium | L19: =VLOOKUP($K$19,$E$24:F59,2,FALSE) -> 36 | M19: =L19*$F$25 -> 36 | N19: =M19*$F$24 -> 56160
B20: Raw Material Storage Costs | C20: =C34*0.02*M24 -> 20685.354 | F20: {=INDIRECT("'Input_Q"&B3&"-Predict'!C38")} -> 9 | I20: Decision | J20: Plastic | K20: Superplast | L20: =VLOOKUP($K$20,$E$25:F60,2,FALSE) -> 44.52 | M20: =L20*$F$28 -> 89.04 | N20: =M20*$F$24 -> 138902.4
B21: Production Fixed Cost | C21: 280000 | E21: MachineryModel | J21: Motor & Cooling | K21: Freezpro | L21: =VLOOKUP($K$21,$E$26:F63,2,FALSE) -> 187.2 | M21: =L21*$F$38 -> 374.4 | N21: =M21*$F$24 -> 584064
C22: =SUM(C17:C21) -> 1327833.8 | E22: Model1 | F22: 1300000 | J22: Electric | K22: Proline | L22: =VLOOKUP($K$22,$E$21:F60,2,FALSE) -> 24.15 | M22: =L22*$F$51 -> 72.45 | N22: =M22*$F$24 -> 113022
E23: Model2 | F23: 1500000 | I23: unit climatizer cost | M23: =SUM(M19:M22) -> 571.89 | N23: =SUM(N19:N22) -> 892148.4
E24: Raw Material | F24: {=INDIRECT("'Input_Q"&B3&"-Predict'!C36")} -> 1560 | G24: # of climatizer RM | I24: Unit Value | M24: =M23-M19 -> 535.89 | N24: =M24*F24 -> 835988.4
B25: Productivity | C25: {=IF(B5="Validation",'Q9-Predict'!C30/'Q9-Predict'!C29,INDIRECT("'Input_Q"&B3&"-Predict'!C34"))} -> 0.96 | E25: Packing | F25: 1 | G25: unit/climatizer
E26: Standard | F26: 20
B27: Climatizer Stock | C27: =INDEX(Data_Stock!B2:N11,MATCH("Left Inventory",Data_Stock!B2:B11,0),MATCH(VALUE(B3-1),Data_Stock!B2:N2,0)) -> 541 | E27: Premium | F27: 36
B28: Raw Material Available | C28: =INDEX(Data_Stock!B2:N11,MATCH("Left",Data_Stock!B2:B11,0),MATCH(VALUE(B3-1),Data_Stock!B2:N2,0)) -> 1868 | E28: Plastic | F28: 2 | G28: unit/climatizer
B29: Planned Production | C29: {=INDIRECT("'Input_Q"&B3&"-Predict'!C33")} -> 1560 | E29: Plastinjet | F29: =(1+F31)*F30 -> 43.2
B30: =IF(B5="Validation","Actual Production","Predict Production") -> Predict Production | C30: =INDEX(Data_Stock!B2:N11,MATCH("Produced",Data_Stock!B2:B11,0),MATCH(VALUE(B3),Data_Stock!B2:N2,0)) -> 1498 | E30: material | F30: 40
E31: Shipping | F31: 0.08
B32: Raw Material Left | E32: Superplast | F32: =(1+F34)*F33 -> 44.52
B33: Raw Material Purchased | C33: =F24 -> 1560 | E33: material | F33: 42
B34: Raw Material Available for Q+1 | C34: =IF(B5="Validation",INDEX(Data_Stock!B2:N11,MATCH("Left",Data_Stock!B2:B11,0),MATCH('Q9-Predict'!B3,Data_Stock!B2:N2,0)),C28+F24-C30) -> 1930 | E34: Shipping | F34: 0.06
B35: Total Inventory Value | C35: =C34*M24 -> 1034267.7 | E35: IPLM | F35: =(1+F37)*F36 -> 56.1
E36: material | F36: 55
E37: Shipping | F37: 0.02
E38: Moter&Cooling | F38: 2 | G38: unit/climatizer
E39: Motojister | F39: =(1+F41)*F40 -> 117.7
E40: material | F40: 110
E41: Shipping | F41: 0.07
E42: Motormaster | F42: =(1+F44)*F43 -> 186.3
E43: material | F43: 162
E44: Shipping | F44: 0.15
E45: InfinityParts | F45: =(1+F47)*F46 -> 193.6
E46: material | F46: 176
E47: Shipping | F47: 0.1
E48: Freezpro | F48: =(1+F50)*F49 -> 187.2
E49: material | F49: 180
E50: Shipping | F50: 0.04
E51: ElectrocalKit | F51: 3 | G51: unit/climatizer
E52: Chukchuk | F52: =(1+F54)*F53 -> 21.6
E53: material | F53: 18
E54: Shipping | F54: 0.2
E55: ConduiteElec | F55: =(1+F57)*F56 -> 22
E56: material | F56: 20
E57: Shipping | F57: 0.1
E58: Proline | F58: =(1+F60)*F59 -> 24.15
E59: material | F59: 23
E60: Shipping | F60: 0.05
B65: 2. Market
B67: Cost Overview
B68: Sales Income | C68: =SUMPRODUCT(F73:I73,F71:I71) -> 3693065
B69: A&P Investiments | C69: =J75 -> 427041.03 | E69: =IF(B5="Validation","Actual S.C.R","Predict S.C.R") -> Predict S.C.R | F69: {=IF($B$5="Validation",F73/F72,INDIRECT("'Input_Q"&$B$3&"-Predict'!D29"))} -> 0.65 | G69: {=IF($B$5="Validation",G73/G72,INDIRECT("'Input_Q"&$B$3&"-Predict'!D30"))} -> 0.65 | H69: {=IF($B$5="Validation",H73/H72,INDIRECT("'Input_Q"&$B$3&"-Predict'!D31"))} -> 0.65 | I69: {=IF($B$5="Validation",I73/I72,INDIRECT("'Input_Q"&$B$3&"-Predict'!D32"))} -> 0.7
B70: Commision Total | C70: =C68*C74 -> 221583.9 | E70: Region | F70: 1 | G70: 2 | H70: 3 | I70: 4 | J70: Total
C71: =SUM(C68:C70) -> 4341689.9 | E71: Unit sale price | F71: {=INDIRECT("'Input_Q"&$B$3&"-Predict'!C10")} -> 2799 | G71: {=INDIRECT("'Input_Q"&$B$3&"-Predict'!C11")} -> 2599 | H71: {=INDIRECT("'Input_Q"&$B$3&"-Predict'!C12")} -> 2799 | I71: {=INDIRECT("'Input_Q"&$B$3&"-Predict'!C13")} -> 2799 | J71: /
E72: Planned Sale | F72: {=INDIRECT("'Input_Q"&$B$3&"-Predict'!C24")} -> 594 | G72: {=INDIRECT("'Input_Q"&$B$3&"-Predict'!C25")} -> 336 | H72: {=INDIRECT("'Input_Q"&$B$3&"-Predict'!C26")} -> 59 | I72: {=INDIRECT("'Input_Q"&$B$3&"-Predict'!C27")} -> 990 | J72: =Archived_Testing_Q5!B19 -> 1600
E73: =IF(B5="Validation","Actual Sale","Predict Sale") -> Predict Sale | F73: =IF($E$73="Actual Sale",INDEX(Data_Sales!$B$3:$N$8,MATCH(F70,Data_Sales!$B$3:$B$8,0),MATCH($B$3,Data_Sales!$B$3:$N$3,0)),ROUNDDOWN(F69*F72,0)) -> 386 | G73: =IF($E$73="Actual Sale",INDEX(Data_Sales!$B$3:$N$8,MATCH(G70,Data_Sales!$B$3:$B$8,0),MATCH($B$3,Data_Sales!$B$3:$N$3,0)),ROUNDDOWN(G69*G72,0)) -> 218 | H73: =IF($E$73="Actual Sale",INDEX(Data_Sales!$B$3:$N$8,MATCH(H70,Data_Sales!$B$3:$B$8,0),MATCH($B$3,Data_Sales!$B$3:$N$3,0)),ROUNDDOWN(H69*H72,0)) -> 38 | I73: =IF($E$73="Actual Sale",INDEX(Data_Sales!$B$3:$N$8,MATCH(I70,Data_Sales!$B$3:$B$8,0),MATCH($B$3,Data_Sales!$B$3:$N$3,0)),ROUNDDOWN(I69*I72,0)) -> 693 | J73: =SUM(F73:I73) -> 1335
B74: Commision | C74: {=INDIRECT("'Input_Q"&B3&"-Predict'!C39")} -> 0.06 | E74: Advertisement unit | F74: {=INDIRECT("'Input_Q"&$B$3&"-Predict'!C41")} -> 7 | G74: {=INDIRECT("'Input_Q"&$B$3&"-Predict'!C42")} -> 10 | H74: {=INDIRECT("'Input_Q"&$B$3&"-Predict'!C43")} -> 1 | I74: {=INDIRECT("'Input_Q"&$B$3&"-Predict'!C44")} -> 8
B75: Planned sale | C75: =J72 -> 1600 | E75: A&P Investment | F75: =F72*F71*F74/100 -> 116382.42 | G75: =G72*G71*G74/100 -> 87326.4 | H75: =H72*H71*H74/100 -> 1651.41 | I75: =I72*I71*I74/100 -> 221680.8 | J75: =SUM(F75:I75) -> 427041.03
B76: Predicted sale | C76: =J73 -> 1335 | E76: New Hired sales | F76: {=INDIRECT("'Input_Q"&$B$3&"-Predict'!C46")} -> 0 | G76: {=INDIRECT("'Input_Q"&$B$3&"-Predict'!C47")} -> 0 | H76: {=INDIRECT("'Input_Q"&$B$3&"-Predict'!C48")} -> 0 | I76: {=INDIRECT("'Input_Q"&$B$3&"-Predict'!C49")} -> 0 | J76: /
B77: left finished good | C77: =C75-C76 -> 265 | E77: Active Sales Force | F77: =INDEX(Data_EmployeeNumber!$A$4:$E$16,MATCH('Q9-Predict'!$B$3-1,Data_EmployeeNumber!$A$4:$A$16,0),MATCH('Q9-Predict'!F70,Data_EmployeeNumber!$A$4:$E$4,0))+'Q9-Predict'!F76 -> 3 | G77: =INDEX(Data_EmployeeNumber!$A$4:$E$16,MATCH('Q9-Predict'!$B$3-1,Data_EmployeeNumber!$A$4:$A$16,0),MATCH('Q9-Predict'!G70,Data_EmployeeNumber!$A$4:$E$4,0))+'Q9-Predict'!G76 -> 3 | H77: =INDEX(Data_EmployeeNumber!$A$4:$E$16,MATCH('Q9-Predict'!$B$3-1,Data_EmployeeNumber!$A$4:$A$16,0),MATCH('Q9-Predict'!H70,Data_EmployeeNumber!$A$4:$E$4,0))+'Q9-Predict'!H76 -> 1 | I77: =INDEX(Data_EmployeeNumber!$A$4:$E$16,MATCH('Q9-Predict'!$B$3-1,Data_EmployeeNumber!$A$4:$A$16,0),MATCH('Q9-Predict'!I70,Data_EmployeeNumber!$A$4:$E$4,0))+'Q9-Predict'!I76 -> 4 | J77: =SUM(F77:I77) -> 11
E78: Total Region Demand | J78: From Report
E79: Market Share by Region | J79: From Report
E80: Feight Cost | F80: 39.23 | G80: 0 | H80: 45.3 | I80: 57
B89: 3. Human Resource
B91: Cost Overview
B92: Salaries | C92: =I98 -> 304200 | E92: Base Salary | F92: {=INDIRECT("'Input_Q"&$B$3&"-Predict'!C50")} -> 5200 | H92: Base Salary | I92: salary per position | J92: Number of employee | K92: Multiplier | L92: Total For 1
B93: Training Investments | C93: =K103 -> 70000 | H93: Manager | I93: =$F$92*K93 -> 26000 | J93: 1 | K93: 5 | L93: =J93*K93 -> 5
B94: CSR. Investments | C94: =K104 -> 18000 | E94: Investment | H94: Operators | I94: =$F$92*K94 -> 5200 | J94: 35 | K94: 1 | L94: =J94*K94 -> 35
B95: Fringe Benefits Investments | C95: =K105 -> 47000 | E95: Training | F95: 10000 | H95: Supervisors | I95: =$F$92*K95 -> 13000 | J95: 3 | K95: 2.5 | L95: =J95*K95 -> 7.5
C96: =SUM(C92:C95) -> 439200 | E96: Unit | F96: {=INDIRECT("'Input_Q"&$B$3&"-Predict'!C51")} -> 7 | H96: Sellers | I96: =$F$92*K96 -> 5200 | J96: =J77 -> 11 | K96: 1 | L96: =J96*K96 -> 11
E97: CSR | F97: 2000 | H97: Total | I97: / | J97: =SUM(J93:J96) -> 50 | K97: / | L97: =SUM(L93:L96) -> 58.5
B98: Employee Satisfaction | E98: Unit | F98: {=INDIRECT("'Input_Q"&$B$3&"-Predict'!C52")} -> 9 | H98: Total Salary paid | I98: =L97*F92 -> 304200
H100: Other Investment and Expense
E101: Fringe Benefit | I101: Unit | J101: Number | K101: Total
E102: Dental | F102: 165 | H102: Salary | I102: =F92 -> 5200 | J102: =L97 -> 58.5 | K102: =I102*J102 -> 304200
E103: Food | F103: 175 | H103: Training | I103: =F95 -> 10000 | J103: =F96 -> 7 | K103: =F95*J103 -> 70000
E104: Tuition | F104: 400 | H104: CSR | I104: =F97 -> 2000 | J104: =F98 -> 9 | K104: =F97*J104 -> 18000
E105: Retirement | F105: 280 | H105: Fringe benefit | I105: =F102+F106+F107+F108 -> 940 | J105: =J97 -> 50 | K105: =I105*J105 -> 47000
E106: Medical | F106: 350 | K106: =SUM(K102:K105) -> 439200
E107: Life Insurance | F107: 135
E108: Transportation | F108: 290
B111: 4. Finance
B113: Contracted Loan | C113: 0
B114: Interest Rate | C114: 0
B115: Interest | C115: =C113*C114 -> 0
B116: Information Report Purchase | C116: {=INDIRECT("'Input_Q"&$B$3&"-Predict'!C53")} -> 80000
B120: Our income statement based on the predicted sales , not the planned sale
B123: Sales Income | C123: =IFERROR(VLOOKUP(B123,$B$14:$C$121,2,FALSE),0) -> 3693065
B124: COGS | C124: =IF(D124="Match",(C74+0.125)*C123+J73*M23,E12) -> 1446690.2 | D124: Match | E124: 996058.8 | F124: Direct Labour = Salaries+Fringe Benefit | G124: DL | I124: =H124/$H$128 -> 0
B125: Gross Profit and Loss | C125: =C123-C124 -> 2246374.8 | G125: FC | H125: =SUMIF(D127:D139,"FC",C127:C139) -> 1919126.4 | I125: =H125/$H$128 -> 1437.5479
G126: COGS | H126: =C124 -> 1446690.2 | I126: =H126/$H$128 -> 1083.6631
B127: Production Fixed Cost | C127: =IF(B7="Overtime",560000,280000) -> 560000 | D127: FC | G127: Full Cost | H127: =SUM(H124:H126) -> 3365816.6
B128: Salaries | C128: =IF(B7="Overtime",VALUE(IFERROR(VLOOKUP(B128,$B$14:$C$121,2,FALSE),0))*2,VALUE(IFERROR(VLOOKUP(B128,$B$14:$C$121,2,FALSE),0))) -> 608400 | D128: FC | G128: Unit Sold | H128: =C76 -> 1335
...

Sheet Q8-Validation
B2: Which Quarter:
B3: 8
B4: For:
B5: Validation
B6: Overtime?
B7: Overtime
B9: From last Quarter
B10: Decicion Point
B11: Prediction
B14: 1. Operation
B16: Cost Overview
B17: Plant | C17: 0 | E17: Note: Raw material cost including the shipping fee related to each part
B18: Research & Development | C18: =F19*F20 -> 135000 | E18: Operation Cost Datasheet | I18: Q3 Order | K18: Type | L18: Unit Cost+Shipping | M18: Climatizer unit cost | N18: Order cost
B19: Raw Material | C19: =N23 -> 857835 | E19: R&D | F19: 15000 | G19: /unit | J19: Packing | K19: Premium | L19: =VLOOKUP($K$19,$E$24:F59,2,FALSE) -> 36 | M19: =L19*$F$25 -> 36 | N19: =M19*$F$24 -> 54000
B20: Raw Material Storage Costs | C20: =C34*0.02*M24 -> 20020.85 | F20: {=INDIRECT("'Input_Q"&B3&"-Predict'!C38")} -> 9 | I20: Decision | J20: Plastic | K20: Superplast | L20: =VLOOKUP($K$20,$E$25:F60,2,FALSE) -> 44.52 | M20: =L20*$F$28 -> 89.04 | N20: =M20*$F$24 -> 133560
B21: Production Fixed Cost | C21: 280000 | E21: MachineryModel | J21: Motor & Cooling | K21: Freezpro | L21: =VLOOKUP($K$21,$E$26:F63,2,FALSE) -> 187.2 | M21: =L21*$F$38 -> 374.4 | N21: =M21*$F$24 -> 561600
C22: =SUM(C17:C21) -> 1292855.9 | E22: Model1 | F22: 1300000 | J22: Electric | K22: Proline | L22: =VLOOKUP($K$22,$E$21:F60,2,FALSE) -> 24.15 | M22: =L22*$F$51 -> 72.45 | N22: =M22*$F$24 -> 108675
E23: Model2 | F23: 1500000 | I23: unit climatizer cost | M23: =SUM(M19:M22) -> 571.89 | N23: =SUM(N19:N22) -> 857835
E24: Raw Material | F24: {=INDIRECT("'Input_Q"&B3&"-Predict'!C36")} -> 1500 | G24: # of climatizer RM | I24: Unit Value | M24: =M23-M19 -> 535.89 | N24: =M24*F24 -> 803835
B25: Productivity | C25: {=IF(B5="Validation",'Q8-Validation'!C30/'Q8-Validation'!C29,INDIRECT("'Input_Q"&B3&"-Predict'!C34"))} -> 0.95972222 | E25: Packing | F25: 1 | G25: unit/climatizer
E26: Standard | F26: 20
B27: Climatizer Stock | C27: =INDEX(Data_Stock!B2:N11,MATCH("Left Inventory",Data_Stock!B2:B11,0),MATCH(VALUE(B3-1),Data_Stock!B2:N2,0)) -> 123 | E27: Premium | F27: 36
B28: Raw Material Available | C28: =INDEX(Data_Stock!B2:N11,MATCH("Left",Data_Stock!B2:B11,0),MATCH(VALUE(B3-1),Data_Stock!B2:N2,0)) -> 1750 | E28: Plastic | F28: 2 | G28: unit/climatizer
B29: Planned Production | C29: {=INDIRECT("'Input_Q"&B3&"-Predict'!C33")} -> 1440 | E29: Plastinjet | F29: =(1+F31)*F30 -> 43.2
B30: =IF(B5="Validation","Actual Production","Predict Production") -> Actual Production | C30: =INDEX(Data_Stock!B2:N11,MATCH("Produced",Data_Stock!B2:B11,0),MATCH(VALUE(B3),Data_Stock!B2:N2,0)) -> 1382 | E30: material | F30: 40
E31: Shipping | F31: 0.08
B32: Raw Material Left | E32: Superplast | F32: =(1+F34)*F33 -> 44.52
B33: Raw Material Purchased | C33: =F24 -> 1500 | E33: material | F33: 42
B34: Raw Material Available for Q+1 | C34: =IF(B5="Validation",INDEX(Data_Stock!B2:N11,MATCH("Left",Data_Stock!B2:B11,0),MATCH('Q8-Validation'!B3,Data_Stock!B2:N2,0)),C28+F24-C30) -> 1868 | E34: Shipping | F34: 0.06
B35: Total Inventory Value | C35: =C34*M24 -> 1001042.5 | E35: IPLM | F35: =(1+F37)*F36 -> 56.1
E36: material | F36: 55
E37: Shipping | F37: 0.02
E38: Moter&Cooling | F38: 2 | G38: unit/climatizer
E39: Motojister | F39: =(1+F41)*F40 -> 117.7
E40: material | F40: 110
E41: Shipping | F41: 0.07
E42: Motormaster | F42: =(1+F44)*F43 -> 186.3
E43: material | F43: 162
E44: Shipping | F44: 0.15
E45: InfinityParts | F45: =(1+F47)*F46 -> 193.6
E46: material | F46: 176
E47: Shipping | F47: 0.1
E48: Freezpro | F48: =(1+F50)*F49 -> 187.2
E49: material | F49: 180
E50: Shipping | F50: 0.04
E51: ElectrocalKit | F51: 3 | G51: unit/climatizer
E52: Chukchuk | F52: =(1+F54)*F53 -> 21.6
E53: material | F53: 18
E54: Shipping | F54: 0.2
E55: ConduiteElec | F55: =(1+F57)*F56 -> 22
E56: material | F56: 20
E57: Shipping | F57: 0.1
E58: Proline | F58: =(1+F60)*F59 -> 24.15
E59: material | F59: 23
E60: Shipping | F60: 0.05
B65: 2. Market
B67: Cost Overview
B68: Sales Income | C68: =SUMPRODUCT(F73:I73,F71:I71) -> 2792036
B69: A&P Investiments | C69: =J75 -> 319567.59 | E69: =IF(B5="Validation","Actual S.C.R","Predict S.C.R") -> Actual S.C.R | F69: {=IF($B$5="Validation",F73/F72,INDIRECT("'Input_Q"&$B$3&"-Predict'!D29"))} -> 0.67692308 | G69: {=IF($B$5="Validation",G73/G72,INDIRECT("'Input_Q"&$B$3&"-Predict'!D30"))} -> 0.50769231 | H69: {=IF($B$5="Validation",H73/H72,INDIRECT("'Input_Q"&$B$3&"-Predict'!D31"))} -> 0.625 | I69: {=IF($B$5="Validation",I73/I72,INDIRECT("'Input_Q"&$B$3&"-Predict'!D32"))} -> 0.64295875
B70: Commision Total | C70: =C68*C74 -> 167522.16 | E70: Region | F70: 1 | G70: 2 | H70: 3 | I70: 4 | J70: Total
C71: =SUM(C68:C70) -> 3279125.8 | E71: Unit sale price | F71: {=INDIRECT("'Input_Q"&$B$3&"-Predict'!C10")} -> 2999 | G71: {=INDIRECT("'Input_Q"&$B$3&"-Predict'!C11")} -> 2499 | H71: {=INDIRECT("'Input_Q"&$B$3&"-Predict'!C12")} -> 2999 | I71: {=INDIRECT("'Input_Q"&$B$3&"-Predict'!C13")} -> 2999 | J71: /
E72: Planned Sale | F72: {=INDIRECT("'Input_Q"&$B$3&"-Predict'!C24")} -> 390 | G72: {=INDIRECT("'Input_Q"&$B$3&"-Predict'!C25")} -> 390 | H72: {=INDIRECT("'Input_Q"&$B$3&"-Predict'!C26")} -> 80 | I72: {=INDIRECT("'Input_Q"&$B$3&"-Predict'!C27")} -> 703 | J72: =Archived_Testing_Q5!B19 -> 1600
E73: =IF(B5="Validation","Actual Sale","Predict Sale") -> Actual Sale | F73: =IF($E$73="Actual Sale",INDEX(Data_Sales!$B$3:$N$8,MATCH(F70,Data_Sales!$B$3:$B$8,0),MATCH($B$3,Data_Sales!$B$3:$N$3,0)),ROUNDDOWN(F69*F72,0)) -> 264 | G73: =IF($E$73="Actual Sale",INDEX(Data_Sales!$B$3:$N$8,MATCH(G70,Data_Sales!$B$3:$B$8,0),MATCH($B$3,Data_Sales!$B$3:$N$3,0)),ROUNDDOWN(G69*G72,0)) -> 198 | H73: =IF($E$73="Actual Sale",INDEX(Data_Sales!$B$3:$N$8,MATCH(H70,Data_Sales!$B$3:$B$8,0),MATCH($B$3,Data_Sales!$B$3:$N$3,0)),ROUNDDOWN(H69*H72,0)) -> 50 | I73: =IF($E$73="Actual Sale",INDEX(Data_Sales!$B$3:$N$8,MATCH(I70,Data_Sales!$B$3:$B$8,0),MATCH($B$3,Data_Sales!$B$3:$N$3,0)),ROUNDDOWN(I69*I72,0)) -> 452 | J73: =SUM(F73:I73) -> 964
B74: Commision | C74: {=INDIRECT("'Input_Q"&B3&"-Predict'!C39")} -> 0.06 | E74: Advertisement unit | F74: {=INDIRECT("'Input_Q"&$B$3&"-Predict'!C41")} -> 7 | G74: {=INDIRECT("'Input_Q"&$B$3&"-Predict'!C42")} -> 9 | H74: {=INDIRECT("'Input_Q"&$B$3&"-Predict'!C43")} -> 1 | I74: {=INDIRECT("'Input_Q"&$B$3&"-Predict'!C44")} -> 7
B75: Planned sale | C75: =J72 -> 1600 | E75: A&P Investment | F75: =F72*F71*F74/100 -> 81872.7 | G75: =G72*G71*G74/100 -> 87714.9 | H75: =H72*H71*H74/100 -> 2399.2 | I75: =I72*I71*I74/100 -> 147580.79 | J75: =SUM(F75:I75) -> 319567.59
B76: Predicted sale | C76: =J73 -> 964 | E76: New Hired sales | F76: {=INDIRECT("'Input_Q"&$B$3&"-Predict'!C46")} -> 0 | G76: {=INDIRECT("'Input_Q"&$B$3&"-Predict'!C47")} -> 0 | H76: {=INDIRECT("'Input_Q"&$B$3&"-Predict'!C48")} -> 0 | I76: {=INDIRECT("'Input_Q"&$B$3&"-Predict'!C49")} -> 0 | J76: /
B77: left finished good | C77: =C75-C76 -> 636 | E77: Active Sales Force | F77: =INDEX(Data_EmployeeNumber!$A$4:$E$16,MATCH('Q8-Validation'!$B$3-1,Data_EmployeeNumber!$A$4:$A$16,0),MATCH('Q8-Validation'!F70,Data_EmployeeNumber!$A$4:$E$4,0))+'Q8-Validation'!F76 -> 3 | G77: =INDEX(Data_EmployeeNumber!$A$4:$E$16,MATCH('Q8-Validation'!$B$3-1,Data_EmployeeNumber!$A$4:$A$16,0),MATCH('Q8-Validation'!G70,Data_EmployeeNumber!$A$4:$E$4,0))+'Q8-Validation'!G76 -> 3 | H77: =INDEX(Data_EmployeeNumber!$A$4:$E$16,MATCH('Q8-Validation'!$B$3-1,Data_EmployeeNumber!$A$4:$A$16,0),MATCH('Q8-Validation'!H70,Data_EmployeeNumber!$A$4:$E$4,0))+'Q8-Validation'!H76 -> 1 | I77: =INDEX(Data_EmployeeNumber!$A$4:$E$16,MATCH('Q8-Validation'!$B$3-1,Data_EmployeeNumber!$A$4:$A$16,0),MATCH('Q8-Validation'!I70,Data_EmployeeNumber!$A$4:$E$4,0))+'Q8-Validation'!I76 -> 4 | J77: =SUM(F77:I77) -> 11
E78: Total Region Demand | J78: From Report
E79: Market Share by Region | J79: From Report
E80: Feight Cost | F80: 39.23 | G80: 0 | H80: 45.3 | I80: 57
B89: 3. Human Resource
B91: Cost Overview
B92: Salaries | C92: =I98 -> 304200 | E92: Base Salary | F92: {=INDIRECT("'Input_Q"&$B$3&"-Predict'!C50")} -> 5200 | H92: Base Salary | I92: salary per position | J92: Number of employee | K92: Multiplier | L92: Total For 1
B93: Training Investments | C93: =K103 -> 70000 | H93: Manager | I93: =$F$92*K93 -> 26000 | J93: 1 | K93: 5 | L93: =J93*K93 -> 5
B94: CSR. Investments | C94: =K104 -> 10000 | E94: Investment | H94: Operators | I94: =$F$92*K94 -> 5200 | J94: 35 | K94: 1 | L94: =J94*K94 -> 35
B95: Fringe Benefits Investments | C95: =K105 -> 47000 | E95: Training | F95: 10000 | H95: Supervisors | I95: =$F$92*K95 -> 13000 | J95: 3 | K95: 2.5 | L95: =J95*K95 -> 7.5
C96: =SUM(C92:C95) -> 431200 | E96: Unit | F96: {=INDIRECT("'Input_Q"&$B$3&"-Predict'!C51")} -> 7 | H96: Sellers | I96: =$F$92*K96 -> 5200 | J96: =J77 -> 11 | K96: 1 | L96: =J96*K96 -> 11
E97: CSR | F97: 2000 | H97: Total | I97: / | J97: =SUM(J93:J96) -> 50 | K97: / | L97: =SUM(L93:L96) -> 58.5
B98: Employee Satisfaction | E98: Unit | F98: {=INDIRECT("'Input_Q"&$B$3&"-Predict'!C52")} -> 5 | H98: Total Salary paid | I98: =L97*F92 -> 304200
H100: Other Investment and Expense
E101: Fringe Benefit | I101: Unit | J101: Number | K101: Total
E102: Dental | F102: 165 | H102: Salary | I102: =F92 -> 5200 | J102: =L97 -> 58.5 | K102: =I102*J102 -> 304200
E103: Food | F103: 175 | H103: Training | I103: =F95 -> 10000 | J103: =F96 -> 7 | K103: =F95*J103 -> 70000
E104: Tuition | F104: 400 | H104: CSR | I104: =F97 -> 2000 | J104: =F98 -> 5 | K104: =F97*J104 -> 10000
E105: Retirement | F105: 280 | H105: Fringe benefit | I105: =F102+F106+F107+F108 -> 940 | J105: =J97 -> 50 | K105: =I105*J105 -> 47000
E106: Medical | F106: 350 | K106: =SUM(K102:K105) -> 431200
E107: Life Insurance | F107: 135
E108: Transportation | F108: 290
B111: 4. Finance
B113: Contracted Loan | C113: 0
B114: Interest Rate | C114: 0
B115: Interest | C115: =C113*C114 -> 0
B116: Information Report Purchase | C116: 40000
B120: Our income statement based on the predicted sales , not the planned sale
B123: Sales Income | C123: =IFERROR(VLOOKUP(B123,$B$14:$C$121,2,FALSE),0) -> 2792036
B124: COGS | C124: =IF(D124="Match",(C74+0.125)*C123+J73*M23,E124) -> 1033124.6 | D124: Not Match | E124: 1033124.6 | G124: DL | I124: =H124/$H$128 -> 0
B125: Gross Profit and Loss | C125: =C123-C124 -> 1758911.4 | G125: FC | H125: =SUM(C127:C139) -> 1848764.4 | I125: =H125/$H$128 -> 1917.8054
G126: COGS | H126: =C124 -> 1033124.6 | I126: =H126/$H$128 -> 1071.706
B127: Production Fixed Cost | C127: =IF(B7="Overtime",560000,280000) -> 560000 | D127: FC | G127: Full Cost | H127: =SUM(H124:H126) -> 2881889.1
B128: Salaries | C128: =IF(B7="Overtime",VALUE(IFERROR(VLOOKUP(B128,$B$14:$C$121,2,FALSE),0))*2,VALUE(IFERROR(VLOOKUP(B128,$B$14:$C$121,2,FALSE),0))) -> 608400 | D128: FC | G128: Unit Sold | H128: =C76 -> 964
...

Sheet Input_Q8-Predict
B1: Preparasion for next quarter prediction
B2: TRUE | C2: 1. Validate data from previous quarter ( By QingQing)
B3: TRUE | C3: 2. Update Data_ Sheets( Need cash flow update By Seb)
B4: TRUE | C4: 3.Create new prediction sheet for new quarter+ Validation ( QingQing)
B5: TRUE | C5: 4. Choose the Number of current quarter in B6
B6: Quarter | C6: 8
B7: Strategy | C7: Maximum Capacity | E7: Note: Conservasive strategy have a constrain which will only keep the next quarter RM unit =1200
B8: Working Hour | C8: Overtime
B9: SalePrice
B10: 1 | C10: 2999
B11: 2 | C11: 2499
B12: 3 | C12: 2999
B13: 4 | C13: 2999
B14: NET PROFIT / LOSS | C14: {=INDIRECT("'Q"&C6&"-Predict'!C149")} -> 485991.36
B15: PROFIT AND LOSS STATEMENT RESULTS | C15: {=INDIRECT("'Q"&C6&"-Predict'!C154")} -> 219473.32
B17: Previous Quarter balance | C17: =INDEX(Data_IncomeStatement!A1:M33,MATCH("PROFIT AND LOSS STATEMENT RESULTS", Data_IncomeStatement!A1:A33, 0),MATCH(VALUE(C6-1), Data_IncomeStatement!A1:M1, 0)) -> -266518.04 | E17: DO NOT CHANGE THIS CELL!!
B18: Loan interest | C18: 0 | E18: Given
B19: Climatizer Stock | C19: =INDEX(Data_Stock!B2:N11,MATCH("Left Inventory",Data_Stock!B2:B11,0),MATCH(VALUE(C6-1),Data_Stock!B2:N2,0)) -> 123 | E19: DO NOT CHANGE THIS CELL!!
B20: Raw Material Available | C20: =INDEX(Data_Stock!B2:N11,MATCH("Left",Data_Stock!B2:B11,0),MATCH(VALUE(C6-1),Data_Stock!B2:N2,0)) -> 1750 | E20: DO NOT CHANGE THIS CELL!!
B21: Maximum Sell unit | C21: =IF(C8="Overtime",MIN((1500*C34+C19),(C19+(C20*C34))),MIN((1200*C34+C19),(C19+(C20*C34)))) -> 1563
B22: Plan to Sell | C22: =C21 -> 1563 | E22: # Prediction based on the demand
B23: ="----------------------------------------------->>" -> ----------------------------------------------->> | C23: =MIN(C22,C21) -> 1563 | E23: #Capped by the maximum sell unit
B24: 1 | C24: =ROUNDDOWN($C$23*D24,0) -> 390 | D24: 0.25 | E24: # Plan to have more market share | H24: 1300 | I24: =C24/H24 -> 0.3
B25: 2 | C25: =ROUNDDOWN($C$23*D25,0) -> 390 | D25: 0.25 | E25: # Focus | H25: 882 | I25: =C25/H25 -> 0.44217687
B26: 3 | C26: =C23-C24-C25-C27 -> 80 | D26: =1-D27-D25-D24 -> 0.05 | H26: 975 | I26: =C26/H26 -> 0.082051282
B27: 4 | C27: =ROUNDDOWN($C$23*D27,0) -> 703 | D27: 0.45 | E27: # Leader | H27: 1486 | I27: =C27/H27 -> 0.4730821
B28: Predicted Sale | C28: =SUM(C29:C32) -> 1398 | E28: #Based on the predicted conversion rate
B29: 1 | C29: =ROUNDDOWN(C24*D29,0) -> 351 | D29: 0.9
B30: 2 | C30: =ROUNDDOWN(C25*D30,0) -> 351 | D30: 0.9
B31: 3 | C31: =ROUNDDOWN(C26*D31,0) -> 64 | D31: 0.8
B32: 4 | C32: =ROUNDDOWN(C27*D32,0) -> 632 | D32: 0.9
B33: Plan to produce | C33: =C23-C19 -> 1440 | E33: # = plan to sale - finish good stock
B34: Productivity | C34: 0.96
B35: Predicted Produced | C35: =ROUNDDOWN(C33*C34,0) -> 1382
B36: Raw Material to purchase | C36: 1500
B37: ="------------------------------->" -> -------------------------------> | C37: =IF(C7="Conservasive",1200-(C20-C35),C36) -> 1500 | E37: # = 1200 - (Raw material available - real produce)
B38: R&D | C38: 9
B39: Commision | C39: 0.06
B40: Advertisement | C40: Level
B41: 1 | C41: 7
B42: 2 | C42: 9
B43: 3 | C43: 1
B44: 4 | C44: 7
B45: New Hire
B46: 1 | C46: 0
B47: 2 | C47: 0
B48: 3 | C48: 0
B49: 4 | C49: 0
B50: Base Salary | C50: 5200
B51: Training | C51: 7
B52: C&R | C52: 5
B53: Total information | C53: 80000 | E53: #Manually Calculate+input

Sheet Q8-Predict
B2: Which Quarter:
B3: 8
B4: For:
B5: Prediction
B6: Overtime?
B7: Overtime
B9: From last Quarter
B10: Decicion Point
B11: Prediction
B14: 1. Operation
B16: Cost Overview
B17: Plant | C17: 0 | E17: Note: Raw material cost including the shipping fee related to each part
B18: Research & Development | C18: =F19*F20 -> 135000 | E18: Operation Cost Datasheet | I18: Q3 Order | K18: Type | L18: Unit Cost+Shipping | M18: Climatizer unit cost | N18: Order cost
B19: Raw Material | C19: =N23 -> 857835 | E19: R&D | F19: 15000 | G19: /unit | J19: Packing | K19: Premium | L19: =VLOOKUP($K$19,$E$24:F59,2,FALSE) -> 36 | M19: =L19*$F$25 -> 36 | N19: =M19*$F$24 -> 54000
B20: Raw Material Storage Costs | C20: =C34*0.02*M24 -> 20020.85 | F20: {=INDIRECT("'Input_Q"&B3&"-Predict'!C38")} -> 9 | I20: Decision | J20: Plastic | K20: Superplast | L20: =VLOOKUP($K$20,$E$25:F60,2,FALSE) -> 44.52 | M20: =L20*$F$28 -> 89.04 | N20: =M20*$F$24 -> 133560
B21: Production Fixed Cost | C21: 280000 | E21: MachineryModel | J21: Motor & Cooling | K21: Freezpro | L21: =VLOOKUP($K$21,$E$26:F63,2,FALSE) -> 187.2 | M21: =L21*$F$38 -> 374.4 | N21: =M21*$F$24 -> 561600
C22: =SUM(C17:C21) -> 1292855.9 | E22: Model1 | F22: 1300000 | J22: Electric | K22: Proline | L22: =VLOOKUP($K$22,$E$21:F60,2,FALSE) -> 24.15 | M22: =L22*$F$51 -> 72.45 | N22: =M22*$F$24 -> 108675
E23: Model2 | F23: 1500000 | I23: unit climatizer cost | M23: =SUM(M19:M22) -> 571.89 | N23: =SUM(N19:N22) -> 857835
E24: Raw Material | F24: {=INDIRECT("'Input_Q"&B3&"-Predict'!C36")} -> 1500 | G24: # of climatizer RM | I24: Unit Value | M24: =M23-M19 -> 535.89 | N24: =M24*F24 -> 803835
B25: Productivity | C25: {=IF(B5="Validation",'Q8-Predict'!C30/'Q8-Predict'!C29,INDIRECT("'Input_Q"&B3&"-Predict'!C34"))} -> 0.96 | E25: Packing | F25: 1 | G25: unit/climatizer
E26: Standard | F26: 20
B27: Climatizer Stock | C27: =INDEX(Data_Stock!B2:N11,MATCH("Left Inventory",Data_Stock!B2:B11,0),MATCH(VALUE(B3-1),Data_Stock!B2:N2,0)) -> 123 | E27: Premium | F27: 36
B28: Raw Material Available | C28: =INDEX(Data_Stock!B2:N11,MATCH("Left",Data_Stock!B2:B11,0),MATCH(VALUE(B3-1),Data_Stock!B2:N2,0)) -> 1750 | E28: Plastic | F28: 2 | G28: unit/climatizer
B29: Planned Production | C29: {=INDIRECT("'Input_Q"&B3&"-Predict'!C33")} -> 1440 | E29: Plastinjet | F29: =(1+F31)*F30 -> 43.2
B30: =IF(B5="Validation","Actual Production","Predict Production") -> Predict Production | C30: =INDEX(Data_Stock!B2:N11,MATCH("Produced",Data_Stock!B2:B11,0),MATCH(VALUE(B3),Data_Stock!B2:N2,0)) -> 1382 | E30: material | F30: 40
E31: Shipping | F31: 0.08
B32: Raw Material Left | E32: Superplast | F32: =(1+F34)*F33 -> 44.52
B33: Raw Material Purchased | C33: =F24 -> 1500 | E33: material | F33: 42
B34: Raw Material Available for Q+1 | C34: =IF(B5="Validation",INDEX(Data_Stock!B2:N11,MATCH("Left",Data_Stock!B2:B11,0),MATCH('Q8-Predict'!B3,Data_Stock!B2:N2,0)),C28+F24-C30) -> 1868 | E34: Shipping | F34: 0.06
B35: Total Inventory Value | C35: =C34*M24 -> 1001042.5 | E35: IPLM | F35: =(1+F37)*F36 -> 56.1
E36: material | F36: 55
E37: Shipping | F37: 0.02
E38: Moter&Cooling | F38: 2 | G38: unit/climatizer
E39: Motojister | F39: =(1+F41)*F40 -> 117.7
E40: material | F40: 110
E41: Shipping | F41: 0.07
E42: Motormaster | F42: =(1+F44)*F43 -> 186.3
E43: material | F43: 162
E44: Shipping | F44: 0.15
E45: InfinityParts | F45: =(1+F47)*F46 -> 193.6
E46: material | F46: 176
E47: Shipping | F47: 0.1
E48: Freezpro | F48: =(1+F50)*F49 -> 187.2
E49: material | F49: 180
E50: Shipping | F50: 0.04
E51: ElectrocalKit | F51: 3 | G51: unit/climatizer
E52: Chukchuk | F52: =(1+F54)*F53 -> 21.6
E53: material | F53: 18
E54: Shipping | F54: 0.2
E55: ConduiteElec | F55: =(1+F57)*F56 -> 22
E56: material | F56: 20
E57: Shipping | F57: 0.1
E58: Proline | F58: =(1+F60)*F59 -> 24.15
E59: material | F59: 23
E60: Shipping | F60: 0.05
B65: 2. Market
B67: Cost Overview
B68: Sales Income | C68: =SUMPRODUCT(F73:I73,F71:I71) -> 4017102
B69: A&P Investiments | C69: =J75 -> 319567.59 | E69: =IF(B5="Validation","Actual S.C.R","Predict S.C.R") -> Predict S.C.R | F69: {=IF($B$5="Validation",F73/F72,INDIRECT("'Input_Q"&$B$3&"-Predict'!D29"))} -> 0.9 | G69: {=IF($B$5="Validation",G73/G72,INDIRECT("'Input_Q"&$B$3&"-Predict'!D30"))} -> 0.9 | H69: {=IF($B$5="Validation",H73/H72,INDIRECT("'Input_Q"&$B$3&"-Predict'!D31"))} -> 0.8 | I69: {=IF($B$5="Validation",I73/I72,INDIRECT("'Input_Q"&$B$3&"-Predict'!D32"))} -> 0.9
B70: Commision Total | C70: =C68*C74 -> 241026.12 | E70: Region | F70: 1 | G70: 2 | H70: 3 | I70: 4 | J70: Total
